// converted by version  [v3.0.4]
// on Thu Sep 30 10:32:05 EDT 2021

.package im/status/phonon {
	.aid 0xA0:0x0:0x0:0x8:0x20:0x0:0x3;
	.version 1.0;

	.imports {
		0xA0:0x0:0x0:0x0:0x62:0x0:0x1 1.0;		//java/lang
		0xA0:0x0:0x0:0x0:0x62:0x1:0x1 1.5;		//javacard/framework
		0xA0:0x0:0x0:0x0:0x62:0x1:0x2 1.5;		//javacard/security
		0xA0:0x0:0x0:0x0:0x62:0x2:0x1 1.4;		//javacardx/crypto
	}

	.applet {
		0xA0:0x0:0x0:0x8:0x20:0x0:0x3:0x1 PhononApplet;
	}

	.constantPool {
		// 0
		instanceFieldRef BerTag Bertlv/bertag;
		// 1
		instanceFieldRef short Bertlv/BuildLength;
		// 2
		instanceFieldRef byte[] BerTag/data;
		// 3
		instanceFieldRef byte[] Bertlv/NextTagData;
		// 4
		instanceFieldRef short BerTag/length;
		// 5
		instanceFieldRef short BerTag/nextData;
		// 6
		instanceFieldRef byte BerTag/tag;
		// 7
		instanceFieldRef 2.14 Crypto/random;
		// 8
		instanceFieldRef 2.22 Crypto/ecdh;
		// 9
		instanceFieldRef 2.11 Crypto/sha512;
		// 10
		instanceFieldRef 2.11 Crypto/sha256;
		// 11
		instanceFieldRef 3.1 Crypto/aesCbcIso9797m2;
		// 12
		instanceFieldRef 2.20 Crypto/tmpAES256;
		// 13
		instanceFieldRef 2.15 Crypto/hmacSHA512;
		// 14
		instanceFieldRef 2.23 Crypto/hmacKey;
		// 15
		instanceFieldRef byte[] Crypto/hmacBlock;
		// 16
		instanceFieldRef short PhononApplet/phononKeyIndex;
		// 17
		instanceFieldRef short PhononApplet/DeletedPhononIndex;
		// 18
		instanceFieldRef Crypto PhononApplet/crypto;
		// 19
		instanceFieldRef SECP256k1 PhononApplet/secp256k1;
		// 20
		instanceFieldRef SecureChannel PhononApplet/secureChannel;
		// 21
		instanceFieldRef byte[] PhononApplet/uid;
		// 22
		instanceFieldRef byte[] PhononApplet/savedData;
		// 23
		instanceFieldRef byte[] PhononApplet/masterSeed;
		// 24
		instanceFieldRef byte PhononApplet/masterSeedStatus;
		// 25
		instanceFieldRef Phonon2[] PhononApplet/PhononArray2;
		// 26
		instanceFieldRef short[] PhononApplet/PhononList;
		// 27
		instanceFieldRef short[] PhononApplet/SendPhononList;
		// 28
		instanceFieldRef short[] PhononApplet/DeletedPhononList;
		// 29
		instanceFieldRef short PhononApplet/PhononListCount;
		// 30
		instanceFieldRef short PhononApplet/PhononListLastSent;
		// 31
		instanceFieldRef short PhononApplet/SendPhononListCount;
		// 32
		instanceFieldRef short PhononApplet/SendPhononListLastSent;
		// 33
		instanceFieldRef boolean PhononApplet/SetReceiveList;
		// 34
		instanceFieldRef 2.19 PhononApplet/masterPublic;
		// 35
		instanceFieldRef 2.18 PhononApplet/masterPrivate;
		// 36
		instanceFieldRef 2.19 PhononApplet/parentPublicKey;
		// 37
		instanceFieldRef 2.18 PhononApplet/parentPrivateKey;
		// 38
		instanceFieldRef 2.19 PhononApplet/publicKey;
		// 39
		instanceFieldRef 2.18 PhononApplet/privateKey;
		// 40
		instanceFieldRef 2.19 PhononApplet/pinlessPublicKey;
		// 41
		instanceFieldRef 2.18 PhononApplet/pinlessPrivateKey;
		// 42
		instanceFieldRef byte[] PhononApplet/masterChainCode;
		// 43
		instanceFieldRef byte[] PhononApplet/parentChainCode;
		// 44
		instanceFieldRef byte[] PhononApplet/chainCode;
		// 45
		instanceFieldRef byte[] PhononApplet/keyPath;
		// 46
		instanceFieldRef byte[] PhononApplet/pinlessPath;
		// 47
		instanceFieldRef byte[] PhononApplet/keyUID;
		// 48
		instanceFieldRef 2.15 PhononApplet/signature;
		// 49
		instanceFieldRef byte[] PhononApplet/duplicationEncKey;
		// 50
		instanceFieldRef short PhononApplet/expectedEntropy;
		// 51
		instanceFieldRef byte[] PhononApplet/OutputData;
		// 52
		instanceFieldRef byte[] PhononApplet/OutputData2;
		// 53
		instanceFieldRef 2.16 PhononApplet/PhononKey;
		// 54
		instanceFieldRef boolean PhononApplet/DebugKeySet;
		// 55
		instanceFieldRef Bertlv[] PhononApplet/BertlvArray;
		// 56
		instanceFieldRef 1.9 PhononApplet/pin;
		// 57
		instanceFieldRef byte[] SecureChannel/CardAESIV;
		// 58
		instanceFieldRef short Phonon2/PhononPublicKeyLen;
		// 59
		instanceFieldRef byte[] Phonon2/sPhononPublicKey;
		// 60
		instanceFieldRef short Phonon2/PhononPrivateKeyLen;
		// 61
		instanceFieldRef byte[] Phonon2/sPhononPrivateKey;
		// 62
		instanceFieldRef byte Phonon2/Status;
		// 63
		instanceFieldRef byte[] PhononApplet/SetReceiveListPubKey;
		// 64
		instanceFieldRef short Phonon2/CurrencyType;
		// 65
		instanceFieldRef byte[] Phonon2/Value;
		// 66
		instanceFieldRef Crypto SECP256k1/crypto;
		// 67
		instanceFieldRef 2.22 SECP256k1/ecPointMultiplier;
		// 68
		instanceFieldRef 2.18 SECP256k1/tmpECPrivateKey;
		// 69
		instanceFieldRef short SecureChannel/preassignedPairingOffset;
		// 70
		instanceFieldRef boolean SecureChannel/mutuallyAuthenticated;
		// 71
		instanceFieldRef byte[] SecureChannel/DebugMasterPrivateKey;
		// 72
		instanceFieldRef Crypto SecureChannel/crypto;
		// 73
		instanceFieldRef SECP256k1 SecureChannel/localsecp256k1;
		// 74
		instanceFieldRef 2.16 SecureChannel/idKeypair;
		// 75
		instanceFieldRef byte[] SecureChannel/idCertificate;
		// 76
		instanceFieldRef byte SecureChannel/idCertStatus;
		// 77
		instanceFieldRef byte SecureChannel/CardidCertStatus;
		// 78
		instanceFieldRef 2.15 SecureChannel/scMac;
		// 79
		instanceFieldRef 2.15 SecureChannel/eccSig;
		// 80
		instanceFieldRef 2.20 SecureChannel/scEncKey;
		// 81
		instanceFieldRef 2.20 SecureChannel/scMacKey;
		// 82
		instanceFieldRef 2.20 SecureChannel/CardscEncKey;
		// 83
		instanceFieldRef 2.20 SecureChannel/CardscMacKey;
		// 84
		instanceFieldRef 2.16 SecureChannel/scKeypair;
		// 85
		instanceFieldRef byte[] SecureChannel/secret;
		// 86
		instanceFieldRef byte[] SecureChannel/CardsessionKey;
		// 87
		instanceFieldRef byte[] SecureChannel/pairingKeys;
		// 88
		instanceFieldRef byte SecureChannel/remainingSlots;
		// 89
		instanceFieldRef byte[] SecureChannel/SenderSalt;
		// 90
		instanceFieldRef byte[] SecureChannel/CardHash;
		// 91
		instanceFieldRef byte[] SecureChannel/CardSecret;
		// 92
		instanceFieldRef byte[] SecureChannel/pairingSecret;
		// 93
		instanceFieldRef byte[] SecureChannel/SenderidCertificate;
		// 94
		instanceFieldRef short SecureChannel/scCounter;
		// 95
		virtualMethodRef 2.11.5([BSS)V;		// update([BSS)V
		// 96
		virtualMethodRef 2.11.1([BSS[BS)S;		// doFinal([BSS[BS)S
		// 97
		staticMethodRef Crypto/add256([BS[BS[BS)S;
		// 98
		staticMethodRef 1.3.0()V;		// javacard/framework/Applet.<init>()V
		// 99
		staticMethodRef 2.14.0(B)Ljavacard/security/RandomData;;		// javacard/security/RandomData.getInstance(B)Ljavacard/security/RandomData;
			.descriptor	Ljavacard/security/RandomData;	2.14;

		// 100
		.classRef 2.16;		// javacard/security/KeyPair
		// 101
		staticMethodRef 2.16.0(BS)V;		// javacard/security/KeyPair.<init>(BS)V
		// 102
		staticMethodRef 0.0.0()V;		// java/lang/Object.<init>()V
		// 103
		.classRef Crypto;
		// 104
		.classRef Bertlv;
		// 105
		staticMethodRef Crypto/<init>()V;
		// 106
		staticMethodRef Bertlv/<init>()V;
		// 107
		.classRef PhononApplet;
		// 108
		staticMethodRef PhononApplet/<init>()V;
		// 109
		virtualMethodRef 1.3.2([BSB)V;		// register([BSB)V
		// 110
		.classRef 1.7;		// javacard/framework/ISOException
		// 111
		.classRef 0.2;		// java/lang/Exception
		// 112
		virtualMethodRef 1.10.1()[B;		// getBuffer()[B
		// 113
		virtualMethodRef SecureChannel/SetDebugKey()V;
		// 114
		staticMethodRef 2.22.0(BZ)Ljavacard/security/KeyAgreement;;		// javacard/security/KeyAgreement.getInstance(BZ)Ljavacard/security/KeyAgreement;
			.descriptor	Ljavacard/security/KeyAgreement;	2.22;

		// 115
		staticMethodRef PhononApplet/processInit(Ljavacard/framework/APDU;)V;
			.descriptor	Ljavacard/framework/APDU;	1.10;

		// 116
		virtualMethodRef 1.3.3()Z;		// selectingApplet()Z
		// 117
		staticMethodRef PhononApplet/selectApplet(Ljavacard/framework/APDU;)V;
			.descriptor	Ljavacard/framework/APDU;	1.10;

		// 118
		staticMethodRef 1.8.18()V;		// javacard/framework/JCSystem.requestObjectDeletion()V
		// 119
		virtualMethodRef SecureChannel/identifyCard(Ljavacard/framework/APDU;)V;
			.descriptor	Ljavacard/framework/APDU;	1.10;

		// 120
		virtualMethodRef SecureChannel/loadCert(Ljavacard/framework/APDU;)V;
			.descriptor	Ljavacard/framework/APDU;	1.10;

		// 121
		virtualMethodRef SecureChannel/openSecureChannel(Ljavacard/framework/APDU;)V;
			.descriptor	Ljavacard/framework/APDU;	1.10;

		// 122
		virtualMethodRef SecureChannel/mutuallyAuthenticate(Ljavacard/framework/APDU;)V;
			.descriptor	Ljavacard/framework/APDU;	1.10;

		// 123
		virtualMethodRef SecureChannel/pair(Ljavacard/framework/APDU;)V;
			.descriptor	Ljavacard/framework/APDU;	1.10;

		// 124
		staticMethodRef PhononApplet/unpair(Ljavacard/framework/APDU;)V;
			.descriptor	Ljavacard/framework/APDU;	1.10;

		// 125
		staticMethodRef PhononApplet/verifyPIN(Ljavacard/framework/APDU;)V;
			.descriptor	Ljavacard/framework/APDU;	1.10;

		// 126
		staticMethodRef PhononApplet/changePIN(Ljavacard/framework/APDU;)V;
			.descriptor	Ljavacard/framework/APDU;	1.10;

		// 127
		staticMethodRef PhononApplet/createPhonon(Ljavacard/framework/APDU;)V;
			.descriptor	Ljavacard/framework/APDU;	1.10;

		// 128
		staticMethodRef PhononApplet/SetPhononDescriptor(Ljavacard/framework/APDU;)V;
			.descriptor	Ljavacard/framework/APDU;	1.10;

		// 129
		staticMethodRef PhononApplet/ListPhonons(Ljavacard/framework/APDU;)V;
			.descriptor	Ljavacard/framework/APDU;	1.10;

		// 130
		staticMethodRef PhononApplet/GetPhononPublicKey(Ljavacard/framework/APDU;)V;
			.descriptor	Ljavacard/framework/APDU;	1.10;

		// 131
		staticMethodRef PhononApplet/DestroyPhonon(Ljavacard/framework/APDU;)V;
			.descriptor	Ljavacard/framework/APDU;	1.10;

		// 132
		staticMethodRef PhononApplet/SendPhonons(Ljavacard/framework/APDU;)V;
			.descriptor	Ljavacard/framework/APDU;	1.10;

		// 133
		staticMethodRef PhononApplet/ReceivePhonons(Ljavacard/framework/APDU;)V;
			.descriptor	Ljavacard/framework/APDU;	1.10;

		// 134
		staticMethodRef PhononApplet/SetReceivePhononList(Ljavacard/framework/APDU;)V;
			.descriptor	Ljavacard/framework/APDU;	1.10;

		// 135
		staticMethodRef PhononApplet/SetTransactionsAsComplete(Ljavacard/framework/APDU;)V;
			.descriptor	Ljavacard/framework/APDU;	1.10;

		// 136
		staticMethodRef PhononApplet/InitCardPairing(Ljavacard/framework/APDU;)V;
			.descriptor	Ljavacard/framework/APDU;	1.10;

		// 137
		staticMethodRef PhononApplet/SenderPairing(Ljavacard/framework/APDU;)V;
			.descriptor	Ljavacard/framework/APDU;	1.10;

		// 138
		staticMethodRef PhononApplet/ReceiverPairing(Ljavacard/framework/APDU;)V;
			.descriptor	Ljavacard/framework/APDU;	1.10;

		// 139
		staticMethodRef PhononApplet/FinalizeCardPairing(Ljavacard/framework/APDU;)V;
			.descriptor	Ljavacard/framework/APDU;	1.10;

		// 140
		virtualMethodRef 1.7.1()S;		// getReason()S
		// 141
		staticMethodRef PhononApplet/handleException(Ljavacard/framework/APDU;S)V;
			.descriptor	Ljavacard/framework/APDU;	1.10;

		// 142
		virtualMethodRef 2.12.1()S;		// getReason()S
		// 143
		staticMethodRef PhononApplet/shouldRespond(Ljavacard/framework/APDU;)Z;
			.descriptor	Ljavacard/framework/APDU;	1.10;

		// 144
		virtualMethodRef SecureChannel/respond(Ljavacard/framework/APDU;SS)V;
			.descriptor	Ljavacard/framework/APDU;	1.10;

		// 145
		virtualMethodRef SecureChannel/isOpen()Z;
		// 146
		virtualMethodRef 1.10.11()B;		// getCurrentState()B
		// 147
		virtualMethodRef 1.10.15()S;		// getIncomingLength()S
		// 148
		virtualMethodRef SecureChannel/SetCardidCertStatus(B)V;
		// 149
		virtualMethodRef SecureChannel/SenderloadCert([BS)V;
		// 150
		virtualMethodRef SecureChannel/GetCertStatus()B;
		// 151
		virtualMethodRef SecureChannel/GetCardCertificate([B)S;
		// 152
		virtualMethodRef Bertlv/BuildTLVStructure(BS[B[B)[B;
		// 153
		virtualMethodRef SecureChannel/SetSenderSalt([B)V;
		// 154
		virtualMethodRef 1.10.8(SS)V;		// setOutgoingAndSend(SS)V
		// 155
		.classRef SECP256k1;
		// 156
		virtualMethodRef SecureChannel/CardSenderpair([BS[B)V;
		// 157
		virtualMethodRef SecureChannel/CardGetAESIV()[B;
		// 158
		virtualMethodRef SecureChannel/CardSignSession([B)S;
		// 159
		virtualMethodRef Bertlv/LoadTag([B)S;
		// 160
		virtualMethodRef Bertlv/GetTag()B;
		// 161
		virtualMethodRef Bertlv/GetLength()S;
		// 162
		virtualMethodRef Bertlv/GetData()[B;
		// 163
		virtualMethodRef SecureChannel/GetSenderSalt()[B;
		// 164
		virtualMethodRef SecureChannel/CardVerifySession([BS)Z;
		// 165
		virtualMethodRef SecureChannel/CardVerifySignature([BS)Z;
		// 166
		virtualMethodRef 2.16.2()Ljavacard/security/PrivateKey;;		// getPrivate()Ljavacard/security/PrivateKey;
			.descriptor	Ljavacard/security/PrivateKey;	2.2;

		// 167
		.classRef 2.17;		// javacard/security/ECKey
		// 168
		virtualMethodRef SECP256k1/setCurveParameters(Ljavacard/security/ECKey;)V;
			.descriptor	Ljavacard/security/ECKey;	2.17;

		// 169
		virtualMethodRef 2.16.3()Ljavacard/security/PublicKey;;		// getPublic()Ljavacard/security/PublicKey;
			.descriptor	Ljavacard/security/PublicKey;	2.3;

		// 170
		virtualMethodRef SecureChannel/preprocessAPDU([B)S;
		// 171
		virtualMethodRef 1.9.4()Z;		// isValidated()Z
		// 172
		staticMethodRef 1.8.1()V;		// javacard/framework/JCSystem.beginTransaction()V
		// 173
		staticMethodRef Phonon2/<init>()V;
		// 174
		virtualMethodRef 2.16.1()V;		// genKeyPair()V
		// 175
		staticMethodRef SECP256k1/<init>(Lim/status/phonon/Crypto;)V;
		// 176
		.classRef BerTag;
		// 177
		staticMethodRef 1.16.1([BS[BSS)S;		// javacard/framework/Util.arrayCopy([BS[BSS)S
		// 178
		.classRef SecureChannel;
		// 179
		staticMethodRef SecureChannel/<init>(BLim/status/phonon/Crypto;Lim/status/phonon/SECP256k1;)V;
		// 180
		staticMethodRef 2.11.0(BZ)Ljavacard/security/MessageDigest;;		// javacard/security/MessageDigest.getInstance(BZ)Ljavacard/security/MessageDigest;
			.descriptor	Ljavacard/security/MessageDigest;	2.11;

		// 181
		staticMethodRef 1.8.2()V;		// javacard/framework/JCSystem.commitTransaction()V
		// 182
		virtualMethodRef SecureChannel/respond(Ljavacard/framework/APDU;[BSS)V;
			.descriptor	Ljavacard/framework/APDU;	1.10;

		// 183
		virtualMethodRef Bertlv/LoadNextTag([BS)S;
		// 184
		staticMethodRef 1.8.13(SB)[B;		// javacard/framework/JCSystem.makeTransientByteArray(SB)[B
		// 185
		virtualMethodRef SECP256k1/derivePublicKey(Ljavacard/security/ECPrivateKey;[BS)S;
			.descriptor	Ljavacard/security/ECPrivateKey;	2.18;

		// 186
		staticMethodRef 1.16.4([BS)S;		// javacard/framework/Util.getShort([BS)S
		// 187
		virtualMethodRef 2.14.1([BSS)V;		// generateData([BSS)V
		// 188
		virtualMethodRef Bertlv/LoadTagBase([BS)S;
		// 189
		staticMethodRef 1.16.0([BS[BSS)B;		// javacard/framework/Util.arrayCompare([BS[BSS)B
		// 190
		virtualMethodRef Bertlv/FindTag(B)S;
		// 191
		staticMethodRef PhononApplet/SendSelectPhononList(Ljavacard/framework/APDU;B)V;
			.descriptor	Ljavacard/framework/APDU;	1.10;

		// 192
		virtualMethodRef Bertlv/BuildTLVStructure(BSS[B)[B;
		// 193
		staticMethodRef PhononApplet/SendPhononList(Ljavacard/framework/APDU;B)V;
			.descriptor	Ljavacard/framework/APDU;	1.10;

		// 194
		virtualMethodRef Bertlv/BuildTLVStructure(BS[B)[B;
		// 195
		virtualMethodRef Bertlv/BuildTLVStructure(BSS)[B;
		// 196
		virtualMethodRef 1.9.5()V;		// reset()V
		// 197
		virtualMethodRef SecureChannel/reset()V;
		// 198
		virtualMethodRef SecureChannel/updateSecureChannelCounter()V;
		// 199
		virtualMethodRef SecureChannel/copyPublicKey([BS)S;
		// 200
		virtualMethodRef SecureChannel/getRemainingPairingSlots()B;
		// 201
		virtualMethodRef 1.10.6()S;		// setIncomingAndReceive()S
		// 202
		virtualMethodRef SecureChannel/oneShotDecrypt([B)V;
		// 203
		staticMethodRef PhononApplet/allDigits([BSS)Z;
		// 204
		virtualMethodRef SecureChannel/initSecureChannel([BS)V;
		// 205
		.classRef 1.9;		// javacard/framework/OwnerPIN
		// 206
		staticMethodRef 1.9.0(BB)V;		// javacard/framework/OwnerPIN.<init>(BB)V
		// 207
		virtualMethodRef 1.9.8([BSB)V;		// update([BSB)V
		// 208
		virtualMethodRef SecureChannel/unpair([B)V;
		// 209
		virtualMethodRef 1.9.1([BSB)Z;		// check([BSB)Z
		// 210
		virtualMethodRef 1.9.2()B;		// getTriesRemaining()B
		// 211
		staticMethodRef PhononApplet/changeUserPIN([BB)V;
		// 212
		staticMethodRef PhononApplet/changePairingSecret([BB)V;
		// 213
		virtualMethodRef SecureChannel/updatePairingSecret([BB)V;
		// 214
		staticMethodRef 3.1.0(BZ)Ljavacardx/crypto/Cipher;;		// javacardx/crypto/Cipher.getInstance(BZ)Ljavacardx/crypto/Cipher;
			.descriptor	Ljavacardx/crypto/Cipher;	3.1;

		// 215
		staticMethodRef BerTag/<init>()V;
		// 216
		.classRef Phonon2;
		// 217
		staticFieldRef byte[] SECP256k1/SECP256K1_A;
		// 218
		staticFieldRef byte[] SECP256k1/SECP256K1_B;
		// 219
		staticFieldRef byte[] SECP256k1/SECP256K1_FP;
		// 220
		staticFieldRef byte[] SECP256k1/SECP256K1_G;
		// 221
		virtualMethodRef SECP256k1/multiplyPoint(Ljavacard/security/ECPrivateKey;[BSS[BS)S;
			.descriptor	Ljavacard/security/ECPrivateKey;	2.18;

		// 222
		virtualMethodRef 2.22.1(Ljavacard/security/PrivateKey;)V;		// init(Ljavacard/security/PrivateKey;)V
			.descriptor	Ljavacard/security/PrivateKey;	2.2;

		// 223
		virtualMethodRef 2.22.3([BSS[BS)S;		// generateSecret([BSS[BS)S
		// 224
		staticMethodRef 2.13.0(BSZ)Ljavacard/security/Key;;		// javacard/security/KeyBuilder.buildKey(BSZ)Ljavacard/security/Key;
			.descriptor	Ljavacard/security/Key;	2.0;

		// 225
		.classRef 2.20;		// javacard/security/AESKey
		// 226
		staticMethodRef 1.7.1(S)V;		// javacard/framework/ISOException.throwIt(S)V
		// 227
		staticMethodRef 2.15.0(BZ)Ljavacard/security/Signature;;		// javacard/security/Signature.getInstance(BZ)Ljavacard/security/Signature;
			.descriptor	Ljavacard/security/Signature;	2.15;

		// 228
		staticMethodRef 1.16.2([BS[BSS)S;		// javacard/framework/Util.arrayCopyNonAtomic([BS[BSS)S
		// 229
		.classRef 2.23;		// javacard/security/HMACKey
		// 230
		staticMethodRef 1.16.6([BSS)S;		// javacard/framework/Util.setShort([BSS)S
		// 231
		.classRef 2.12;		// javacard/security/CryptoException
		// 232
		virtualMethodRef 3.1.4(Ljavacard/security/Key;B[BSS)V;		// init(Ljavacard/security/Key;B[BSS)V
			.descriptor	Ljavacard/security/Key;	2.0;

		// 233
		.classRef 2.19;		// javacard/security/ECPublicKey
		// 234
		virtualMethodRef 3.1.1([BSS[BS)S;		// doFinal([BSS[BS)S
		// 235
		.classRef 2.18;		// javacard/security/ECPrivateKey
		// 236
		virtualMethodRef Crypto/bip32IsHardened([BS)Z;
		// 237
		staticMethodRef Crypto/hmacSHA512([BSS[BSS[BS)V;
		// 238
		staticFieldRef byte[] SECP256k1/SECP256K1_R;
		// 239
		staticMethodRef Crypto/ucmp256([BS[BS)S;
		// 240
		staticMethodRef Crypto/addm256([BS[BS[BS[BS)V;
		// 241
		staticMethodRef Crypto/isZero256([BS)Z;
		// 242
		staticFieldRef byte[] Crypto/KEY_BITCOIN_SEED;
		// 243
		staticFieldRef byte[] Crypto/MAX_S;
		// 244
		staticFieldRef byte[] Crypto/S_SUB;
		// 245
		staticMethodRef Crypto/sub256([BS[BS[BS)S;
		// 246
		virtualMethodRef 2.15.3(Ljavacard/security/Key;B)V;		// init(Ljavacard/security/Key;B)V
			.descriptor	Ljavacard/security/Key;	2.0;

		// 247
		virtualMethodRef 2.15.5([BSS[BS)S;		// sign([BSS[BS)S
		// 248
		staticMethodRef SecureChannel/checkPairingIndexAndGetOffset(B)S;
		// 249
		staticMethodRef 1.16.3([BSSB)S;		// javacard/framework/Util.arrayFillNonAtomic([BSSB)S
		// 250
		virtualMethodRef 2.15.9([BSS[BS)S;		// signPreComputedHash([BSS[BS)S
		// 251
		staticMethodRef SecureChannel/pairStep1([B)S;
		// 252
		staticMethodRef SecureChannel/pairStep2([B)S;
		// 253
		virtualMethodRef 2.15.7([BSS[BSS)Z;		// verify([BSS[BSS)Z
		// 254
		staticMethodRef SecureChannel/verifyAESMAC([BS)Z;
		// 255
		virtualMethodRef 2.15.6([BSS)V;		// update([BSS)V
		// 256
		staticMethodRef SecureChannel/computeAESMAC(S[B)V;
		// 257
		staticMethodRef PhononApplet/resetCurveParameters()V;
	}

	.class public BerTag 0 extends 0.0 {		// extends java/lang/Object

		.fields {
			 byte[] data 0;		// [B
			 byte tag 1;		// B
			 short length 2;		// S
			 short nextData 3;		// S
		}

		.publicMethodTable 1 {
			equals(Ljava/lang/Object;)Z;
		}

		.packageMethodTable 0 {
		}

		.method public <init>()V 0 {
			.stack 1;
			.locals 0;

				L0:	aload_0;
					invokespecial 102;		// java/lang/Object.<init>()V
					return;
		}

	}

	.class public Bertlv 1 extends 0.0 {		// extends java/lang/Object

		.fields {
			 BerTag bertag 0;		// Lim/status/phonon/BerTag;
			 byte[] NextTagData 1;		// [B
			 short BuildLength 2;		// S
		}

		.publicMethodTable 1 {
			equals(Ljava/lang/Object;)Z;
			LoadNextTag(Lim/status/phonon/Bertlv;)Z;
			LoadNextTag([BS)S;
			LoadTag([B)S;
			FindTag(B)S;
			LoadTagBase([BS)S;
			GetTag()B;
			GetLength()S;
			GetData()[B;
			GetNextData([BS)[B;
			BuildTLVStructure(BS[B)[B;
			BuildTLVStructure(BSS)[B;
			BuildTLVStructure(SS[B)[B;
			BuildTLVStructure(SSS)[B;
			BuildTLVStructure(BS[B[B)[B;
			BuildTLVStructure(SS[B[B)[B;
			BuildTLVStructure(BSS[B)[B;
			GetBuildTLVLength()S;
		}

		.packageMethodTable 0 {
		}

		.method public <init>()V 0 {
			.stack 3;
			.locals 0;

				L0:	aload_0;
					invokespecial 102;		// java/lang/Object.<init>()V
					aload_0;
					new 176;		// im/status/phonon/BerTag
					dup;
					invokespecial 215;		// im/status/phonon/BerTag.<init>()V
					putfield_a 0;		// reference im/status/phonon/Bertlv.bertag
					aload_0;
					sconst_0;
					putfield_s 1;		// short im/status/phonon/Bertlv.BuildLength
					getfield_a_this 0;		// reference im/status/phonon/Bertlv.bertag
					sspush 255;
					sconst_2;
					invokestatic 184;		// javacard/framework/JCSystem.makeTransientByteArray(SB)[B
					putfield_a 2;		// reference im/status/phonon/BerTag.data
					aload_0;
					sspush 255;
					newarray 11;
					putfield_a 3;		// reference im/status/phonon/Bertlv.NextTagData
					return;
		}

		.method public LoadNextTag(Lim/status/phonon/Bertlv;)Z 1 {
			.stack 3;
			.locals 0;

				L0:	getfield_a_this 0;		// reference im/status/phonon/Bertlv.bertag
					getfield_s 4;		// short im/status/phonon/BerTag.length
					getfield_a_this 0;		// reference im/status/phonon/Bertlv.bertag
					getfield_s 5;		// short im/status/phonon/BerTag.nextData
					if_scmplt L2;
				L1:	sconst_0;
					sreturn;
				L2:	aload_1;
					getfield_a_this 0;		// reference im/status/phonon/Bertlv.bertag
					getfield_a 2;		// reference im/status/phonon/BerTag.data
					getfield_a_this 0;		// reference im/status/phonon/Bertlv.bertag
					getfield_s 5;		// short im/status/phonon/BerTag.nextData
					invokevirtual 188;		// LoadTagBase([BS)S
					pop;
					getfield_a_this 0;		// reference im/status/phonon/Bertlv.bertag
					dup;
					getfield_s 5;		// short im/status/phonon/BerTag.nextData
					aload_1;
					getfield_a 0;		// reference im/status/phonon/Bertlv.bertag
					getfield_s 5;		// short im/status/phonon/BerTag.nextData
					sadd;
					putfield_s 5;		// short im/status/phonon/BerTag.nextData
					sconst_1;
					sreturn;
		}

		.method public LoadNextTag([BS)S 2 {
			.stack 3;
			.locals 0;

				L0:	aload_0;
					aload_1;
					sload_2;
					invokevirtual 188;		// LoadTagBase([BS)S
					sreturn;
		}

		.method public LoadTag([B)S 3 {
			.stack 3;
			.locals 1;

				L0:	sconst_0;
					sstore_2;
				L1:	aload_0;
					aload_1;
					sload_2;
					invokevirtual 188;		// LoadTagBase([BS)S
					sreturn;
		}

		.method public FindTag(B)S 4 {
			.stack 4;
			.locals 4;

				L0:	getfield_a_this 0;		// reference im/status/phonon/Bertlv.bertag
					getfield_s 4;		// short im/status/phonon/BerTag.length
					sstore_2;
				L1:	sconst_0;
					sstore_3;
				L2:	goto L10;
				L3:	getfield_a_this 0;		// reference im/status/phonon/Bertlv.bertag
					getfield_a 2;		// reference im/status/phonon/BerTag.data
					sload_3;
					baload;
					sload_1;
					if_scmpne L5;
				L4:	sload_3;
					sreturn;
				L5:	sinc 3 1;
					getfield_a_this 0;		// reference im/status/phonon/Bertlv.bertag
					getfield_a 2;		// reference im/status/phonon/BerTag.data
					sload_3;
					dup;
					sconst_1;
					sadd;
					sstore_3;
					baload;
					sstore 4;
				L6:	sconst_0;
					sstore 5;
				L7:	sload 4;
					sstore 5;
					sload 5;
					ifeq L9;
				L8:	sload_3;
					sload 5;
					sadd;
					sconst_1;
					ssub;
					sstore_3;
				L9:	sinc 3 1;
				L10:	sload_3;
					sload_2;
					if_scmplt L3;
				L11:	sconst_m1;
					sreturn;
		}

		.method public LoadTagBase([BS)S 5 {
			.stack 5;
			.locals 2;

				L0:	getfield_a_this 0;		// reference im/status/phonon/Bertlv.bertag
					aload_1;
					sload_2;
					dup;
					sconst_1;
					sadd;
					sstore_2;
					baload;
					putfield_b 6;		// byte im/status/phonon/BerTag.tag
					aload_1;
					sload_2;
					dup;
					sconst_1;
					sadd;
					sstore_2;
					baload;
					sstore_3;
				L1:	sload_3;
					stableswitch L5 -127 -126 L2 L3;
				L2:	getfield_a_this 0;		// reference im/status/phonon/Bertlv.bertag
					aload_1;
					sload_2;
					baload;
					sspush 255;
					sand;
					putfield_s 4;		// short im/status/phonon/BerTag.length
					sinc 2 1;
					goto L8;
				L3:	getfield_a_this 0;		// reference im/status/phonon/Bertlv.bertag
					aload_1;
					sload_2;
					baload;
					bspush 8;
					sshl;
					putfield_s 4;		// short im/status/phonon/BerTag.length
					sinc 2 1;
					aload_1;
					sload_2;
					baload;
					sstore 4;
				L4:	getfield_a_this 0;		// reference im/status/phonon/Bertlv.bertag
					dup;
					getfield_s 4;		// short im/status/phonon/BerTag.length
					sload 4;
					sadd;
					putfield_s 4;		// short im/status/phonon/BerTag.length
					sinc 2 1;
					goto L8;
				L5:	sload_3;
					bspush 127;
					if_scmple L7;
				L6:	sspush 27012;
					invokestatic 226;		// javacard/framework/ISOException.throwIt(S)V
					sconst_0;
					sreturn;
				L7:	getfield_a_this 0;		// reference im/status/phonon/Bertlv.bertag
					sload_3;
					putfield_s 4;		// short im/status/phonon/BerTag.length
				L8:	getfield_a_this 0;		// reference im/status/phonon/Bertlv.bertag
					getfield_s 4;		// short im/status/phonon/BerTag.length
					ifeq L10;
				L9:	aload_1;
					sload_2;
					getfield_a_this 0;		// reference im/status/phonon/Bertlv.bertag
					getfield_a 2;		// reference im/status/phonon/BerTag.data
					sconst_0;
					getfield_a_this 0;		// reference im/status/phonon/Bertlv.bertag
					getfield_s 4;		// short im/status/phonon/BerTag.length
					invokestatic 228;		// javacard/framework/Util.arrayCopyNonAtomic([BS[BSS)S
					pop;
					goto L11;
				L10:	getfield_a_this 0;		// reference im/status/phonon/Bertlv.bertag
					aconst_null;
					putfield_a 2;		// reference im/status/phonon/BerTag.data
				L11:	getfield_a_this 0;		// reference im/status/phonon/Bertlv.bertag
					getfield_a_this 0;		// reference im/status/phonon/Bertlv.bertag
					getfield_s 4;		// short im/status/phonon/BerTag.length
					sload_2;
					sadd;
					putfield_s 5;		// short im/status/phonon/BerTag.nextData
					getfield_a_this 0;		// reference im/status/phonon/Bertlv.bertag
					getfield_s 4;		// short im/status/phonon/BerTag.length
					sreturn;
		}

		.method public GetTag()B 6 {
			.stack 1;
			.locals 0;

				L0:	getfield_a_this 0;		// reference im/status/phonon/Bertlv.bertag
					getfield_b 6;		// byte im/status/phonon/BerTag.tag
					sreturn;
		}

		.method public GetLength()S 7 {
			.stack 1;
			.locals 0;

				L0:	getfield_a_this 0;		// reference im/status/phonon/Bertlv.bertag
					getfield_s 4;		// short im/status/phonon/BerTag.length
					sreturn;
		}

		.method public GetData()[B 8 {
			.stack 1;
			.locals 0;

				L0:	getfield_a_this 0;		// reference im/status/phonon/Bertlv.bertag
					getfield_a 2;		// reference im/status/phonon/BerTag.data
					areturn;
		}

		.method public GetNextData([BS)[B 9 {
			.stack 6;
			.locals 0;

				L0:	aload_1;
					sload_2;
					getfield_a_this 3;		// reference im/status/phonon/Bertlv.NextTagData
					sconst_0;
					getfield_a_this 0;		// reference im/status/phonon/Bertlv.bertag
					getfield_s 4;		// short im/status/phonon/BerTag.length
					getfield_a_this 0;		// reference im/status/phonon/Bertlv.bertag
					getfield_s 5;		// short im/status/phonon/BerTag.nextData
					ssub;
					invokestatic 228;		// javacard/framework/Util.arrayCopyNonAtomic([BS[BSS)S
					pop;
					getfield_a_this 0;		// reference im/status/phonon/Bertlv.bertag
					getfield_a_this 0;		// reference im/status/phonon/Bertlv.bertag
					getfield_s 5;		// short im/status/phonon/BerTag.nextData
					getfield_a_this 0;		// reference im/status/phonon/Bertlv.bertag
					getfield_s 4;		// short im/status/phonon/BerTag.length
					sadd;
					putfield_s 5;		// short im/status/phonon/BerTag.nextData
					getfield_a_this 3;		// reference im/status/phonon/Bertlv.NextTagData
					areturn;
		}

		.method public BuildTLVStructure(BS[B)[B 10 {
			.stack 5;
			.locals 3;

				L0:	sload_2;
					sconst_2;
					sadd;
					sstore 4;
				L1:	sload_2;
					sspush 255;
					if_scmple L3;
				L2:	sinc 4 2;
				L3:	sload 4;
					sconst_2;
					invokestatic 184;		// javacard/framework/JCSystem.makeTransientByteArray(SB)[B
					astore 5;
				L4:	sconst_0;
					sstore 6;
				L5:	aload 5;
					sload 6;
					dup;
					sconst_1;
					sadd;
					sstore 6;
					sload_1;
					bastore;
					sload_2;
					sspush 255;
					if_scmple L7;
				L6:	aload 5;
					sload 6;
					dup;
					sconst_1;
					sadd;
					sstore 6;
					bspush -126;
					bastore;
					aload 5;
					sload 6;
					sload_2;
					invokestatic 230;		// javacard/framework/Util.setShort([BSS)S
					pop;
					sinc 6 2;
					goto L8;
				L7:	aload 5;
					sload 6;
					dup;
					sconst_1;
					sadd;
					sstore 6;
					sload_2;
					s2b;
					bastore;
				L8:	aload_3;
					sconst_0;
					aload 5;
					sload 6;
					sload_2;
					invokestatic 228;		// javacard/framework/Util.arrayCopyNonAtomic([BS[BSS)S
					pop;
					aload_0;
					sload 6;
					sload_2;
					sadd;
					putfield_s 1;		// short im/status/phonon/Bertlv.BuildLength
					aload 5;
					areturn;
		}

		.method public BuildTLVStructure(BSS)[B 11 {
			.stack 4;
			.locals 3;

				L0:	sconst_4;
					sstore 4;
				L1:	sload_2;
					sspush 255;
					if_scmple L3;
				L2:	sinc 4 2;
				L3:	sload 4;
					sconst_2;
					invokestatic 184;		// javacard/framework/JCSystem.makeTransientByteArray(SB)[B
					astore 5;
				L4:	sconst_0;
					sstore 6;
				L5:	aload 5;
					sload 6;
					dup;
					sconst_1;
					sadd;
					sstore 6;
					sload_1;
					bastore;
					aload 5;
					sload 6;
					dup;
					sconst_1;
					sadd;
					sstore 6;
					sload_2;
					s2b;
					bastore;
					aload 5;
					sload 6;
					sload_3;
					invokestatic 230;		// javacard/framework/Util.setShort([BSS)S
					pop;
					aload_0;
					sload 6;
					sconst_2;
					sadd;
					putfield_s 1;		// short im/status/phonon/Bertlv.BuildLength
					aload 5;
					areturn;
		}

		.method public BuildTLVStructure(SS[B)[B 12 {
			.stack 5;
			.locals 3;

				L0:	sload_2;
					sconst_3;
					sadd;
					sstore 4;
				L1:	sload_2;
					sspush 255;
					if_scmple L3;
				L2:	sinc 4 2;
				L3:	sload 4;
					sconst_2;
					invokestatic 184;		// javacard/framework/JCSystem.makeTransientByteArray(SB)[B
					astore 5;
				L4:	sconst_0;
					sstore 6;
				L5:	aload 5;
					sload 6;
					sload_1;
					invokestatic 230;		// javacard/framework/Util.setShort([BSS)S
					pop;
					sinc 6 2;
					sload_2;
					sspush 255;
					if_scmple L7;
				L6:	aload 5;
					sload 6;
					dup;
					sconst_1;
					sadd;
					sstore 6;
					bspush -126;
					bastore;
					aload 5;
					sload 6;
					sload_2;
					invokestatic 230;		// javacard/framework/Util.setShort([BSS)S
					pop;
					sinc 6 2;
					goto L8;
				L7:	aload 5;
					sload 6;
					dup;
					sconst_1;
					sadd;
					sstore 6;
					sload_2;
					s2b;
					bastore;
				L8:	aload_3;
					sconst_0;
					aload 5;
					sload 6;
					sload_2;
					invokestatic 228;		// javacard/framework/Util.arrayCopyNonAtomic([BS[BSS)S
					pop;
					aload_0;
					sload 6;
					sload_2;
					sadd;
					putfield_s 1;		// short im/status/phonon/Bertlv.BuildLength
					aload 5;
					areturn;
		}

		.method public BuildTLVStructure(SSS)[B 13 {
			.stack 3;
			.locals 3;

				L0:	sload_2;
					sconst_3;
					sadd;
					sstore 4;
				L1:	sload_2;
					sspush 255;
					if_scmple L3;
				L2:	sinc 4 2;
				L3:	sload 4;
					sconst_2;
					invokestatic 184;		// javacard/framework/JCSystem.makeTransientByteArray(SB)[B
					astore 5;
				L4:	sconst_0;
					sstore 6;
				L5:	aload 5;
					sload 6;
					sload_1;
					invokestatic 230;		// javacard/framework/Util.setShort([BSS)S
					pop;
					sinc 6 2;
					aload 5;
					sload 6;
					sload_2;
					invokestatic 230;		// javacard/framework/Util.setShort([BSS)S
					pop;
					sinc 6 2;
					aload 5;
					sload 6;
					sload_3;
					invokestatic 230;		// javacard/framework/Util.setShort([BSS)S
					pop;
					aload_0;
					sload 6;
					sconst_2;
					sadd;
					putfield_s 1;		// short im/status/phonon/Bertlv.BuildLength
					aload 5;
					areturn;
		}

		.method public BuildTLVStructure(BS[B[B)[B 14 {
			.stack 5;
			.locals 2;

				L0:	sload_2;
					sconst_2;
					sadd;
					sstore 5;
				L1:	sload_2;
					sspush 255;
					if_scmple L3;
				L2:	sinc 5 2;
				L3:	sconst_0;
					sstore 6;
				L4:	aload 4;
					sload 6;
					dup;
					sconst_1;
					sadd;
					sstore 6;
					sload_1;
					bastore;
					sload_2;
					sspush 255;
					if_scmple L6;
				L5:	aload 4;
					sload 6;
					dup;
					sconst_1;
					sadd;
					sstore 6;
					bspush -126;
					bastore;
					aload 4;
					sload 6;
					sload_2;
					invokestatic 230;		// javacard/framework/Util.setShort([BSS)S
					pop;
					sinc 6 2;
					goto L7;
				L6:	aload 4;
					sload 6;
					dup;
					sconst_1;
					sadd;
					sstore 6;
					sload_2;
					s2b;
					bastore;
				L7:	aload_3;
					sconst_0;
					aload 4;
					sload 6;
					sload_2;
					invokestatic 228;		// javacard/framework/Util.arrayCopyNonAtomic([BS[BSS)S
					pop;
					aload_0;
					sload 6;
					sload_2;
					sadd;
					putfield_s 1;		// short im/status/phonon/Bertlv.BuildLength
					aload 4;
					areturn;
		}

		.method public BuildTLVStructure(SS[B[B)[B 15 {
			.stack 5;
			.locals 2;

				L0:	sload_2;
					sconst_3;
					sadd;
					sstore 5;
				L1:	sload_2;
					sspush 255;
					if_scmple L3;
				L2:	sinc 5 2;
				L3:	sconst_0;
					sstore 6;
				L4:	aload 4;
					sload 6;
					sload_1;
					invokestatic 230;		// javacard/framework/Util.setShort([BSS)S
					pop;
					sinc 6 2;
					sload_2;
					sspush 255;
					if_scmple L6;
				L5:	aload 4;
					sload 6;
					dup;
					sconst_1;
					sadd;
					sstore 6;
					bspush -126;
					bastore;
					aload 4;
					sload 6;
					sload_2;
					invokestatic 230;		// javacard/framework/Util.setShort([BSS)S
					pop;
					sinc 6 2;
					goto L7;
				L6:	aload 4;
					sload 6;
					dup;
					sconst_1;
					sadd;
					sstore 6;
					sload_2;
					s2b;
					bastore;
				L7:	aload_3;
					sconst_0;
					aload 4;
					sload 6;
					sload_2;
					invokestatic 228;		// javacard/framework/Util.arrayCopyNonAtomic([BS[BSS)S
					pop;
					aload_0;
					sload 6;
					sload_2;
					sadd;
					putfield_s 1;		// short im/status/phonon/Bertlv.BuildLength
					aload 4;
					areturn;
		}

		.method public BuildTLVStructure(BSS[B)[B 16 {
			.stack 4;
			.locals 2;

				L0:	sconst_4;
					sstore 5;
				L1:	sload_2;
					sspush 255;
					if_scmple L3;
				L2:	sinc 5 2;
				L3:	sconst_0;
					sstore 6;
				L4:	aload 4;
					sload 6;
					dup;
					sconst_1;
					sadd;
					sstore 6;
					sload_1;
					bastore;
					aload 4;
					sload 6;
					dup;
					sconst_1;
					sadd;
					sstore 6;
					sload_2;
					s2b;
					bastore;
					aload 4;
					sload 6;
					sload_3;
					invokestatic 230;		// javacard/framework/Util.setShort([BSS)S
					pop;
					aload_0;
					sload 6;
					sconst_2;
					sadd;
					putfield_s 1;		// short im/status/phonon/Bertlv.BuildLength
					aload 4;
					areturn;
		}

		.method public GetBuildTLVLength()S 17 {
			.stack 1;
			.locals 0;

				L0:	getfield_s_this 1;		// short im/status/phonon/Bertlv.BuildLength
					sreturn;
		}

	}

	.class public Crypto 2 extends 0.0 {		// extends java/lang/Object

		.fields {
			 2.14 random 0;		// Ljavacard/security/RandomData;
			 2.22 ecdh 1;		// Ljavacard/security/KeyAgreement;
			 2.11 sha256 2;		// Ljavacard/security/MessageDigest;
			 2.11 sha512 3;		// Ljavacard/security/MessageDigest;
			 2.22 Cardecdh 4;		// Ljavacard/security/KeyAgreement;
			 2.11 Cardsha256 5;		// Ljavacard/security/MessageDigest;
			 2.11 Cardsha512 6;		// Ljavacard/security/MessageDigest;
			 3.1 aesCbcIso9797m2 7;		// Ljavacardx/crypto/Cipher;
			private 2.15 hmacSHA512 8;		// Ljavacard/security/Signature;
			private 2.23 hmacKey 9;		// Ljavacard/security/HMACKey;
			private 2.20 tmpAES256 10;		// Ljavacard/security/AESKey;
			private byte[] hmacBlock 11;		// [B
			public static final short AES_BLOCK_SIZE = 16;		// S
			static final short KEY_SECRET_SIZE = 32;		// S
			static final short KEY_PUB_SIZE = 65;		// S
			static final short KEY_DERIVATION_SCRATCH_SIZE = 37;		// S
			private static final short HMAC_OUT_SIZE = 64;		// S
			private static final byte[] MAX_S = {127,-1,-1,-1,-1,-1,-1,-1,-1,-1,-1,-1,-1,-1,-1,-1,93,87,110,115,87,-92,80,29,-33,-23,47,70,104,27,32,-96};		// [B
			private static final byte[] S_SUB = {-1,-1,-1,-1,-1,-1,-1,-1,-1,-1,-1,-1,-1,-1,-1,-2,-70,-82,-36,-26,-81,72,-96,59,-65,-46,94,-116,-48,54,65,65};		// [B
			private static final byte HMAC_IPAD = 54;		// B
			private static final byte HMAC_OPAD = 92;		// B
			private static final short HMAC_BLOCK_SIZE = 128;		// S
			private static final byte[] KEY_BITCOIN_SEED = {66,105,116,99,111,105,110,32,115,101,101,100};		// [B
		}

		.publicMethodTable 1 {
			equals(Ljava/lang/Object;)Z;
			oneShotAES(B[BSS[BS[BS)S;
		}

		.packageMethodTable 0 {
			bip32IsHardened([BS)Z;
			bip32CKDPriv([BS[BS[BS[BS)Z;
			bip32MasterFromSeed([BSS[BS)V;
			fixS([BS)S;
		}

		.method  <init>()V {
			.stack 4;
			.locals 1;

				L0:	aload_0;
					invokespecial 102;		// java/lang/Object.<init>()V
					aload_0;
					sconst_2;
					invokestatic 99;		// javacard/security/RandomData.getInstance(B)Ljavacard/security/RandomData;
					putfield_a 7;		// reference im/status/phonon/Crypto.random
					aload_0;
					sconst_3;
					sconst_0;
					invokestatic 114;		// javacard/security/KeyAgreement.getInstance(BZ)Ljavacard/security/KeyAgreement;
					putfield_a 8;		// reference im/status/phonon/Crypto.ecdh
					aload_0;
					bspush 6;
					sconst_0;
					invokestatic 180;		// javacard/security/MessageDigest.getInstance(BZ)Ljavacard/security/MessageDigest;
					putfield_a 9;		// reference im/status/phonon/Crypto.sha512
					aload_0;
					sconst_4;
					sconst_0;
					invokestatic 180;		// javacard/security/MessageDigest.getInstance(BZ)Ljavacard/security/MessageDigest;
					putfield_a 10;		// reference im/status/phonon/Crypto.sha256
					aload_0;
					bspush 23;
					sconst_0;
					invokestatic 214;		// javacardx/crypto/Cipher.getInstance(BZ)Ljavacardx/crypto/Cipher;
					putfield_a 11;		// reference im/status/phonon/Crypto.aesCbcIso9797m2
					aload_0;
					bspush 14;
					sspush 256;
					sconst_0;
					invokestatic 224;		// javacard/security/KeyBuilder.buildKey(BSZ)Ljavacard/security/Key;
					checkcast 0 225;		// T_CLASSORINTERFACE javacard/security/AESKey
					putfield_a 12;		// reference im/status/phonon/Crypto.tmpAES256
				L1:	aload_0;
					bspush 27;
					sconst_0;
					invokestatic 227;		// javacard/security/Signature.getInstance(BZ)Ljavacard/security/Signature;
					putfield_a 13;		// reference im/status/phonon/Crypto.hmacSHA512
					aload_0;
					bspush 20;
					bspush 32;
					sconst_0;
					invokestatic 224;		// javacard/security/KeyBuilder.buildKey(BSZ)Ljavacard/security/Key;
					checkcast 0 229;		// T_CLASSORINTERFACE javacard/security/HMACKey
					putfield_a 14;		// reference im/status/phonon/Crypto.hmacKey
				L2:	goto L5;
				L3:	astore_1;
				L4:	aload_0;
					aconst_null;
					putfield_a 13;		// reference im/status/phonon/Crypto.hmacSHA512
					aload_0;
					sspush 128;
					sconst_1;
					invokestatic 184;		// javacard/framework/JCSystem.makeTransientByteArray(SB)[B
					putfield_a 15;		// reference im/status/phonon/Crypto.hmacBlock
				L5:	return;
			.exceptionTable {
				// start_block end_block handler_block catch_type_index
				L1 L2 L3 231;
			}
		}

		.method public oneShotAES(B[BSS[BS[BS)S 1 {
			.stack 6;
			.locals 0;

				L0:	getfield_a_this 12;		// reference im/status/phonon/Crypto.tmpAES256
					aload 7;
					sload 8;
					invokeinterface 3 225 4;		// javacard/security/AESKey
					getfield_a_this 11;		// reference im/status/phonon/Crypto.aesCbcIso9797m2
					getfield_a_this 12;		// reference im/status/phonon/Crypto.tmpAES256
					sload_1;
					aload_2;
					sload_3;
					bspush 16;
					invokevirtual 232;		// init(Ljavacard/security/Key;B[BSS)V
					getfield_a_this 11;		// reference im/status/phonon/Crypto.aesCbcIso9797m2
					aload_2;
					sload_3;
					bspush 16;
					sadd;
					sload 4;
					aload 5;
					sload 6;
					invokevirtual 234;		// doFinal([BSS[BS)S
					sreturn;
		}

		.method  bip32IsHardened([BS)Z 128 {
			.stack 2;
			.locals 0;

				L0:	aload_1;
					sload_2;
					baload;
					bspush -128;
					sand;
					bspush -128;
					if_scmpne L2;
				L1:	sconst_1;
					sreturn;
				L2:	sconst_0;
					sreturn;
		}

		.method  bip32CKDPriv([BS[BS[BS[BS)Z 129 {
			.stack 9;
			.locals 1;

				L0:	sload 4;
					sstore 9;
				L1:	aload_0;
					aload_1;
					sload_2;
					invokevirtual 236;		// bip32IsHardened([BS)Z
					ifeq L3;
				L2:	aload_3;
					sload 9;
					dup;
					sconst_1;
					sadd;
					sstore 9;
					sconst_0;
					bastore;
					aload 5;
					sload 6;
					aload_3;
					sload 9;
					bspush 32;
					invokestatic 228;		// javacard/framework/Util.arrayCopyNonAtomic([BS[BSS)S
					sstore 9;
					goto L7;
				L3:	aload_3;
					sload 9;
					dup;
					sconst_1;
					sadd;
					sstore 9;
					aload 5;
					sload 6;
					bspush 32;
					sadd;
					bspush 32;
					sadd;
					bspush 65;
					sadd;
					sconst_1;
					ssub;
					baload;
					sconst_1;
					sand;
					ifeq L5;
				L4:	sconst_3;
					goto L6;
				L5:	sconst_2;
				L6:	bastore;
					aload 5;
					sload 6;
					bspush 32;
					sadd;
					bspush 32;
					sadd;
					sconst_1;
					sadd;
					aload_3;
					sload 9;
					bspush 32;
					invokestatic 228;		// javacard/framework/Util.arrayCopyNonAtomic([BS[BSS)S
					sstore 9;
				L7:	aload_1;
					sload_2;
					aload_3;
					sload 9;
					sconst_4;
					invokestatic 228;		// javacard/framework/Util.arrayCopyNonAtomic([BS[BSS)S
					sstore 9;
					aload_0;
					aload 5;
					sload 6;
					bspush 32;
					sadd;
					bspush 32;
					aload_3;
					sload 4;
					sload 9;
					sload 4;
					ssub;
					aload 7;
					sload 8;
					invokespecial 237;		// im/status/phonon/Crypto.hmacSHA512([BSS[BSS[BS)V
					aload_0;
					aload 7;
					sload 8;
					getstatic_a 238;		// reference im/status/phonon/SECP256k1.SECP256K1_R
					sconst_0;
					invokespecial 239;		// im/status/phonon/Crypto.ucmp256([BS[BS)S
					iflt L9;
				L8:	sconst_0;
					sreturn;
				L9:	aload_0;
					aload 7;
					sload 8;
					aload 5;
					sload 6;
					getstatic_a 238;		// reference im/status/phonon/SECP256k1.SECP256K1_R
					sconst_0;
					aload 7;
					sload 8;
					invokespecial 240;		// im/status/phonon/Crypto.addm256([BS[BS[BS[BS)V
					aload_0;
					aload 7;
					sload 8;
					invokespecial 241;		// im/status/phonon/Crypto.isZero256([BS)Z
					ifeq L11;
				L10:	sconst_0;
					sreturn;
				L11:	sconst_1;
					sreturn;
		}

		.method  bip32MasterFromSeed([BSS[BS)V 130 {
			.stack 9;
			.locals 0;

				L0:	aload_0;
					getstatic_a 242;		// reference im/status/phonon/Crypto.KEY_BITCOIN_SEED
					sconst_0;
					getstatic_a 242;		// reference im/status/phonon/Crypto.KEY_BITCOIN_SEED
					arraylength;
					aload_1;
					sload_2;
					sload_3;
					aload 4;
					sload 5;
					invokespecial 237;		// im/status/phonon/Crypto.hmacSHA512([BSS[BSS[BS)V
					return;
		}

		.method  fixS([BS)S 131 {
			.stack 7;
			.locals 2;

				L0:	aload_1;
					sload_2;
					sconst_3;
					sadd;
					baload;
					sload_2;
					sconst_5;
					sadd;
					sadd;
					sstore_3;
				L1:	sconst_0;
					sstore 4;
				L2:	aload_1;
					sload_3;
					baload;
					bspush 33;
					if_scmpne L4;
				L3:	aload_1;
					sload_3;
					sconst_2;
					sadd;
					aload_1;
					sload_3;
					sconst_1;
					sadd;
					bspush 32;
					invokestatic 228;		// javacard/framework/Util.arrayCopyNonAtomic([BS[BSS)S
					pop;
					aload_1;
					sload_3;
					bspush 32;
					bastore;
					aload_1;
					sload_2;
					sconst_1;
					sadd;
					dup2;
					baload;
					sconst_1;
					ssub;
					s2b;
					bastore;
					sconst_m1;
					sstore 4;
				L4:	sinc 3 1;
					sload 4;
					sconst_m1;
					if_scmpeq L6;
				L5:	aload_0;
					aload_1;
					sload_3;
					getstatic_a 243;		// reference im/status/phonon/Crypto.MAX_S
					sconst_0;
					invokespecial 239;		// im/status/phonon/Crypto.ucmp256([BS[BS)S
					ifle L7;
				L6:	aload_0;
					getstatic_a 244;		// reference im/status/phonon/Crypto.S_SUB
					sconst_0;
					aload_1;
					sload_3;
					aload_1;
					sload_3;
					invokespecial 245;		// im/status/phonon/Crypto.sub256([BS[BS[BS)S
					pop;
				L7:	sload 4;
					sreturn;
		}

		.method private hmacSHA512([BSS[BSS[BS)V {
			.stack 6;
			.locals 2;

				L0:	getfield_a_this 13;		// reference im/status/phonon/Crypto.hmacSHA512
					ifnull L2;
				L1:	getfield_a_this 14;		// reference im/status/phonon/Crypto.hmacKey
					aload_1;
					sload_2;
					sload_3;
					invokeinterface 4 229 4;		// javacard/security/HMACKey
					getfield_a_this 13;		// reference im/status/phonon/Crypto.hmacSHA512
					getfield_a_this 14;		// reference im/status/phonon/Crypto.hmacKey
					sconst_1;
					invokevirtual 246;		// init(Ljavacard/security/Key;B)V
					getfield_a_this 13;		// reference im/status/phonon/Crypto.hmacSHA512
					aload 4;
					sload 5;
					sload 6;
					aload 7;
					sload 8;
					invokevirtual 247;		// sign([BSS[BS)S
					pop;
					goto L16;
				L2:	sconst_0;
					sstore 9;
				L3:	goto L15;
				L4:	getfield_a_this 15;		// reference im/status/phonon/Crypto.hmacBlock
					sconst_0;
					sspush 128;
					sload 9;
					ifne L6;
				L5:	bspush 54;
					goto L7;
				L6:	bspush 92;
				L7:	invokestatic 249;		// javacard/framework/Util.arrayFillNonAtomic([BSSB)S
					pop;
					sconst_0;
					sstore 10;
				L8:	goto L10;
				L9:	getfield_a_this 15;		// reference im/status/phonon/Crypto.hmacBlock
					sload 10;
					dup2;
					baload;
					aload_1;
					sload_2;
					sload 10;
					sadd;
					baload;
					sxor;
					bastore;
					sinc 10 1;
				L10:	sload 10;
					sload_3;
					if_scmplt L9;
				L11:	getfield_a_this 9;		// reference im/status/phonon/Crypto.sha512
					getfield_a_this 15;		// reference im/status/phonon/Crypto.hmacBlock
					sconst_0;
					sspush 128;
					invokevirtual 95;		// update([BSS)V
					sload 9;
					ifne L13;
				L12:	getfield_a_this 9;		// reference im/status/phonon/Crypto.sha512
					aload 4;
					sload 5;
					sload 6;
					aload 7;
					sload 8;
					invokevirtual 96;		// doFinal([BSS[BS)S
					pop;
					goto L14;
				L13:	getfield_a_this 9;		// reference im/status/phonon/Crypto.sha512
					aload 7;
					sload 8;
					bspush 64;
					aload 7;
					sload 8;
					invokevirtual 96;		// doFinal([BSS[BS)S
					pop;
				L14:	sload 9;
					sconst_1;
					sadd;
					s2b;
					sstore 9;
				L15:	sload 9;
					sconst_2;
					if_scmplt L4;
				L16:	return;
		}

		.method private addm256([BS[BS[BS[BS)V {
			.stack 7;
			.locals 0;

				L0:	aload_0;
					aload_1;
					sload_2;
					aload_3;
					sload 4;
					aload 7;
					sload 8;
					invokespecial 97;		// im/status/phonon/Crypto.add256([BS[BS[BS)S
					ifne L2;
				L1:	aload_0;
					aload 7;
					sload 8;
					aload 5;
					sload 6;
					invokespecial 239;		// im/status/phonon/Crypto.ucmp256([BS[BS)S
					ifle L3;
				L2:	aload_0;
					aload 7;
					sload 8;
					aload 5;
					sload 6;
					aload 7;
					sload 8;
					invokespecial 245;		// im/status/phonon/Crypto.sub256([BS[BS[BS)S
					pop;
				L3:	return;
		}

		.method private ucmp256([BS[BS)S {
			.stack 3;
			.locals 3;

				L0:	sconst_0;
					sstore 7;
				L1:	goto L7;
				L2:	aload_1;
					sload_2;
					sload 7;
					sadd;
					baload;
					sspush 255;
					sand;
					sstore 5;
				L3:	aload_3;
					sload 4;
					sload 7;
					sadd;
					baload;
					sspush 255;
					sand;
					sstore 6;
				L4:	sload 5;
					sload 6;
					if_scmpeq L6;
				L5:	sload 5;
					sload 6;
					ssub;
					sreturn;
				L6:	sinc 7 1;
				L7:	sload 7;
					bspush 32;
					if_scmplt L2;
				L8:	sconst_0;
					sreturn;
		}

		.method private isZero256([BS)Z {
			.stack 3;
			.locals 2;

				L0:	sconst_1;
					sstore_3;
				L1:	sconst_0;
					sstore 4;
				L2:	goto L6;
				L3:	aload_1;
					sload_2;
					sload 4;
					sadd;
					baload;
					ifeq L5;
				L4:	sconst_0;
					sstore_3;
					goto L7;
				L5:	sinc 4 1;
				L6:	sload 4;
					bspush 32;
					if_scmplt L3;
				L7:	sload_3;
					sreturn;
		}

		.method private add256([BS[BS[BS)S {
			.stack 4;
			.locals 2;

				L0:	sconst_0;
					sstore 7;
				L1:	bspush 31;
					sstore 8;
				L2:	goto L4;
				L3:	aload_1;
					sload_2;
					sload 8;
					sadd;
					baload;
					sspush 255;
					sand;
					aload_3;
					sload 4;
					sload 8;
					sadd;
					baload;
					sspush 255;
					sand;
					sadd;
					sload 7;
					sadd;
					sstore 7;
					aload 5;
					sload 6;
					sload 8;
					sadd;
					sload 7;
					s2b;
					bastore;
					sload 7;
					bspush 8;
					sshr;
					sstore 7;
					sinc 8 -1;
				L4:	sload 8;
					ifge L3;
				L5:	sload 7;
					sreturn;
		}

		.method private sub256([BS[BS[BS)S {
			.stack 4;
			.locals 2;

				L0:	sconst_0;
					sstore 7;
				L1:	bspush 31;
					sstore 8;
				L2:	goto L7;
				L3:	aload_1;
					sload_2;
					sload 8;
					sadd;
					baload;
					sspush 255;
					sand;
					aload_3;
					sload 4;
					sload 8;
					sadd;
					baload;
					sspush 255;
					sand;
					ssub;
					sload 7;
					ssub;
					sstore 7;
					aload 5;
					sload 6;
					sload 8;
					sadd;
					sload 7;
					s2b;
					bastore;
					sload 7;
					bspush 8;
					sshr;
					ifeq L5;
				L4:	sconst_1;
					goto L6;
				L5:	sconst_0;
				L6:	sstore 7;
					sinc 8 -1;
				L7:	sload 8;
					ifge L3;
				L8:	sload 7;
					sreturn;
		}

	}

	.class public Phonon2 3 extends 0.0 {		// extends java/lang/Object

		.fields {
			 byte[] sPhononPublicKey 0;		// [B
			 byte[] Value 1;		// [B
			 byte[] sPhononPrivateKey 2;		// [B
			 short PhononPublicKeyLen 3;		// S
			 short CurrencyType 4;		// S
			 short PhononPrivateKeyLen 5;		// S
			 byte Status 6;		// B
		}

		.publicMethodTable 1 {
			equals(Ljava/lang/Object;)Z;
		}

		.packageMethodTable 0 {
		}

		.method public <init>()V 0 {
			.stack 1;
			.locals 0;

				L0:	aload_0;
					invokespecial 102;		// java/lang/Object.<init>()V
					return;
		}

	}

	.class public PhononApplet 4 extends 1.3 {		// extends javacard/framework/Applet

		.fields {
			private Crypto crypto 0;		// Lim/status/phonon/Crypto;
			private SECP256k1 secp256k1 1;		// Lim/status/phonon/SECP256k1;
			private SecureChannel secureChannel 2;		// Lim/status/phonon/SecureChannel;
			private Crypto crypto2 3;		// Lim/status/phonon/Crypto;
			private SECP256k1 secp256k12 4;		// Lim/status/phonon/SECP256k1;
			private SecureChannel secureChannel2 5;		// Lim/status/phonon/SecureChannel;
			private Crypto cardcrypto 6;		// Lim/status/phonon/Crypto;
			private byte[] uid 7;		// [B
			private byte[] savedData 8;		// [B
			private 2.19 masterPublic 9;		// Ljavacard/security/ECPublicKey;
			private 2.18 masterPrivate 10;		// Ljavacard/security/ECPrivateKey;
			private byte[] masterChainCode 11;		// [B
			private 2.19 parentPublicKey 12;		// Ljavacard/security/ECPublicKey;
			private 2.18 parentPrivateKey 13;		// Ljavacard/security/ECPrivateKey;
			private byte[] parentChainCode 14;		// [B
			private 2.19 publicKey 15;		// Ljavacard/security/ECPublicKey;
			private 2.18 privateKey 16;		// Ljavacard/security/ECPrivateKey;
			private byte[] chainCode 17;		// [B
			private 2.19 pinlessPublicKey 18;		// Ljavacard/security/ECPublicKey;
			private 2.18 pinlessPrivateKey 19;		// Ljavacard/security/ECPrivateKey;
			private byte[] keyPath 20;		// [B
			private byte[] pinlessPath 21;		// [B
			private 2.15 signature 22;		// Ljavacard/security/Signature;
			private byte[] keyUID 23;		// [B
			private byte[] masterSeed 24;		// [B
			private byte[] duplicationEncKey 25;		// [B
			private 1.9 pin 26;		// Ljavacard/framework/OwnerPIN;
			private byte[] OutputData 27;		// [B
			private byte[] OutputData2 28;		// [B
			private Phonon2[] PhononArray2 29;		// [Lim/status/phonon/Phonon2;
			 2.16 PhononKey 30;		// Ljavacard/security/KeyPair;
			private short[] PhononList 31;		// [S
			private short[] SendPhononList 32;		// [S
			private short[] DeletedPhononList 33;		// [S
			private byte[] SetReceiveListPubKey 34;		// [B
			private Bertlv[] BertlvArray 35;		// [Lim/status/phonon/Bertlv;
			private byte[] ExtendedBuffer 36;		// [B
			private byte masterSeedStatus 37;		// B
			private boolean isExtended 38;		// Z
			private short keyPathLen 39;		// S
			private short pinlessPathLen 40;		// S
			private short expectedEntropy 41;		// S
			private short phononKeyIndex 42;		// S
			private short DeletedPhononIndex 43;		// S
			private short PhononListCount 44;		// S
			private short PhononListLastSent 45;		// S
			private short SendPhononListCount 46;		// S
			private short SendPhononListLastSent 47;		// S
			private boolean SetReceiveList 48;		// Z
			private boolean DebugKeySet 49;		// Z
			public static final short PHONON_KEY_LENGTH = 256;		// S
			public static final short MAX_NUMBER_PHONONS = 256;		// S
			private static final boolean DEBUG_MODE = 0;		// Z
			private static final short EXTENDED_BUFFER_LENGTH = 16;		// S
			static final byte PHONON_STATUS_UNINITIALIZED = 0;		// B
			static final byte PHONON_STATUS_INITIALIZED = 1;		// B
			static final byte PHONON_STATUS_PERSONALIZED = 2;		// B
			static final byte PHONON_STATUS_SENT = 3;		// B
			static final byte PHONON_STATUS_DELETED = 4;		// B
			static final short APPLICATION_VERSION = 2;		// S
			static final byte CAPABILITY_SECURE_CHANNEL = 1;		// B
			static final byte CAPABILITY_KEY_MANAGEMENT = 2;		// B
			static final byte CAPABILITY_CREDENTIALS_MANAGEMENT = 4;		// B
			static final byte CAPABILITY_NDEF = 8;		// B
			static final byte APPLICATION_CAPABILITIES = 7;		// B
			static final byte INS_INIT = -2;		// B
			static final byte INS_CREATE_PHONON = 48;		// B
			static final byte INS_SET_PHONON_DESCRIPTOR = 49;		// B
			static final byte INS_LIST_PHONONS = 50;		// B
			static final byte INS_GET_PHONON_PUB_KEY = 51;		// B
			static final byte INS_DESTROY_PHONON = 52;		// B
			static final byte INS_SEND_PHONONS = 53;		// B
			static final byte INS_RECV_PHONONS = 54;		// B
			static final byte INS_SET_RECV_LIST = 55;		// B
			static final byte INS_TRANSACTION_ACK = 56;		// B
			static final byte INS_INIT_CARD_PAIRING = 80;		// B
			static final byte INS_CARD_SENDER_PAIR = 81;		// B
			static final byte INS_CARD_RECEIVER_PAIR = 82;		// B
			static final byte INS_CARD_FINALIZE = 83;		// B
			static final byte PUK_LENGTH = 12;		// B
			static final byte PUK_MAX_RETRIES = 5;		// B
			static final byte PIN_LENGTH = 6;		// B
			static final byte PIN_MAX_RETRIES = 3;		// B
			static final byte KEY_PATH_MAX_DEPTH = 10;		// B
			static final byte PAIRING_MAX_CLIENT_COUNT = 1;		// B
			static final byte UID_LENGTH = 16;		// B
			static final short SAVED_DATA_SIZE = 223;		// S
			static final short CHAIN_CODE_SIZE = 32;		// S
			static final short KEY_UID_LENGTH = 32;		// S
			static final short BIP39_SEED_SIZE = 64;		// S
			static final byte MASTERSEED_EMPTY = 0;		// B
			static final byte MASTERSEED_NOT_EXPORTABLE = 1;		// B
			static final byte MASTERSEED_EXPORTABLE = 2;		// B
			static final byte TLV_SIGNATURE_TEMPLATE = -96;		// B
			static final byte TLV_KEY_TEMPLATE = -95;		// B
			static final byte TLV_PUB_KEY = -128;		// B
			static final byte TLV_PRIV_KEY = -127;		// B
			static final byte TLV_CHAIN_CODE = -126;		// B
			static final byte TLV_SEED = -125;		// B
			static final byte TLV_SEED_STATUS = -124;		// B
			static final byte TLV_DATA = -123;		// B
			static final byte TLV_PHONON_KEY = 64;		// B
			static final byte TLV_PHONON_INDEX = 65;		// B
			static final byte TLV_APPLICATION_STATUS_TEMPLATE = -93;		// B
			static final byte TLV_PAIRING_SLOT = 3;		// B
			static final byte TLV_INT = 2;		// B
			static final byte TLV_BOOL = 1;		// B
			static final byte TLV_APPLICATION_INFO_TEMPLATE = -92;		// B
			static final byte TLV_UID = -113;		// B
			static final byte TLV_KEY_UID = -114;		// B
			static final byte TLV_CAPABILITIES = -115;		// B
			static final byte INS_VERIFY_PIN = 32;		// B
			static final byte INS_CHANGE_PIN = 33;		// B
			static final byte CHANGE_PIN_P1_USER_PIN = 0;		// B
			static final byte CHANGE_PIN_P1_PUK = 1;		// B
			static final byte CHANGE_PIN_P1_PAIRING_SECRET = 2;		// B
			static final byte TLV_SET_PHONON_DESCRIPTOR = 80;		// B
			static final byte TLV_PHONON_COLLECTION = 82;		// B
			static final byte TLV_PHONON_COLLECTION_COUNT = 83;		// B
			static final byte TLV_PHONON_PRIVATE_DESCRIPTOR = 68;		// B
			static final byte TLV_PHONON_INDEX_COUNT = 66;		// B
			static final byte TLV_PHONON_TRANSFER_PACKET = 67;		// B
			static final byte TLV_PHONON_FILTER = 96;		// B
			static final byte TLV_SET_PHONON_KEY_INDEX = 65;		// B
			static final byte TLV_PHONON_PUB_KEY_LIST = 127;		// B
			static final byte TLV_PHONON_PUBLIC_KEY = -128;		// B
			static final byte TLV_SET_PHONON_CURRENCY = -127;		// B
			static final byte TLV_SET_PHONON_VALUE = -125;		// B
			static final byte TLV_PHONON_LESS_THAN = -124;		// B
			static final byte TLV_PHONON_GREATER_THAN = -123;		// B
			static final byte LIST_FILTER_ALL = 0;		// B
			static final byte LIST_FILTER_LESS_THAN = 1;		// B
			static final byte LIST_FILTER_GREATER_THAN = 2;		// B
			static final byte LIST_FILTER_GT_AND_LT = 3;		// B
			static final byte LIST_FILTER_LAST = 3;		// B
			static final short TLV_NOT_FOUND = -1;		// S
			static final byte TLV_CARD_CERTIFICATE = -112;		// B
			static final byte TLV_SALT = -111;		// B
			static final byte TLV_AESIV = -110;		// B
			static final byte TLV_RECEIVER_SIG = -109;		// B
		}

		.publicMethodTable 7 {
			equals(Ljava/lang/Object;)Z;
			register()V;
			register([BSB)V;
			selectingApplet()Z;
			deselect()V;
			getShareableInterfaceObject(Ljavacard/framework/AID;B)Ljavacard/framework/Shareable;;
			select()Z;
			process(Ljavacard/framework/APDU;)V;
		}

		.packageMethodTable 0 {
		}

		.method public <init>()V 0 {
			.stack 6;
			.locals 1;

				L0:	aload_0;
					invokespecial 98;		// javacard/framework/Applet.<init>()V
					aload_0;
					sconst_0;
					putfield_s 16;		// short im/status/phonon/PhononApplet.phononKeyIndex
					aload_0;
					sconst_0;
					putfield_s 17;		// short im/status/phonon/PhononApplet.DeletedPhononIndex
					aload_0;
					new 103;		// im/status/phonon/Crypto
					dup;
					invokespecial 105;		// im/status/phonon/Crypto.<init>()V
					putfield_a 18;		// reference im/status/phonon/PhononApplet.crypto
					aload_0;
					new 155;		// im/status/phonon/SECP256k1
					dup;
					getfield_a_this 18;		// reference im/status/phonon/PhononApplet.crypto
					invokespecial 175;		// im/status/phonon/SECP256k1.<init>(Lim/status/phonon/Crypto;)V
					putfield_a 19;		// reference im/status/phonon/PhononApplet.secp256k1
					aload_0;
					new 178;		// im/status/phonon/SecureChannel
					dup;
					sconst_1;
					getfield_a_this 18;		// reference im/status/phonon/PhononApplet.crypto
					getfield_a_this 19;		// reference im/status/phonon/PhononApplet.secp256k1
					invokespecial 179;		// im/status/phonon/SecureChannel.<init>(BLim/status/phonon/Crypto;Lim/status/phonon/SECP256k1;)V
					putfield_a 20;		// reference im/status/phonon/PhononApplet.secureChannel
					aload_0;
					bspush 16;
					newarray 11;
					putfield_a 21;		// reference im/status/phonon/PhononApplet.uid
					getfield_a_this 18;		// reference im/status/phonon/PhononApplet.crypto
					getfield_a 7;		// reference im/status/phonon/Crypto.random
					getfield_a_this 21;		// reference im/status/phonon/PhononApplet.uid
					sconst_0;
					bspush 16;
					invokevirtual 187;		// generateData([BSS)V
					aload_0;
					sspush 223;
					newarray 11;
					putfield_a 22;		// reference im/status/phonon/PhononApplet.savedData
					aload_0;
					bspush 64;
					newarray 11;
					putfield_a 23;		// reference im/status/phonon/PhononApplet.masterSeed
					aload_0;
					sconst_0;
					putfield_b 24;		// byte im/status/phonon/PhononApplet.masterSeedStatus
					aload_0;
					sspush 256;
					anewarray 216;		// im/status/phonon/Phonon2
					putfield_a 25;		// reference im/status/phonon/PhononApplet.PhononArray2
					aload_0;
					sspush 256;
					newarray 12;
					putfield_a 26;		// reference im/status/phonon/PhononApplet.PhononList
					aload_0;
					sspush 256;
					newarray 12;
					putfield_a 27;		// reference im/status/phonon/PhononApplet.SendPhononList
					aload_0;
					sspush 256;
					newarray 12;
					putfield_a 28;		// reference im/status/phonon/PhononApplet.DeletedPhononList
					aload_0;
					sconst_0;
					putfield_s 29;		// short im/status/phonon/PhononApplet.PhononListCount
					aload_0;
					sconst_0;
					putfield_s 30;		// short im/status/phonon/PhononApplet.PhononListLastSent
					aload_0;
					sconst_0;
					putfield_s 31;		// short im/status/phonon/PhononApplet.SendPhononListCount
					aload_0;
					sconst_0;
					putfield_s 32;		// short im/status/phonon/PhononApplet.SendPhononListLastSent
					aload_0;
					sconst_0;
					putfield_b 33;		// boolean im/status/phonon/PhononApplet.SetReceiveList
					aload_0;
					bspush 11;
					sspush 256;
					sconst_0;
					invokestatic 224;		// javacard/security/KeyBuilder.buildKey(BSZ)Ljavacard/security/Key;
					checkcast 0 233;		// T_CLASSORINTERFACE javacard/security/ECPublicKey
					putfield_a 34;		// reference im/status/phonon/PhononApplet.masterPublic
					aload_0;
					bspush 12;
					sspush 256;
					sconst_0;
					invokestatic 224;		// javacard/security/KeyBuilder.buildKey(BSZ)Ljavacard/security/Key;
					checkcast 0 235;		// T_CLASSORINTERFACE javacard/security/ECPrivateKey
					putfield_a 35;		// reference im/status/phonon/PhononApplet.masterPrivate
					aload_0;
					bspush 11;
					sspush 256;
					sconst_0;
					invokestatic 224;		// javacard/security/KeyBuilder.buildKey(BSZ)Ljavacard/security/Key;
					checkcast 0 233;		// T_CLASSORINTERFACE javacard/security/ECPublicKey
					putfield_a 36;		// reference im/status/phonon/PhononApplet.parentPublicKey
					aload_0;
					bspush 12;
					sspush 256;
					sconst_0;
					invokestatic 224;		// javacard/security/KeyBuilder.buildKey(BSZ)Ljavacard/security/Key;
					checkcast 0 235;		// T_CLASSORINTERFACE javacard/security/ECPrivateKey
					putfield_a 37;		// reference im/status/phonon/PhononApplet.parentPrivateKey
					aload_0;
					bspush 11;
					sspush 256;
					sconst_0;
					invokestatic 224;		// javacard/security/KeyBuilder.buildKey(BSZ)Ljavacard/security/Key;
					checkcast 0 233;		// T_CLASSORINTERFACE javacard/security/ECPublicKey
					putfield_a 38;		// reference im/status/phonon/PhononApplet.publicKey
					aload_0;
					bspush 12;
					sspush 256;
					sconst_0;
					invokestatic 224;		// javacard/security/KeyBuilder.buildKey(BSZ)Ljavacard/security/Key;
					checkcast 0 235;		// T_CLASSORINTERFACE javacard/security/ECPrivateKey
					putfield_a 39;		// reference im/status/phonon/PhononApplet.privateKey
					aload_0;
					bspush 11;
					sspush 256;
					sconst_0;
					invokestatic 224;		// javacard/security/KeyBuilder.buildKey(BSZ)Ljavacard/security/Key;
					checkcast 0 233;		// T_CLASSORINTERFACE javacard/security/ECPublicKey
					putfield_a 40;		// reference im/status/phonon/PhononApplet.pinlessPublicKey
					aload_0;
					bspush 12;
					sspush 256;
					sconst_0;
					invokestatic 224;		// javacard/security/KeyBuilder.buildKey(BSZ)Ljavacard/security/Key;
					checkcast 0 235;		// T_CLASSORINTERFACE javacard/security/ECPrivateKey
					putfield_a 41;		// reference im/status/phonon/PhononApplet.pinlessPrivateKey
					aload_0;
					bspush 32;
					newarray 11;
					putfield_a 42;		// reference im/status/phonon/PhononApplet.masterChainCode
					aload_0;
					bspush 32;
					newarray 11;
					putfield_a 43;		// reference im/status/phonon/PhononApplet.parentChainCode
					aload_0;
					bspush 32;
					newarray 11;
					putfield_a 44;		// reference im/status/phonon/PhononApplet.chainCode
					aload_0;
					bspush 40;
					newarray 11;
					putfield_a 45;		// reference im/status/phonon/PhononApplet.keyPath
					aload_0;
					bspush 40;
					newarray 11;
					putfield_a 46;		// reference im/status/phonon/PhononApplet.pinlessPath
					aload_0;
					bspush 32;
					newarray 11;
					putfield_a 47;		// reference im/status/phonon/PhononApplet.keyUID
					aload_0;
					invokespecial 257;		// im/status/phonon/PhononApplet.resetCurveParameters()V
					aload_0;
					bspush 33;
					sconst_0;
					invokestatic 227;		// javacard/security/Signature.getInstance(BZ)Ljavacard/security/Signature;
					putfield_a 48;		// reference im/status/phonon/PhononApplet.signature
					aload_0;
					bspush 32;
					newarray 11;
					putfield_a 49;		// reference im/status/phonon/PhononApplet.duplicationEncKey
					aload_0;
					sconst_m1;
					putfield_s 50;		// short im/status/phonon/PhononApplet.expectedEntropy
					aload_0;
					sspush 255;
					sconst_1;
					invokestatic 184;		// javacard/framework/JCSystem.makeTransientByteArray(SB)[B
					putfield_a 51;		// reference im/status/phonon/PhononApplet.OutputData
					aload_0;
					sspush 255;
					sconst_1;
					invokestatic 184;		// javacard/framework/JCSystem.makeTransientByteArray(SB)[B
					putfield_a 52;		// reference im/status/phonon/PhononApplet.OutputData2
					aload_0;
					new 100;		// javacard/security/KeyPair
					dup;
					sconst_5;
					sspush 256;
					invokespecial 101;		// javacard/security/KeyPair.<init>(BS)V
					putfield_a 53;		// reference im/status/phonon/PhononApplet.PhononKey
					aload_0;
					sconst_0;
					putfield_b 54;		// boolean im/status/phonon/PhononApplet.DebugKeySet
					aload_0;
					sconst_5;
					anewarray 104;		// im/status/phonon/Bertlv
					putfield_a 55;		// reference im/status/phonon/PhononApplet.BertlvArray
					sconst_0;
					sstore_1;
				L1:	goto L3;
				L2:	getfield_a_this 55;		// reference im/status/phonon/PhononApplet.BertlvArray
					sload_1;
					new 104;		// im/status/phonon/Bertlv
					dup;
					invokespecial 106;		// im/status/phonon/Bertlv.<init>()V
					aastore;
					sinc 1 1;
				L3:	sload_1;
					sconst_5;
					if_scmplt L2;
				L4:	return;
		}

		.method public static install([BSB)V 1 {
			.stack 5;
			.locals 0;

				L0:	new 107;		// im/status/phonon/PhononApplet
					dup;
					invokespecial 108;		// im/status/phonon/PhononApplet.<init>()V
					aload_0;
					sload_1;
					sconst_1;
					sadd;
					aload_0;
					sload_1;
					baload;
					invokevirtual 109;		// register([BSB)V
					return;
		}

		.method public process(Ljavacard/framework/APDU;)V 7 {
			.stack 4;
			.locals 2;

			.descriptor	Ljavacard/framework/APDU;	1.10;

				L0:	aload_1;
					invokevirtual 112;		// getBuffer()[B
					astore_2;
				L1:	getfield_b_this 54;		// boolean im/status/phonon/PhononApplet.DebugKeySet
					ifne L3;
				L2:	getfield_a_this 20;		// reference im/status/phonon/PhononApplet.secureChannel
					invokevirtual 113;		// SetDebugKey()V
					aload_0;
					sconst_1;
					putfield_b 54;		// boolean im/status/phonon/PhononApplet.DebugKeySet
				L3:	aload_2;
					sconst_1;
					baload;
					bspush 20;
					if_scmpeq L7;
				L4:	aload_2;
					sconst_1;
					baload;
					bspush 21;
					if_scmpeq L7;
				L5:	getfield_a_this 56;		// reference im/status/phonon/PhononApplet.pin
					ifnonnull L7;
				L6:	aload_0;
					aload_1;
					invokespecial 115;		// im/status/phonon/PhononApplet.processInit(Ljavacard/framework/APDU;)V
					return;
				L7:	aload_0;
					invokevirtual 116;		// selectingApplet()Z
					ifeq L9;
				L8:	aload_0;
					aload_1;
					invokespecial 117;		// im/status/phonon/PhononApplet.selectApplet(Ljavacard/framework/APDU;)V
					invokestatic 118;		// javacard/framework/JCSystem.requestObjectDeletion()V
					return;
				L9:	aload_2;
					sconst_1;
					baload;
					slookupswitch L31 21 16 L12 17 L13 18 L14 19 L15 20 L10 21 L11 32 L16 33 L17 48 L18 49 L19 50 L20 51 L21 52 L22 53 L23 54 L24 55 L25 56 L26 80 L27 81 L28 82 L29 83 L30;
				L10:	getfield_a_this 20;		// reference im/status/phonon/PhononApplet.secureChannel
					aload_1;
					invokevirtual 119;		// identifyCard(Ljavacard/framework/APDU;)V
					goto_w L41;
				L11:	getfield_a_this 20;		// reference im/status/phonon/PhononApplet.secureChannel
					aload_1;
					invokevirtual 120;		// loadCert(Ljavacard/framework/APDU;)V
					goto_w L41;
				L12:	getfield_a_this 20;		// reference im/status/phonon/PhononApplet.secureChannel
					aload_1;
					invokevirtual 121;		// openSecureChannel(Ljavacard/framework/APDU;)V
					goto_w L41;
				L13:	getfield_a_this 20;		// reference im/status/phonon/PhononApplet.secureChannel
					aload_1;
					invokevirtual 122;		// mutuallyAuthenticate(Ljavacard/framework/APDU;)V
					goto_w L41;
				L14:	getfield_a_this 20;		// reference im/status/phonon/PhononApplet.secureChannel
					aload_1;
					invokevirtual 123;		// pair(Ljavacard/framework/APDU;)V
					goto_w L41;
				L15:	aload_0;
					aload_1;
					invokespecial 124;		// im/status/phonon/PhononApplet.unpair(Ljavacard/framework/APDU;)V
					goto_w L41;
				L16:	aload_0;
					aload_1;
					invokespecial 125;		// im/status/phonon/PhononApplet.verifyPIN(Ljavacard/framework/APDU;)V
					goto_w L41;
				L17:	aload_0;
					aload_1;
					invokespecial 126;		// im/status/phonon/PhononApplet.changePIN(Ljavacard/framework/APDU;)V
					goto_w L41;
				L18:	aload_0;
					aload_1;
					invokespecial 127;		// im/status/phonon/PhononApplet.createPhonon(Ljavacard/framework/APDU;)V
					goto_w L41;
				L19:	aload_0;
					aload_1;
					invokespecial 128;		// im/status/phonon/PhononApplet.SetPhononDescriptor(Ljavacard/framework/APDU;)V
					goto L41;
				L20:	aload_0;
					aload_1;
					invokespecial 129;		// im/status/phonon/PhononApplet.ListPhonons(Ljavacard/framework/APDU;)V
					invokestatic 118;		// javacard/framework/JCSystem.requestObjectDeletion()V
					goto L41;
				L21:	aload_0;
					aload_1;
					invokespecial 130;		// im/status/phonon/PhononApplet.GetPhononPublicKey(Ljavacard/framework/APDU;)V
					goto L41;
				L22:	aload_0;
					aload_1;
					invokespecial 131;		// im/status/phonon/PhononApplet.DestroyPhonon(Ljavacard/framework/APDU;)V
					goto L41;
				L23:	aload_0;
					aload_1;
					invokespecial 132;		// im/status/phonon/PhononApplet.SendPhonons(Ljavacard/framework/APDU;)V
					goto L41;
				L24:	aload_0;
					aload_1;
					invokespecial 133;		// im/status/phonon/PhononApplet.ReceivePhonons(Ljavacard/framework/APDU;)V
					goto L41;
				L25:	aload_0;
					aload_1;
					invokespecial 134;		// im/status/phonon/PhononApplet.SetReceivePhononList(Ljavacard/framework/APDU;)V
					goto L41;
				L26:	aload_0;
					aload_1;
					invokespecial 135;		// im/status/phonon/PhononApplet.SetTransactionsAsComplete(Ljavacard/framework/APDU;)V
					goto L41;
				L27:	aload_0;
					aload_1;
					invokespecial 136;		// im/status/phonon/PhononApplet.InitCardPairing(Ljavacard/framework/APDU;)V
					goto L41;
				L28:	aload_0;
					aload_1;
					invokespecial 137;		// im/status/phonon/PhononApplet.SenderPairing(Ljavacard/framework/APDU;)V
					goto L41;
				L29:	aload_0;
					aload_1;
					invokespecial 138;		// im/status/phonon/PhononApplet.ReceiverPairing(Ljavacard/framework/APDU;)V
					goto L41;
				L30:	aload_0;
					aload_1;
					invokespecial 139;		// im/status/phonon/PhononApplet.FinalizeCardPairing(Ljavacard/framework/APDU;)V
				L31:	sspush 27904;
					invokestatic 226;		// javacard/framework/ISOException.throwIt(S)V
				L32:	goto L41;
				L33:	astore_3;
				L34:	aload_0;
					aload_1;
					aload_3;
					invokevirtual 140;		// getReason()S
					invokespecial 141;		// im/status/phonon/PhononApplet.handleException(Ljavacard/framework/APDU;S)V
				L35:	goto L41;
				L36:	astore_3;
				L37:	aload_0;
					aload_1;
					sspush 28416;
					aload_3;
					invokevirtual 142;		// getReason()S
					sor;
					invokespecial 141;		// im/status/phonon/PhononApplet.handleException(Ljavacard/framework/APDU;S)V
				L38:	goto L41;
				L39:	astore_3;
				L40:	aload_0;
					aload_1;
					sspush 28416;
					invokespecial 141;		// im/status/phonon/PhononApplet.handleException(Ljavacard/framework/APDU;S)V
				L41:	aload_0;
					aload_1;
					invokespecial 143;		// im/status/phonon/PhononApplet.shouldRespond(Ljavacard/framework/APDU;)Z
					ifeq L43;
				L42:	getfield_a_this 20;		// reference im/status/phonon/PhononApplet.secureChannel
					aload_1;
					sconst_0;
					sspush -28672;
					invokevirtual 144;		// respond(Ljavacard/framework/APDU;SS)V
				L43:	return;
			.exceptionTable {
				// start_block end_block handler_block catch_type_index
				L9 L32 L33 110;
				L9 L32 L36 231;
				L9 L32 L39 111;
			}
		}

		.method private handleException(Ljavacard/framework/APDU;S)V {
			.stack 4;
			.locals 0;

			.descriptor	Ljavacard/framework/APDU;	1.10;

				L0:	aload_0;
					aload_1;
					invokespecial 143;		// im/status/phonon/PhononApplet.shouldRespond(Ljavacard/framework/APDU;)Z
					ifeq L3;
				L1:	sload_2;
					sspush 27010;
					if_scmpeq L3;
				L2:	getfield_a_this 20;		// reference im/status/phonon/PhononApplet.secureChannel
					aload_1;
					sconst_0;
					sload_2;
					invokevirtual 144;		// respond(Ljavacard/framework/APDU;SS)V
					goto L4;
				L3:	sload_2;
					invokestatic 226;		// javacard/framework/ISOException.throwIt(S)V
				L4:	return;
		}

		.method private shouldRespond(Ljavacard/framework/APDU;)Z {
			.stack 2;
			.locals 0;

			.descriptor	Ljavacard/framework/APDU;	1.10;

				L0:	getfield_a_this 20;		// reference im/status/phonon/PhononApplet.secureChannel
					invokevirtual 145;		// isOpen()Z
					ifeq L3;
				L1:	aload_1;
					invokevirtual 146;		// getCurrentState()B
					bspush 6;
					if_scmpeq L3;
				L2:	sconst_1;
					sreturn;
				L3:	sconst_0;
					sreturn;
		}

		.method private InitCardPairing(Ljavacard/framework/APDU;)V {
			.stack 5;
			.locals 12;

			.descriptor	Ljavacard/framework/APDU;	1.10;

				L0:	aload_1;
					invokevirtual 112;		// getBuffer()[B
					astore_2;
				L1:	aload_1;
					invokevirtual 147;		// getIncomingLength()S
					sstore_3;
				L2:	aload_2;
					astore 4;
				L3:	sconst_5;
					sstore 5;
				L4:	aload 4;
					sload 5;
					baload;
					bspush -112;
					if_scmpeq L6;
				L5:	getfield_a_this 20;		// reference im/status/phonon/PhononApplet.secureChannel
					aload_1;
					sconst_0;
					sspush 27264;
					invokevirtual 144;		// respond(Ljavacard/framework/APDU;SS)V
					return;
				L6:	sinc 5 1;
					aload 4;
					sload 5;
					baload;
					sspush 255;
					sand;
					sstore 6;
				L7:	sinc 5 1;
					aload 4;
					sload 5;
					getfield_a_this 51;		// reference im/status/phonon/PhononApplet.OutputData
					sconst_0;
					sload 6;
					invokestatic 228;		// javacard/framework/Util.arrayCopyNonAtomic([BS[BSS)S
					pop;
					getfield_a_this 20;		// reference im/status/phonon/PhononApplet.secureChannel
					sconst_0;
					invokevirtual 148;		// SetCardidCertStatus(B)V
					getfield_a_this 20;		// reference im/status/phonon/PhononApplet.secureChannel
					getfield_a_this 51;		// reference im/status/phonon/PhononApplet.OutputData
					sload 6;
					invokevirtual 149;		// SenderloadCert([BS)V
					getfield_a_this 20;		// reference im/status/phonon/PhononApplet.secureChannel
					invokevirtual 150;		// GetCertStatus()B
					sstore 7;
				L8:	sload 7;
					ifne L10;
				L9:	sspush 27014;
					invokestatic 226;		// javacard/framework/ISOException.throwIt(S)V
				L10:	sconst_0;
					sstore 8;
				L11:	aload_1;
					invokevirtual 112;		// getBuffer()[B
					astore 9;
				L12:	getfield_a_this 20;		// reference im/status/phonon/PhononApplet.secureChannel
					getfield_a_this 51;		// reference im/status/phonon/PhononApplet.OutputData
					invokevirtual 151;		// GetCardCertificate([B)S
					sstore 10;
				L13:	getfield_a_this 55;		// reference im/status/phonon/PhononApplet.BertlvArray
					sconst_0;
					aaload;
					astore 11;
				L14:	aload 11;
					bspush -112;
					sload 10;
					getfield_a_this 51;		// reference im/status/phonon/PhononApplet.OutputData
					getfield_a_this 52;		// reference im/status/phonon/PhononApplet.OutputData2
					invokevirtual 152;		// BuildTLVStructure(BS[B[B)[B
					pop;
					getfield_a_this 52;		// reference im/status/phonon/PhononApplet.OutputData2
					sconst_0;
					aload 9;
					sload 8;
					aload 11;
					getfield_s 1;		// short im/status/phonon/Bertlv.BuildLength
					invokestatic 228;		// javacard/framework/Util.arrayCopyNonAtomic([BS[BSS)S
					pop;
					sload 8;
					aload 11;
					getfield_s 1;		// short im/status/phonon/Bertlv.BuildLength
					sadd;
					sstore 8;
					bspush 32;
					newarray 11;
					astore 12;
				L15:	aload 12;
					sconst_0;
					bspush 32;
					sconst_1;
					invokestatic 249;		// javacard/framework/Util.arrayFillNonAtomic([BSSB)S
					pop;
					getfield_a_this 20;		// reference im/status/phonon/PhononApplet.secureChannel
					aload 12;
					invokevirtual 153;		// SetSenderSalt([B)V
					getfield_a_this 55;		// reference im/status/phonon/PhononApplet.BertlvArray
					sconst_0;
					aaload;
					astore 13;
				L16:	aload 13;
					bspush -111;
					bspush 32;
					aload 12;
					getfield_a_this 52;		// reference im/status/phonon/PhononApplet.OutputData2
					invokevirtual 152;		// BuildTLVStructure(BS[B[B)[B
					pop;
					getfield_a_this 52;		// reference im/status/phonon/PhononApplet.OutputData2
					sconst_0;
					aload 9;
					sload 8;
					aload 13;
					getfield_s 1;		// short im/status/phonon/Bertlv.BuildLength
					invokestatic 228;		// javacard/framework/Util.arrayCopyNonAtomic([BS[BSS)S
					pop;
					sload 8;
					aload 13;
					getfield_s 1;		// short im/status/phonon/Bertlv.BuildLength
					sadd;
					sstore 8;
					aload_1;
					sconst_0;
					sload 8;
					invokevirtual 154;		// setOutgoingAndSend(SS)V
					return;
		}

		.method private SenderPairing(Ljavacard/framework/APDU;)V {
			.stack 5;
			.locals 13;

			.descriptor	Ljavacard/framework/APDU;	1.10;

				L0:	aload_1;
					invokevirtual 112;		// getBuffer()[B
					astore_2;
				L1:	aload_1;
					invokevirtual 147;		// getIncomingLength()S
					sstore_3;
				L2:	aload_2;
					astore 4;
				L3:	sconst_5;
					sstore 5;
				L4:	aload 4;
					sload 5;
					baload;
					bspush -112;
					if_scmpeq L6;
				L5:	getfield_a_this 20;		// reference im/status/phonon/PhononApplet.secureChannel
					aload_1;
					sconst_0;
					sspush 27264;
					invokevirtual 144;		// respond(Ljavacard/framework/APDU;SS)V
					return;
				L6:	sinc 5 1;
					aload 4;
					sload 5;
					baload;
					sspush 255;
					sand;
					sstore 6;
				L7:	sinc 5 1;
					aload 4;
					sload 5;
					getfield_a_this 51;		// reference im/status/phonon/PhononApplet.OutputData
					sconst_0;
					sload 6;
					invokestatic 228;		// javacard/framework/Util.arrayCopyNonAtomic([BS[BSS)S
					pop;
					getfield_a_this 20;		// reference im/status/phonon/PhononApplet.secureChannel
					sconst_0;
					invokevirtual 148;		// SetCardidCertStatus(B)V
					getfield_a_this 20;		// reference im/status/phonon/PhononApplet.secureChannel
					getfield_a_this 51;		// reference im/status/phonon/PhononApplet.OutputData
					sload 6;
					invokevirtual 149;		// SenderloadCert([BS)V
					sload 5;
					sload 6;
					sadd;
					sstore 5;
					aload 4;
					sload 5;
					baload;
					bspush -111;
					if_scmpeq L9;
				L8:	getfield_a_this 20;		// reference im/status/phonon/PhononApplet.secureChannel
					aload_1;
					sconst_0;
					sspush 27264;
					invokevirtual 144;		// respond(Ljavacard/framework/APDU;SS)V
					return;
				L9:	sinc 5 1;
					aload 4;
					sload 5;
					baload;
					sstore 7;
				L10:	sinc 5 1;
					sload 7;
					sconst_2;
					invokestatic 184;		// javacard/framework/JCSystem.makeTransientByteArray(SB)[B
					astore 8;
				L11:	aload 4;
					sload 5;
					aload 8;
					sconst_0;
					sload 7;
					invokestatic 228;		// javacard/framework/Util.arrayCopyNonAtomic([BS[BSS)S
					pop;
					bspush 32;
					newarray 11;
					astore 9;
				L12:	aload 9;
					sconst_0;
					bspush 32;
					sconst_2;
					invokestatic 249;		// javacard/framework/Util.arrayFillNonAtomic([BSSB)S
					pop;
					sconst_0;
					sstore 10;
				L13:	getfield_a_this 20;		// reference im/status/phonon/PhononApplet.secureChannel
					getfield_a 57;		// reference im/status/phonon/SecureChannel.CardAESIV
					sconst_0;
					bspush 16;
					sconst_3;
					invokestatic 249;		// javacard/framework/Util.arrayFillNonAtomic([BSSB)S
					pop;
					getfield_a_this 20;		// reference im/status/phonon/PhononApplet.secureChannel
					aload 8;
					sload 7;
					aload 9;
					invokevirtual 156;		// CardSenderpair([BS[B)V
					getfield_a_this 55;		// reference im/status/phonon/PhononApplet.BertlvArray
					sconst_0;
					aaload;
					astore 11;
				L14:	aload 11;
					bspush -111;
					bspush 32;
					aload 9;
					getfield_a_this 52;		// reference im/status/phonon/PhononApplet.OutputData2
					invokevirtual 152;		// BuildTLVStructure(BS[B[B)[B
					pop;
					getfield_a_this 52;		// reference im/status/phonon/PhononApplet.OutputData2
					sconst_0;
					aload_2;
					sload 10;
					aload 11;
					getfield_s 1;		// short im/status/phonon/Bertlv.BuildLength
					invokestatic 228;		// javacard/framework/Util.arrayCopyNonAtomic([BS[BSS)S
					pop;
					sload 10;
					aload 11;
					getfield_s 1;		// short im/status/phonon/Bertlv.BuildLength
					sadd;
					sstore 10;
					getfield_a_this 55;		// reference im/status/phonon/PhononApplet.BertlvArray
					sconst_0;
					aaload;
					astore 12;
				L15:	aload 12;
					bspush -110;
					bspush 16;
					getfield_a_this 20;		// reference im/status/phonon/PhononApplet.secureChannel
					invokevirtual 157;		// CardGetAESIV()[B
					getfield_a_this 52;		// reference im/status/phonon/PhononApplet.OutputData2
					invokevirtual 152;		// BuildTLVStructure(BS[B[B)[B
					pop;
					getfield_a_this 52;		// reference im/status/phonon/PhononApplet.OutputData2
					sconst_0;
					aload_2;
					sload 10;
					aload 12;
					getfield_s 1;		// short im/status/phonon/Bertlv.BuildLength
					invokestatic 228;		// javacard/framework/Util.arrayCopyNonAtomic([BS[BSS)S
					pop;
					sload 10;
					aload 12;
					getfield_s 1;		// short im/status/phonon/Bertlv.BuildLength
					sadd;
					sstore 10;
					getfield_a_this 51;		// reference im/status/phonon/PhononApplet.OutputData
					sconst_0;
					getfield_a_this 51;		// reference im/status/phonon/PhononApplet.OutputData
					arraylength;
					sconst_0;
					invokestatic 249;		// javacard/framework/Util.arrayFillNonAtomic([BSSB)S
					pop;
					getfield_a_this 20;		// reference im/status/phonon/PhononApplet.secureChannel
					getfield_a_this 51;		// reference im/status/phonon/PhononApplet.OutputData
					invokevirtual 158;		// CardSignSession([B)S
					sstore 13;
				L16:	getfield_a_this 55;		// reference im/status/phonon/PhononApplet.BertlvArray
					sconst_0;
					aaload;
					astore 14;
				L17:	aload 14;
					bspush -109;
					sload 13;
					getfield_a_this 51;		// reference im/status/phonon/PhononApplet.OutputData
					getfield_a_this 52;		// reference im/status/phonon/PhononApplet.OutputData2
					invokevirtual 152;		// BuildTLVStructure(BS[B[B)[B
					pop;
					getfield_a_this 52;		// reference im/status/phonon/PhononApplet.OutputData2
					sconst_0;
					aload_2;
					sload 10;
					aload 14;
					getfield_s 1;		// short im/status/phonon/Bertlv.BuildLength
					invokestatic 228;		// javacard/framework/Util.arrayCopyNonAtomic([BS[BSS)S
					pop;
					sload 10;
					aload 14;
					getfield_s 1;		// short im/status/phonon/Bertlv.BuildLength
					sadd;
					sstore 10;
					aload_1;
					sconst_0;
					sload 10;
					invokevirtual 154;		// setOutgoingAndSend(SS)V
					return;
		}

		.method private ReceiverPairing(Ljavacard/framework/APDU;)V {
			.stack 5;
			.locals 11;

			.descriptor	Ljavacard/framework/APDU;	1.10;

				L0:	aload_1;
					invokevirtual 112;		// getBuffer()[B
					astore_2;
				L1:	aload_1;
					invokevirtual 147;		// getIncomingLength()S
					sstore_3;
				L2:	getfield_a_this 55;		// reference im/status/phonon/PhononApplet.BertlvArray
					sconst_0;
					aaload;
					astore 4;
				L3:	getfield_a_this 51;		// reference im/status/phonon/PhononApplet.OutputData
					astore 5;
				L4:	aload_2;
					sconst_5;
					aload 5;
					sconst_0;
					sload_3;
					invokestatic 228;		// javacard/framework/Util.arrayCopyNonAtomic([BS[BSS)S
					pop;
					aload 4;
					aload 5;
					invokevirtual 159;		// LoadTag([B)S
					pop;
					aload 4;
					invokevirtual 160;		// GetTag()B
					bspush -111;
					if_scmpeq L6;
				L5:	sspush 27264;
					invokestatic 226;		// javacard/framework/ISOException.throwIt(S)V
					return;
				L6:	aload 4;
					invokevirtual 161;		// GetLength()S
					newarray 11;
					astore 6;
				L7:	aload 4;
					invokevirtual 162;		// GetData()[B
					sconst_0;
					aload 6;
					sconst_0;
					aload 4;
					invokevirtual 161;		// GetLength()S
					invokestatic 228;		// javacard/framework/Util.arrayCopyNonAtomic([BS[BSS)S
					pop;
					getfield_a_this 55;		// reference im/status/phonon/PhononApplet.BertlvArray
					sconst_0;
					aaload;
					astore 7;
				L8:	aload 4;
					invokevirtual 161;		// GetLength()S
					sconst_2;
					sadd;
					sstore 8;
				L9:	aload 7;
					aload 5;
					sload 8;
					invokevirtual 188;		// LoadTagBase([BS)S
					pop;
					aload 7;
					invokevirtual 160;		// GetTag()B
					bspush -110;
					if_scmpne L11;
				L10:	aload 7;
					invokevirtual 161;		// GetLength()S
					bspush 16;
					if_scmpeq L12;
				L11:	sspush 27264;
					invokestatic 226;		// javacard/framework/ISOException.throwIt(S)V
					return;
				L12:	aload 7;
					invokevirtual 162;		// GetData()[B
					sconst_0;
					getfield_a_this 20;		// reference im/status/phonon/PhononApplet.secureChannel
					getfield_a 57;		// reference im/status/phonon/SecureChannel.CardAESIV
					sconst_0;
					aload 7;
					invokevirtual 161;		// GetLength()S
					invokestatic 228;		// javacard/framework/Util.arrayCopyNonAtomic([BS[BSS)S
					pop;
					sload 8;
					aload 7;
					invokevirtual 161;		// GetLength()S
					sconst_2;
					sadd;
					sadd;
					sstore 8;
					getfield_a_this 55;		// reference im/status/phonon/PhononApplet.BertlvArray
					sconst_0;
					aaload;
					astore 9;
				L13:	aload 9;
					aload 5;
					sload 8;
					invokevirtual 188;		// LoadTagBase([BS)S
					pop;
					aload 9;
					invokevirtual 160;		// GetTag()B
					bspush -109;
					if_scmpeq L15;
				L14:	sspush 27264;
					invokestatic 226;		// javacard/framework/ISOException.throwIt(S)V
					return;
				L15:	getfield_a_this 20;		// reference im/status/phonon/PhononApplet.secureChannel
					getfield_a_this 20;		// reference im/status/phonon/PhononApplet.secureChannel
					invokevirtual 163;		// GetSenderSalt()[B
					aload 4;
					invokevirtual 161;		// GetLength()S
					aload 6;
					invokevirtual 156;		// CardSenderpair([BS[B)V
					getfield_a_this 20;		// reference im/status/phonon/PhononApplet.secureChannel
					aload 9;
					invokevirtual 162;		// GetData()[B
					aload 9;
					invokevirtual 161;		// GetLength()S
					invokevirtual 164;		// CardVerifySession([BS)Z
					sstore 10;
				L16:	sload 10;
					ifne L18;
				L17:	sspush 27010;
					invokestatic 226;		// javacard/framework/ISOException.throwIt(S)V
					return;
				L18:	getfield_a_this 51;		// reference im/status/phonon/PhononApplet.OutputData
					sconst_0;
					getfield_a_this 51;		// reference im/status/phonon/PhononApplet.OutputData
					arraylength;
					sconst_0;
					invokestatic 249;		// javacard/framework/Util.arrayFillNonAtomic([BSSB)S
					pop;
					getfield_a_this 20;		// reference im/status/phonon/PhononApplet.secureChannel
					getfield_a_this 51;		// reference im/status/phonon/PhononApplet.OutputData
					invokevirtual 158;		// CardSignSession([B)S
					sstore 11;
				L19:	getfield_a_this 55;		// reference im/status/phonon/PhononApplet.BertlvArray
					sconst_0;
					aaload;
					astore 12;
				L20:	aload 12;
					bspush -109;
					sload 11;
					getfield_a_this 51;		// reference im/status/phonon/PhononApplet.OutputData
					getfield_a_this 52;		// reference im/status/phonon/PhononApplet.OutputData2
					invokevirtual 152;		// BuildTLVStructure(BS[B[B)[B
					pop;
					getfield_a_this 52;		// reference im/status/phonon/PhononApplet.OutputData2
					sconst_0;
					aload_2;
					sload 8;
					aload 12;
					getfield_s 1;		// short im/status/phonon/Bertlv.BuildLength
					invokestatic 228;		// javacard/framework/Util.arrayCopyNonAtomic([BS[BSS)S
					pop;
					sload 8;
					aload 12;
					getfield_s 1;		// short im/status/phonon/Bertlv.BuildLength
					sadd;
					sstore 8;
					aload_1;
					sconst_0;
					sload 8;
					invokevirtual 154;		// setOutgoingAndSend(SS)V
					return;
		}

		.method private FinalizeCardPairing(Ljavacard/framework/APDU;)V {
			.stack 4;
			.locals 4;

			.descriptor	Ljavacard/framework/APDU;	1.10;

				L0:	aload_1;
					invokevirtual 112;		// getBuffer()[B
					astore_2;
				L1:	aload_1;
					invokevirtual 147;		// getIncomingLength()S
					sstore_3;
				L2:	getfield_a_this 55;		// reference im/status/phonon/PhononApplet.BertlvArray
					sconst_0;
					aaload;
					astore 4;
				L3:	aload 4;
					aload_2;
					invokevirtual 159;		// LoadTag([B)S
					pop;
					aload 4;
					invokevirtual 160;		// GetTag()B
					bspush -109;
					if_scmpeq L5;
				L4:	sspush 27264;
					invokestatic 226;		// javacard/framework/ISOException.throwIt(S)V
					return;
				L5:	getfield_a_this 20;		// reference im/status/phonon/PhononApplet.secureChannel
					aload 4;
					invokevirtual 162;		// GetData()[B
					aload 4;
					invokevirtual 161;		// GetLength()S
					invokevirtual 165;		// CardVerifySignature([BS)Z
					sstore 5;
				L6:	sload 5;
					ifne L8;
				L7:	sspush 27010;
					invokestatic 226;		// javacard/framework/ISOException.throwIt(S)V
					return;
				L8:	getfield_a_this 20;		// reference im/status/phonon/PhononApplet.secureChannel
					aload_1;
					sconst_0;
					sspush -28672;
					invokevirtual 144;		// respond(Ljavacard/framework/APDU;SS)V
					return;
		}

		.method private createPhonon(Ljavacard/framework/APDU;)V {
			.stack 6;
			.locals 9;

			.descriptor	Ljavacard/framework/APDU;	1.10;

				L0:	getfield_a_this 19;		// reference im/status/phonon/PhononApplet.secp256k1
					getfield_a_this 53;		// reference im/status/phonon/PhononApplet.PhononKey
					invokevirtual 166;		// getPrivate()Ljavacard/security/PrivateKey;
					checkcast 0 167;		// T_CLASSORINTERFACE javacard/security/ECKey
					invokevirtual 168;		// setCurveParameters(Ljavacard/security/ECKey;)V
					getfield_a_this 19;		// reference im/status/phonon/PhononApplet.secp256k1
					getfield_a_this 53;		// reference im/status/phonon/PhononApplet.PhononKey
					invokevirtual 169;		// getPublic()Ljavacard/security/PublicKey;
					checkcast 0 167;		// T_CLASSORINTERFACE javacard/security/ECKey
					invokevirtual 168;		// setCurveParameters(Ljavacard/security/ECKey;)V
					aload_1;
					invokevirtual 112;		// getBuffer()[B
					astore_2;
				L1:	getfield_a_this 20;		// reference im/status/phonon/PhononApplet.secureChannel
					aload_2;
					invokevirtual 170;		// preprocessAPDU([B)S
					sstore_3;
				L2:	getfield_a_this 56;		// reference im/status/phonon/PhononApplet.pin
					invokevirtual 171;		// isValidated()Z
					ifne L4;
				L3:	getfield_a_this 20;		// reference im/status/phonon/PhononApplet.secureChannel
					aload_1;
					sconst_0;
					sspush 27013;
					invokevirtual 144;		// respond(Ljavacard/framework/APDU;SS)V
					return;
				L4:	getfield_s_this 16;		// short im/status/phonon/PhononApplet.phononKeyIndex
					sspush 256;
					if_scmplt L7;
				L5:	getfield_s_this 17;		// short im/status/phonon/PhononApplet.DeletedPhononIndex
					ifne L7;
				L6:	getfield_a_this 20;		// reference im/status/phonon/PhononApplet.secureChannel
					aload_1;
					sconst_0;
					sspush 27268;
					invokevirtual 144;		// respond(Ljavacard/framework/APDU;SS)V
					return;
				L7:	invokestatic 172;		// javacard/framework/JCSystem.beginTransaction()V
					getfield_s_this 16;		// short im/status/phonon/PhononApplet.phononKeyIndex
					sstore 4;
				L8:	sconst_0;
					sstore 5;
				L9:	getfield_s_this 17;		// short im/status/phonon/PhononApplet.DeletedPhononIndex
					ifne L11;
				L10:	getfield_a_this 25;		// reference im/status/phonon/PhononApplet.PhononArray2
					sload 4;
					new 216;		// im/status/phonon/Phonon2
					dup;
					invokespecial 173;		// im/status/phonon/Phonon2.<init>()V
					aastore;
					aload_0;
					dup;
					getfield_s 16;		// short im/status/phonon/PhononApplet.phononKeyIndex
					sconst_1;
					sadd;
					putfield_s 16;		// short im/status/phonon/PhononApplet.phononKeyIndex
					goto L12;
				L11:	aload_0;
					dup;
					getfield_s 17;		// short im/status/phonon/PhononApplet.DeletedPhononIndex
					sconst_1;
					ssub;
					putfield_s 17;		// short im/status/phonon/PhononApplet.DeletedPhononIndex
					getfield_a_this 28;		// reference im/status/phonon/PhononApplet.DeletedPhononList
					getfield_s_this 17;		// short im/status/phonon/PhononApplet.DeletedPhononIndex
					saload;
					sstore 4;
					sconst_1;
					sstore 5;
				L12:	getfield_a_this 53;		// reference im/status/phonon/PhononApplet.PhononKey
					invokevirtual 174;		// genKeyPair()V
					getfield_a_this 53;		// reference im/status/phonon/PhononApplet.PhononKey
					invokevirtual 169;		// getPublic()Ljavacard/security/PublicKey;
					checkcast 0 233;		// T_CLASSORINTERFACE javacard/security/ECPublicKey
					astore 6;
				L13:	getfield_a_this 25;		// reference im/status/phonon/PhononApplet.PhononArray2
					sload 4;
					aaload;
					aload 6;
					getfield_a_this 51;		// reference im/status/phonon/PhononApplet.OutputData
					sconst_0;
					invokeinterface 3 233 19;		// javacard/security/ECPublicKey
					putfield_s 58;		// short im/status/phonon/Phonon2.PhononPublicKeyLen
					sload 5;
					ifne L15;
				L14:	getfield_a_this 25;		// reference im/status/phonon/PhononApplet.PhononArray2
					sload 4;
					aaload;
					getfield_a_this 25;		// reference im/status/phonon/PhononApplet.PhononArray2
					sload 4;
					aaload;
					getfield_s 58;		// short im/status/phonon/Phonon2.PhononPublicKeyLen
					newarray 11;
					putfield_a 59;		// reference im/status/phonon/Phonon2.sPhononPublicKey
				L15:	getfield_a_this 51;		// reference im/status/phonon/PhononApplet.OutputData
					sconst_0;
					getfield_a_this 25;		// reference im/status/phonon/PhononApplet.PhononArray2
					sload 4;
					aaload;
					getfield_a 59;		// reference im/status/phonon/Phonon2.sPhononPublicKey
					sconst_0;
					getfield_a_this 25;		// reference im/status/phonon/PhononApplet.PhononArray2
					sload 4;
					aaload;
					getfield_s 58;		// short im/status/phonon/Phonon2.PhononPublicKeyLen
					invokestatic 177;		// javacard/framework/Util.arrayCopy([BS[BSS)S
					pop;
					getfield_a_this 53;		// reference im/status/phonon/PhononApplet.PhononKey
					invokevirtual 166;		// getPrivate()Ljavacard/security/PrivateKey;
					checkcast 0 235;		// T_CLASSORINTERFACE javacard/security/ECPrivateKey
					astore 7;
				L16:	getfield_a_this 25;		// reference im/status/phonon/PhononApplet.PhononArray2
					sload 4;
					aaload;
					aload 7;
					getfield_a_this 51;		// reference im/status/phonon/PhononApplet.OutputData
					sconst_0;
					invokeinterface 3 235 19;		// javacard/security/ECPrivateKey
					putfield_s 60;		// short im/status/phonon/Phonon2.PhononPrivateKeyLen
					sload 5;
					ifne L18;
				L17:	getfield_a_this 25;		// reference im/status/phonon/PhononApplet.PhononArray2
					sload 4;
					aaload;
					getfield_a_this 25;		// reference im/status/phonon/PhononApplet.PhononArray2
					sload 4;
					aaload;
					getfield_s 60;		// short im/status/phonon/Phonon2.PhononPrivateKeyLen
					newarray 11;
					putfield_a 61;		// reference im/status/phonon/Phonon2.sPhononPrivateKey
				L18:	getfield_a_this 51;		// reference im/status/phonon/PhononApplet.OutputData
					sconst_0;
					getfield_a_this 25;		// reference im/status/phonon/PhononApplet.PhononArray2
					sload 4;
					aaload;
					getfield_a 61;		// reference im/status/phonon/Phonon2.sPhononPrivateKey
					sconst_0;
					getfield_a_this 25;		// reference im/status/phonon/PhononApplet.PhononArray2
					sload 4;
					aaload;
					getfield_s 60;		// short im/status/phonon/Phonon2.PhononPrivateKeyLen
					invokestatic 177;		// javacard/framework/Util.arrayCopy([BS[BSS)S
					pop;
					getfield_a_this 25;		// reference im/status/phonon/PhononApplet.PhononArray2
					sload 4;
					aaload;
					sconst_1;
					putfield_b 62;		// byte im/status/phonon/Phonon2.Status
					invokestatic 181;		// javacard/framework/JCSystem.commitTransaction()V
					getfield_a_this 51;		// reference im/status/phonon/PhononApplet.OutputData
					astore 8;
				L19:	sconst_0;
					sstore 9;
				L20:	aload 8;
					sload 9;
					dup;
					sconst_1;
					sadd;
					sstore 9;
					bspush 64;
					bastore;
					sinc 9 1;
					aload 8;
					sload 9;
					dup;
					sconst_1;
					sadd;
					sstore 9;
					bspush 65;
					bastore;
					aload 8;
					sload 9;
					dup;
					sconst_1;
					sadd;
					sstore 9;
					sconst_2;
					bastore;
					aload 8;
					sload 9;
					sload 4;
					sconst_1;
					sadd;
					invokestatic 230;		// javacard/framework/Util.setShort([BSS)S
					pop;
					sinc 9 2;
					aload 8;
					sload 9;
					dup;
					sconst_1;
					sadd;
					sstore 9;
					bspush -128;
					bastore;
					sload 9;
					dup;
					sconst_1;
					sadd;
					sstore 9;
					sstore 10;
				L21:	getfield_a_this 25;		// reference im/status/phonon/PhononApplet.PhononArray2
					sload 4;
					aaload;
					getfield_a 59;		// reference im/status/phonon/Phonon2.sPhononPublicKey
					sconst_0;
					aload 8;
					sload 9;
					getfield_a_this 25;		// reference im/status/phonon/PhononApplet.PhononArray2
					sload 4;
					aaload;
					getfield_s 58;		// short im/status/phonon/Phonon2.PhononPublicKeyLen
					invokestatic 228;		// javacard/framework/Util.arrayCopyNonAtomic([BS[BSS)S
					pop;
					aload 8;
					sload 10;
					getfield_a_this 25;		// reference im/status/phonon/PhononApplet.PhononArray2
					sload 4;
					aaload;
					getfield_s 58;		// short im/status/phonon/Phonon2.PhononPublicKeyLen
					s2b;
					bastore;
					sload 9;
					getfield_a_this 25;		// reference im/status/phonon/PhononApplet.PhononArray2
					sload 4;
					aaload;
					getfield_s 58;		// short im/status/phonon/Phonon2.PhononPublicKeyLen
					sadd;
					sstore 9;
					aload 8;
					sconst_1;
					sload 9;
					sconst_1;
					ssub;
					s2b;
					bastore;
					getfield_a_this 20;		// reference im/status/phonon/PhononApplet.secureChannel
					aload_1;
					aload 8;
					sload 9;
					sspush -28672;
					invokevirtual 182;		// respond(Ljavacard/framework/APDU;[BSS)V
					return;
		}

		.method private SetReceivePhononList(Ljavacard/framework/APDU;)V {
			.stack 5;
			.locals 8;

			.descriptor	Ljavacard/framework/APDU;	1.10;

				L0:	aload_1;
					invokevirtual 112;		// getBuffer()[B
					astore_2;
				L1:	getfield_a_this 20;		// reference im/status/phonon/PhononApplet.secureChannel
					aload_2;
					invokevirtual 170;		// preprocessAPDU([B)S
					sstore_3;
				L2:	getfield_a_this 56;		// reference im/status/phonon/PhononApplet.pin
					invokevirtual 171;		// isValidated()Z
					ifne L4;
				L3:	getfield_a_this 20;		// reference im/status/phonon/PhononApplet.secureChannel
					aload_1;
					sconst_0;
					sspush 27013;
					invokevirtual 144;		// respond(Ljavacard/framework/APDU;SS)V
					return;
				L4:	getfield_s_this 16;		// short im/status/phonon/PhononApplet.phononKeyIndex
					sspush 256;
					if_scmplt L6;
				L5:	getfield_a_this 20;		// reference im/status/phonon/PhononApplet.secureChannel
					aload_1;
					sconst_0;
					sspush 27268;
					invokevirtual 144;		// respond(Ljavacard/framework/APDU;SS)V
					return;
				L6:	getfield_a_this 55;		// reference im/status/phonon/PhononApplet.BertlvArray
					sconst_0;
					aaload;
					astore 4;
				L7:	sload_3;
					sconst_2;
					invokestatic 184;		// javacard/framework/JCSystem.makeTransientByteArray(SB)[B
					astore 5;
				L8:	aload_2;
					sconst_0;
					aload 5;
					sconst_0;
					sload_3;
					invokestatic 228;		// javacard/framework/Util.arrayCopyNonAtomic([BS[BSS)S
					pop;
					aload 4;
					aload 5;
					invokevirtual 159;		// LoadTag([B)S
					pop;
					aload 4;
					invokevirtual 160;		// GetTag()B
					bspush 127;
					if_scmpeq L10;
				L9:	getfield_a_this 20;		// reference im/status/phonon/PhononApplet.secureChannel
					aload_1;
					sconst_0;
					sspush 27264;
					invokevirtual 144;		// respond(Ljavacard/framework/APDU;SS)V
					return;
				L10:	aload 4;
					invokevirtual 161;		// GetLength()S
					sstore 6;
				L11:	sload 6;
					bspush 65;
					sdiv;
					sstore 6;
					sconst_0;
					sstore 7;
				L12:	sconst_0;
					sstore 8;
				L13:	goto L19;
				L14:	getfield_a_this 55;		// reference im/status/phonon/PhononApplet.BertlvArray
					sconst_1;
					aaload;
					astore 9;
				L15:	aload 9;
					aload 4;
					invokevirtual 162;		// GetData()[B
					sload 7;
					invokevirtual 183;		// LoadNextTag([BS)S
					pop;
					aload 9;
					getfield_a 0;		// reference im/status/phonon/Bertlv.bertag
					getfield_s 5;		// short im/status/phonon/BerTag.nextData
					sstore 7;
					aload 9;
					invokevirtual 160;		// GetTag()B
					bspush -128;
					if_scmpeq L17;
				L16:	getfield_a_this 20;		// reference im/status/phonon/PhononApplet.secureChannel
					aload_1;
					sconst_0;
					sspush 27264;
					invokevirtual 144;		// respond(Ljavacard/framework/APDU;SS)V
				L17:	aload_0;
					aload 9;
					invokevirtual 161;		// GetLength()S
					sconst_1;
					invokestatic 184;		// javacard/framework/JCSystem.makeTransientByteArray(SB)[B
					putfield_a 63;		// reference im/status/phonon/PhononApplet.SetReceiveListPubKey
					aload 9;
					invokevirtual 162;		// GetData()[B
					sconst_0;
					getfield_a_this 63;		// reference im/status/phonon/PhononApplet.SetReceiveListPubKey
					sconst_0;
					aload 9;
					invokevirtual 161;		// GetLength()S
					invokestatic 228;		// javacard/framework/Util.arrayCopyNonAtomic([BS[BSS)S
					pop;
					aload_0;
					sconst_1;
					putfield_b 33;		// boolean im/status/phonon/PhononApplet.SetReceiveList
				L18:	sinc 8 1;
				L19:	sload 8;
					sload 6;
					if_scmplt L14;
				L20:	getfield_a_this 20;		// reference im/status/phonon/PhononApplet.secureChannel
					aload_1;
					sconst_0;
					sspush -28672;
					invokevirtual 144;		// respond(Ljavacard/framework/APDU;SS)V
					return;
		}

		.method private ReceivePhonons(Ljavacard/framework/APDU;)V {
			.stack 6;
			.locals 19;

			.descriptor	Ljavacard/framework/APDU;	1.10;

				L0:	aload_1;
					invokevirtual 112;		// getBuffer()[B
					astore_2;
				L1:	getfield_a_this 20;		// reference im/status/phonon/PhononApplet.secureChannel
					aload_2;
					invokevirtual 170;		// preprocessAPDU([B)S
					sstore_3;
				L2:	getfield_a_this 56;		// reference im/status/phonon/PhononApplet.pin
					invokevirtual 171;		// isValidated()Z
					ifne L4;
				L3:	getfield_a_this 20;		// reference im/status/phonon/PhononApplet.secureChannel
					aload_1;
					sconst_0;
					sspush 27013;
					invokevirtual 144;		// respond(Ljavacard/framework/APDU;SS)V
					return;
				L4:	getfield_s_this 16;		// short im/status/phonon/PhononApplet.phononKeyIndex
					sspush 256;
					if_scmplt L6;
				L5:	getfield_a_this 20;		// reference im/status/phonon/PhononApplet.secureChannel
					aload_1;
					sconst_0;
					sspush 27268;
					invokevirtual 144;		// respond(Ljavacard/framework/APDU;SS)V
					return;
				L6:	getfield_b_this 33;		// boolean im/status/phonon/PhononApplet.SetReceiveList
					ifne L8;
				L7:	getfield_a_this 20;		// reference im/status/phonon/PhononApplet.secureChannel
					aload_1;
					sconst_0;
					sspush 27013;
					invokevirtual 144;		// respond(Ljavacard/framework/APDU;SS)V
					return;
				L8:	sload_3;
					sconst_2;
					invokestatic 184;		// javacard/framework/JCSystem.makeTransientByteArray(SB)[B
					astore 4;
				L9:	aload_2;
					sconst_5;
					aload 4;
					sconst_0;
					sload_3;
					invokestatic 228;		// javacard/framework/Util.arrayCopyNonAtomic([BS[BSS)S
					pop;
					getfield_a_this 55;		// reference im/status/phonon/PhononApplet.BertlvArray
					sconst_0;
					aaload;
					astore 5;
				L10:	sload_3;
					sconst_2;
					invokestatic 184;		// javacard/framework/JCSystem.makeTransientByteArray(SB)[B
					astore 6;
				L11:	aload 4;
					sconst_0;
					aload 6;
					sconst_0;
					sload_3;
					invokestatic 228;		// javacard/framework/Util.arrayCopyNonAtomic([BS[BSS)S
					pop;
					aload 5;
					aload 6;
					invokevirtual 159;		// LoadTag([B)S
					pop;
					aload 5;
					invokevirtual 160;		// GetTag()B
					bspush 67;
					if_scmpeq L13;
				L12:	getfield_a_this 20;		// reference im/status/phonon/PhononApplet.secureChannel
					aload_1;
					sconst_0;
					sspush 27264;
					invokevirtual 144;		// respond(Ljavacard/framework/APDU;SS)V
					return;
				L13:	aload 5;
					invokevirtual 161;		// GetLength()S
					sstore 7;
				L14:	sload 7;
					bspush 46;
					sdiv;
					sstore 7;
					sconst_0;
					sstore 8;
				L15:	sconst_0;
					sstore 9;
				L16:	goto_w L41;
				L17:	getfield_s_this 16;		// short im/status/phonon/PhononApplet.phononKeyIndex
					sspush 256;
					if_scmplt L19;
				L18:	getfield_a_this 20;		// reference im/status/phonon/PhononApplet.secureChannel
					aload_1;
					sconst_0;
					sspush 27268;
					invokevirtual 144;		// respond(Ljavacard/framework/APDU;SS)V
					return;
				L19:	getfield_a_this 55;		// reference im/status/phonon/PhononApplet.BertlvArray
					sconst_1;
					aaload;
					astore 10;
				L20:	aload 10;
					aload 5;
					invokevirtual 162;		// GetData()[B
					sload 8;
					invokevirtual 183;		// LoadNextTag([BS)S
					pop;
					aload 10;
					getfield_a 0;		// reference im/status/phonon/Bertlv.bertag
					getfield_s 5;		// short im/status/phonon/BerTag.nextData
					sstore 8;
					getfield_a_this 55;		// reference im/status/phonon/PhononApplet.BertlvArray
					sconst_2;
					aaload;
					astore 11;
				L21:	aload 11;
					aload 10;
					invokevirtual 162;		// GetData()[B
					invokevirtual 159;		// LoadTag([B)S
					pop;
					getfield_a_this 55;		// reference im/status/phonon/PhononApplet.BertlvArray
					sconst_3;
					aaload;
					astore 12;
				L22:	aload 12;
					aload 10;
					invokevirtual 162;		// GetData()[B
					aload 11;
					getfield_a 0;		// reference im/status/phonon/Bertlv.bertag
					getfield_s 5;		// short im/status/phonon/BerTag.nextData
					invokevirtual 183;		// LoadNextTag([BS)S
					pop;
					getfield_a_this 55;		// reference im/status/phonon/PhononApplet.BertlvArray
					sconst_4;
					aaload;
					astore 13;
				L23:	aload 13;
					aload 10;
					invokevirtual 162;		// GetData()[B
					aload 12;
					getfield_a 0;		// reference im/status/phonon/Bertlv.bertag
					getfield_s 5;		// short im/status/phonon/BerTag.nextData
					invokevirtual 183;		// LoadNextTag([BS)S
					pop;
					invokestatic 172;		// javacard/framework/JCSystem.beginTransaction()V
					getfield_s_this 16;		// short im/status/phonon/PhononApplet.phononKeyIndex
					sstore 14;
				L24:	sconst_0;
					sstore 15;
				L25:	getfield_s_this 17;		// short im/status/phonon/PhononApplet.DeletedPhononIndex
					ifne L27;
				L26:	getfield_a_this 25;		// reference im/status/phonon/PhononApplet.PhononArray2
					sload 14;
					new 216;		// im/status/phonon/Phonon2
					dup;
					invokespecial 173;		// im/status/phonon/Phonon2.<init>()V
					aastore;
					aload_0;
					dup;
					getfield_s 16;		// short im/status/phonon/PhononApplet.phononKeyIndex
					sconst_1;
					sadd;
					putfield_s 16;		// short im/status/phonon/PhononApplet.phononKeyIndex
					goto L28;
				L27:	aload_0;
					dup;
					getfield_s 17;		// short im/status/phonon/PhononApplet.DeletedPhononIndex
					sconst_1;
					ssub;
					putfield_s 17;		// short im/status/phonon/PhononApplet.DeletedPhononIndex
					getfield_a_this 28;		// reference im/status/phonon/PhononApplet.DeletedPhononList
					getfield_s_this 17;		// short im/status/phonon/PhononApplet.DeletedPhononIndex
					saload;
					sstore 14;
					sconst_1;
					sstore 15;
				L28:	getfield_a_this 53;		// reference im/status/phonon/PhononApplet.PhononKey
					invokevirtual 166;		// getPrivate()Ljavacard/security/PrivateKey;
					checkcast 0 235;		// T_CLASSORINTERFACE javacard/security/ECPrivateKey
					astore 16;
				L29:	getfield_a_this 25;		// reference im/status/phonon/PhononApplet.PhononArray2
					sload 14;
					aaload;
					aload 11;
					invokevirtual 161;		// GetLength()S
					putfield_s 60;		// short im/status/phonon/Phonon2.PhononPrivateKeyLen
					sload 15;
					ifne L31;
				L30:	getfield_a_this 25;		// reference im/status/phonon/PhononApplet.PhononArray2
					sload 14;
					aaload;
					getfield_a_this 25;		// reference im/status/phonon/PhononApplet.PhononArray2
					sload 14;
					aaload;
					getfield_s 60;		// short im/status/phonon/Phonon2.PhononPrivateKeyLen
					newarray 11;
					putfield_a 61;		// reference im/status/phonon/Phonon2.sPhononPrivateKey
				L31:	aload 11;
					invokevirtual 162;		// GetData()[B
					sconst_0;
					getfield_a_this 25;		// reference im/status/phonon/PhononApplet.PhononArray2
					sload 14;
					aaload;
					getfield_a 61;		// reference im/status/phonon/Phonon2.sPhononPrivateKey
					sconst_0;
					getfield_a_this 25;		// reference im/status/phonon/PhononApplet.PhononArray2
					sload 14;
					aaload;
					getfield_s 60;		// short im/status/phonon/Phonon2.PhononPrivateKeyLen
					invokestatic 228;		// javacard/framework/Util.arrayCopyNonAtomic([BS[BSS)S
					pop;
					aload 16;
					getfield_a_this 25;		// reference im/status/phonon/PhononApplet.PhononArray2
					sload 14;
					aaload;
					getfield_a 61;		// reference im/status/phonon/Phonon2.sPhononPrivateKey
					sconst_0;
					getfield_a_this 25;		// reference im/status/phonon/PhononApplet.PhononArray2
					sload 14;
					aaload;
					getfield_s 60;		// short im/status/phonon/Phonon2.PhononPrivateKeyLen
					invokeinterface 4 235 18;		// javacard/security/ECPrivateKey
					getfield_a_this 51;		// reference im/status/phonon/PhononApplet.OutputData
					astore 17;
				L32:	getfield_a_this 19;		// reference im/status/phonon/PhononApplet.secp256k1
					aload 16;
					aload 17;
					sconst_0;
					invokevirtual 185;		// derivePublicKey(Ljavacard/security/ECPrivateKey;[BS)S
					sstore 18;
				L33:	getfield_a_this 53;		// reference im/status/phonon/PhononApplet.PhononKey
					invokevirtual 169;		// getPublic()Ljavacard/security/PublicKey;
					checkcast 0 233;		// T_CLASSORINTERFACE javacard/security/ECPublicKey
					astore 19;
				L34:	aload 19;
					aload 17;
					sconst_0;
					sload 18;
					invokeinterface 4 233 18;		// javacard/security/ECPublicKey
					getfield_a_this 25;		// reference im/status/phonon/PhononApplet.PhononArray2
					sload 14;
					aaload;
					sload 18;
					putfield_s 58;		// short im/status/phonon/Phonon2.PhononPublicKeyLen
					sload 15;
					ifne L36;
				L35:	getfield_a_this 25;		// reference im/status/phonon/PhononApplet.PhononArray2
					sload 14;
					aaload;
					getfield_a_this 25;		// reference im/status/phonon/PhononApplet.PhononArray2
					sload 14;
					aaload;
					getfield_s 58;		// short im/status/phonon/Phonon2.PhononPublicKeyLen
					newarray 11;
					putfield_a 59;		// reference im/status/phonon/Phonon2.sPhononPublicKey
				L36:	aload 17;
					sconst_0;
					getfield_a_this 25;		// reference im/status/phonon/PhononApplet.PhononArray2
					sload 14;
					aaload;
					getfield_a 59;		// reference im/status/phonon/Phonon2.sPhononPublicKey
					sconst_0;
					getfield_a_this 25;		// reference im/status/phonon/PhononApplet.PhononArray2
					sload 14;
					aaload;
					getfield_s 58;		// short im/status/phonon/Phonon2.PhononPublicKeyLen
					invokestatic 228;		// javacard/framework/Util.arrayCopyNonAtomic([BS[BSS)S
					pop;
					getfield_a_this 25;		// reference im/status/phonon/PhononApplet.PhononArray2
					sload 14;
					aaload;
					aload 13;
					invokevirtual 162;		// GetData()[B
					sconst_0;
					invokestatic 186;		// javacard/framework/Util.getShort([BS)S
					putfield_s 64;		// short im/status/phonon/Phonon2.CurrencyType
					aload 12;
					invokevirtual 161;		// GetLength()S
					sstore 20;
				L37:	getfield_a_this 25;		// reference im/status/phonon/PhononApplet.PhononArray2
					sload 14;
					aaload;
					sload 20;
					newarray 11;
					putfield_a 65;		// reference im/status/phonon/Phonon2.Value
					aload 12;
					invokevirtual 162;		// GetData()[B
					sconst_0;
					getfield_a_this 25;		// reference im/status/phonon/PhononApplet.PhononArray2
					sload 14;
					aaload;
					getfield_a 65;		// reference im/status/phonon/Phonon2.Value
					sconst_0;
					sload 20;
					invokestatic 228;		// javacard/framework/Util.arrayCopyNonAtomic([BS[BSS)S
					pop;
					aload 17;
					sconst_0;
					getfield_a_this 63;		// reference im/status/phonon/PhononApplet.SetReceiveListPubKey
					sconst_0;
					sload 18;
					invokestatic 189;		// javacard/framework/Util.arrayCompare([BS[BSS)B
					ifeq L39;
				L38:	getfield_a_this 20;		// reference im/status/phonon/PhononApplet.secureChannel
					aload_1;
					sconst_0;
					sspush 27264;
					invokevirtual 144;		// respond(Ljavacard/framework/APDU;SS)V
					return;
				L39:	getfield_a_this 25;		// reference im/status/phonon/PhononApplet.PhononArray2
					sload 14;
					aaload;
					sconst_1;
					putfield_b 62;		// byte im/status/phonon/Phonon2.Status
					invokestatic 181;		// javacard/framework/JCSystem.commitTransaction()V
					aload_0;
					dup;
					getfield_s 16;		// short im/status/phonon/PhononApplet.phononKeyIndex
					sconst_1;
					sadd;
					putfield_s 16;		// short im/status/phonon/PhononApplet.phononKeyIndex
				L40:	sinc 9 1;
				L41:	sload 9;
					sload 7;
					if_scmplt_w L17;
				L42:	getfield_a_this 20;		// reference im/status/phonon/PhononApplet.secureChannel
					aload_1;
					sconst_0;
					sspush -28672;
					invokevirtual 144;		// respond(Ljavacard/framework/APDU;SS)V
					return;
		}

		.method private DestroyPhonon(Ljavacard/framework/APDU;)V {
			.stack 5;
			.locals 8;

			.descriptor	Ljavacard/framework/APDU;	1.10;

				L0:	aload_1;
					invokevirtual 112;		// getBuffer()[B
					astore_2;
				L1:	getfield_a_this 20;		// reference im/status/phonon/PhononApplet.secureChannel
					aload_2;
					invokevirtual 170;		// preprocessAPDU([B)S
					sstore_3;
				L2:	getfield_a_this 56;		// reference im/status/phonon/PhononApplet.pin
					invokevirtual 171;		// isValidated()Z
					ifne L4;
				L3:	getfield_a_this 20;		// reference im/status/phonon/PhononApplet.secureChannel
					aload_1;
					sconst_0;
					sspush 27013;
					invokevirtual 144;		// respond(Ljavacard/framework/APDU;SS)V
					return;
				L4:	sload_3;
					sconst_2;
					invokestatic 184;		// javacard/framework/JCSystem.makeTransientByteArray(SB)[B
					astore 4;
				L5:	aload_2;
					sconst_5;
					aload 4;
					sconst_0;
					sload_3;
					invokestatic 228;		// javacard/framework/Util.arrayCopyNonAtomic([BS[BSS)S
					pop;
					sload_3;
					sconst_4;
					if_scmple L7;
				L6:	getfield_a_this 20;		// reference im/status/phonon/PhononApplet.secureChannel
					aload_1;
					sconst_0;
					sspush 26368;
					invokevirtual 144;		// respond(Ljavacard/framework/APDU;SS)V
					return;
				L7:	getfield_a_this 55;		// reference im/status/phonon/PhononApplet.BertlvArray
					sconst_0;
					aaload;
					astore 5;
				L8:	aload 4;
					astore 6;
				L9:	aload 5;
					aload 6;
					invokevirtual 159;		// LoadTag([B)S
					pop;
					aload 5;
					invokevirtual 160;		// GetTag()B
					bspush 65;
					if_scmpeq L11;
				L10:	getfield_a_this 20;		// reference im/status/phonon/PhononApplet.secureChannel
					aload_1;
					sconst_0;
					sspush 27264;
					invokevirtual 144;		// respond(Ljavacard/framework/APDU;SS)V
					return;
				L11:	aload 5;
					invokevirtual 162;		// GetData()[B
					sconst_0;
					invokestatic 186;		// javacard/framework/Util.getShort([BS)S
					sstore 7;
				L12:	sload 7;
					ifne L14;
				L13:	getfield_a_this 20;		// reference im/status/phonon/PhononApplet.secureChannel
					aload_1;
					sconst_0;
					sspush 27011;
					invokevirtual 144;		// respond(Ljavacard/framework/APDU;SS)V
					return;
				L14:	sinc 7 -1;
					sload 7;
					getfield_s_this 16;		// short im/status/phonon/PhononApplet.phononKeyIndex
					if_scmplt L16;
				L15:	getfield_a_this 20;		// reference im/status/phonon/PhononApplet.secureChannel
					aload_1;
					sconst_0;
					sspush 27011;
					invokevirtual 144;		// respond(Ljavacard/framework/APDU;SS)V
					return;
				L16:	getfield_a_this 25;		// reference im/status/phonon/PhononApplet.PhononArray2
					sload 7;
					aaload;
					ifnull L18;
				L17:	getfield_a_this 25;		// reference im/status/phonon/PhononApplet.PhononArray2
					sload 7;
					aaload;
					getfield_b 62;		// byte im/status/phonon/Phonon2.Status
					sconst_4;
					if_scmpne L19;
				L18:	getfield_a_this 20;		// reference im/status/phonon/PhononApplet.secureChannel
					aload_1;
					sconst_0;
					sspush 27011;
					invokevirtual 144;		// respond(Ljavacard/framework/APDU;SS)V
					return;
				L19:	invokestatic 172;		// javacard/framework/JCSystem.beginTransaction()V
					getfield_a_this 55;		// reference im/status/phonon/PhononApplet.BertlvArray
					sconst_1;
					aaload;
					astore 8;
				L20:	getfield_a_this 51;		// reference im/status/phonon/PhononApplet.OutputData
					astore 9;
				L21:	aload 8;
					bspush -127;
					getfield_a_this 25;		// reference im/status/phonon/PhononApplet.PhononArray2
					sload 7;
					aaload;
					getfield_s 60;		// short im/status/phonon/Phonon2.PhononPrivateKeyLen
					getfield_a_this 25;		// reference im/status/phonon/PhononApplet.PhononArray2
					sload 7;
					aaload;
					getfield_a 61;		// reference im/status/phonon/Phonon2.sPhononPrivateKey
					aload 9;
					invokevirtual 152;		// BuildTLVStructure(BS[B[B)[B
					pop;
					getfield_a_this 25;		// reference im/status/phonon/PhononApplet.PhononArray2
					sload 7;
					aaload;
					sconst_4;
					putfield_b 62;		// byte im/status/phonon/Phonon2.Status
					getfield_a_this 25;		// reference im/status/phonon/PhononApplet.PhononArray2
					sload 7;
					aaload;
					sconst_0;
					putfield_s 64;		// short im/status/phonon/Phonon2.CurrencyType
					getfield_a_this 28;		// reference im/status/phonon/PhononApplet.DeletedPhononList
					getfield_s_this 17;		// short im/status/phonon/PhononApplet.DeletedPhononIndex
					sload 7;
					sastore;
					aload_0;
					dup;
					getfield_s 17;		// short im/status/phonon/PhononApplet.DeletedPhononIndex
					sconst_1;
					sadd;
					putfield_s 17;		// short im/status/phonon/PhononApplet.DeletedPhononIndex
					invokestatic 181;		// javacard/framework/JCSystem.commitTransaction()V
					getfield_a_this 20;		// reference im/status/phonon/PhononApplet.secureChannel
					aload_1;
					aload 9;
					aload 8;
					getfield_s 1;		// short im/status/phonon/Bertlv.BuildLength
					sspush -28672;
					invokevirtual 182;		// respond(Ljavacard/framework/APDU;[BSS)V
					return;
		}

		.method private SetPhononDescriptor(Ljavacard/framework/APDU;)V {
			.stack 5;
			.locals 13;

			.descriptor	Ljavacard/framework/APDU;	1.10;

				L0:	aload_1;
					invokevirtual 112;		// getBuffer()[B
					astore_2;
				L1:	getfield_a_this 20;		// reference im/status/phonon/PhononApplet.secureChannel
					aload_2;
					invokevirtual 170;		// preprocessAPDU([B)S
					sstore_3;
				L2:	getfield_a_this 56;		// reference im/status/phonon/PhononApplet.pin
					invokevirtual 171;		// isValidated()Z
					ifne L4;
				L3:	getfield_a_this 20;		// reference im/status/phonon/PhononApplet.secureChannel
					aload_1;
					sconst_0;
					sspush 27013;
					invokevirtual 144;		// respond(Ljavacard/framework/APDU;SS)V
					return;
				L4:	sload_3;
					sconst_2;
					invokestatic 184;		// javacard/framework/JCSystem.makeTransientByteArray(SB)[B
					astore 4;
				L5:	aload_2;
					sconst_5;
					aload 4;
					sconst_0;
					sload_3;
					invokestatic 228;		// javacard/framework/Util.arrayCopyNonAtomic([BS[BSS)S
					pop;
					sload_3;
					bspush 16;
					if_scmple L7;
				L6:	getfield_a_this 20;		// reference im/status/phonon/PhononApplet.secureChannel
					aload_1;
					sconst_0;
					sspush 26368;
					invokevirtual 144;		// respond(Ljavacard/framework/APDU;SS)V
					return;
				L7:	getfield_a_this 55;		// reference im/status/phonon/PhononApplet.BertlvArray
					sconst_0;
					aaload;
					astore 5;
				L8:	aload 5;
					aload 4;
					invokevirtual 159;		// LoadTag([B)S
					pop;
					aload 5;
					invokevirtual 160;		// GetTag()B
					bspush 80;
					if_scmpeq L10;
				L9:	getfield_a_this 20;		// reference im/status/phonon/PhononApplet.secureChannel
					aload_1;
					sconst_0;
					sspush 27264;
					invokevirtual 144;		// respond(Ljavacard/framework/APDU;SS)V
					return;
				L10:	aload 5;
					invokevirtual 162;		// GetData()[B
					astore 6;
				L11:	getfield_a_this 55;		// reference im/status/phonon/PhononApplet.BertlvArray
					sconst_1;
					aaload;
					astore 7;
				L12:	aload 7;
					aload 6;
					invokevirtual 159;		// LoadTag([B)S
					pop;
					aload 7;
					getfield_a 0;		// reference im/status/phonon/Bertlv.bertag
					getfield_s 5;		// short im/status/phonon/BerTag.nextData
					sstore 8;
				L13:	aload 7;
					invokevirtual 160;		// GetTag()B
					bspush 65;
					if_scmpeq L15;
				L14:	getfield_a_this 20;		// reference im/status/phonon/PhononApplet.secureChannel
					aload_1;
					sconst_0;
					sspush 27264;
					invokevirtual 144;		// respond(Ljavacard/framework/APDU;SS)V
					return;
				L15:	aload 7;
					invokevirtual 162;		// GetData()[B
					sconst_0;
					invokestatic 186;		// javacard/framework/Util.getShort([BS)S
					sstore 9;
				L16:	sload 9;
					ifne L18;
				L17:	getfield_a_this 20;		// reference im/status/phonon/PhononApplet.secureChannel
					aload_1;
					sconst_0;
					sspush 27011;
					invokevirtual 144;		// respond(Ljavacard/framework/APDU;SS)V
					return;
				L18:	sinc 9 -1;
					sload 9;
					getfield_s_this 16;		// short im/status/phonon/PhononApplet.phononKeyIndex
					if_scmplt L20;
				L19:	getfield_a_this 20;		// reference im/status/phonon/PhononApplet.secureChannel
					aload_1;
					sconst_0;
					sspush 27011;
					invokevirtual 144;		// respond(Ljavacard/framework/APDU;SS)V
					return;
				L20:	getfield_a_this 25;		// reference im/status/phonon/PhononApplet.PhononArray2
					sload 9;
					aaload;
					ifnonnull L22;
				L21:	getfield_a_this 20;		// reference im/status/phonon/PhononApplet.secureChannel
					aload_1;
					sconst_0;
					sspush 27011;
					invokevirtual 144;		// respond(Ljavacard/framework/APDU;SS)V
					return;
				L22:	getfield_a_this 25;		// reference im/status/phonon/PhononApplet.PhononArray2
					sload 9;
					aaload;
					getfield_s 64;		// short im/status/phonon/Phonon2.CurrencyType
					ifeq L24;
				L23:	getfield_a_this 20;		// reference im/status/phonon/PhononApplet.secureChannel
					aload_1;
					sconst_0;
					sspush 27265;
					invokevirtual 144;		// respond(Ljavacard/framework/APDU;SS)V
					return;
				L24:	getfield_a_this 55;		// reference im/status/phonon/PhononApplet.BertlvArray
					sconst_2;
					aaload;
					astore 10;
				L25:	aload 10;
					aload 6;
					sload 8;
					invokevirtual 183;		// LoadNextTag([BS)S
					pop;
					aload 10;
					getfield_a 0;		// reference im/status/phonon/Bertlv.bertag
					getfield_s 5;		// short im/status/phonon/BerTag.nextData
					sstore 8;
					aload 10;
					invokevirtual 160;		// GetTag()B
					bspush -127;
					if_scmpeq L27;
				L26:	getfield_a_this 20;		// reference im/status/phonon/PhononApplet.secureChannel
					aload_1;
					sconst_0;
					sspush 27011;
					invokevirtual 144;		// respond(Ljavacard/framework/APDU;SS)V
					return;
				L27:	aload 10;
					invokevirtual 162;		// GetData()[B
					astore 11;
				L28:	aload 11;
					sconst_0;
					invokestatic 186;		// javacard/framework/Util.getShort([BS)S
					sstore 12;
				L29:	sload 12;
					ifne L31;
				L30:	getfield_a_this 20;		// reference im/status/phonon/PhononApplet.secureChannel
					aload_1;
					sconst_0;
					sspush 27012;
					invokevirtual 144;		// respond(Ljavacard/framework/APDU;SS)V
					return;
				L31:	invokestatic 172;		// javacard/framework/JCSystem.beginTransaction()V
					getfield_a_this 25;		// reference im/status/phonon/PhononApplet.PhononArray2
					sload 9;
					aaload;
					sload 12;
					putfield_s 64;		// short im/status/phonon/Phonon2.CurrencyType
					getfield_a_this 55;		// reference im/status/phonon/PhononApplet.BertlvArray
					sconst_3;
					aaload;
					astore 13;
				L32:	aload 13;
					aload 6;
					sload 8;
					invokevirtual 183;		// LoadNextTag([BS)S
					pop;
					aload 13;
					getfield_a 0;		// reference im/status/phonon/Bertlv.bertag
					getfield_s 5;		// short im/status/phonon/BerTag.nextData
					sstore 8;
					aload 13;
					invokevirtual 160;		// GetTag()B
					bspush -125;
					if_scmpeq L34;
				L33:	getfield_a_this 20;		// reference im/status/phonon/PhononApplet.secureChannel
					aload_1;
					sconst_0;
					sspush 27011;
					invokevirtual 144;		// respond(Ljavacard/framework/APDU;SS)V
					return;
				L34:	aload 13;
					invokevirtual 161;		// GetLength()S
					sstore 14;
				L35:	getfield_a_this 25;		// reference im/status/phonon/PhononApplet.PhononArray2
					sload 9;
					aaload;
					getfield_a 65;		// reference im/status/phonon/Phonon2.Value
					ifnonnull L37;
				L36:	getfield_a_this 25;		// reference im/status/phonon/PhononApplet.PhononArray2
					sload 9;
					aaload;
					sload 14;
					newarray 11;
					putfield_a 65;		// reference im/status/phonon/Phonon2.Value
				L37:	aload 13;
					invokevirtual 162;		// GetData()[B
					sconst_0;
					getfield_a_this 25;		// reference im/status/phonon/PhononApplet.PhononArray2
					sload 9;
					aaload;
					getfield_a 65;		// reference im/status/phonon/Phonon2.Value
					sconst_0;
					sload 14;
					invokestatic 228;		// javacard/framework/Util.arrayCopyNonAtomic([BS[BSS)S
					pop;
					invokestatic 181;		// javacard/framework/JCSystem.commitTransaction()V
					getfield_a_this 20;		// reference im/status/phonon/PhononApplet.secureChannel
					aload_1;
					sconst_0;
					sspush -28672;
					invokevirtual 144;		// respond(Ljavacard/framework/APDU;SS)V
					return;
		}

		.method private GetPhononPublicKey(Ljavacard/framework/APDU;)V {
			.stack 5;
			.locals 8;

			.descriptor	Ljavacard/framework/APDU;	1.10;

				L0:	aload_1;
					invokevirtual 112;		// getBuffer()[B
					astore_2;
				L1:	getfield_a_this 20;		// reference im/status/phonon/PhononApplet.secureChannel
					aload_2;
					invokevirtual 170;		// preprocessAPDU([B)S
					sstore_3;
				L2:	getfield_a_this 56;		// reference im/status/phonon/PhononApplet.pin
					invokevirtual 171;		// isValidated()Z
					ifne L4;
				L3:	getfield_a_this 20;		// reference im/status/phonon/PhononApplet.secureChannel
					aload_1;
					sconst_0;
					sspush 27013;
					invokevirtual 144;		// respond(Ljavacard/framework/APDU;SS)V
					return;
				L4:	sload_3;
					sconst_2;
					invokestatic 184;		// javacard/framework/JCSystem.makeTransientByteArray(SB)[B
					astore 4;
				L5:	aload_2;
					sconst_5;
					aload 4;
					sconst_0;
					sload_3;
					invokestatic 228;		// javacard/framework/Util.arrayCopyNonAtomic([BS[BSS)S
					pop;
					sload_3;
					sconst_4;
					if_scmple L7;
				L6:	getfield_a_this 20;		// reference im/status/phonon/PhononApplet.secureChannel
					aload_1;
					sconst_0;
					sspush 26368;
					invokevirtual 144;		// respond(Ljavacard/framework/APDU;SS)V
					return;
				L7:	getfield_a_this 55;		// reference im/status/phonon/PhononApplet.BertlvArray
					sconst_0;
					aaload;
					astore 5;
				L8:	sload_3;
					sconst_2;
					invokestatic 184;		// javacard/framework/JCSystem.makeTransientByteArray(SB)[B
					astore 6;
				L9:	aload 4;
					sconst_0;
					aload 6;
					sconst_0;
					sload_3;
					invokestatic 228;		// javacard/framework/Util.arrayCopyNonAtomic([BS[BSS)S
					pop;
					aload 5;
					aload 6;
					invokevirtual 159;		// LoadTag([B)S
					pop;
					aload 5;
					invokevirtual 160;		// GetTag()B
					bspush 65;
					if_scmpeq L11;
				L10:	getfield_a_this 20;		// reference im/status/phonon/PhononApplet.secureChannel
					aload_1;
					sconst_0;
					sspush 27264;
					invokevirtual 144;		// respond(Ljavacard/framework/APDU;SS)V
					return;
				L11:	aload 5;
					invokevirtual 162;		// GetData()[B
					sconst_0;
					invokestatic 186;		// javacard/framework/Util.getShort([BS)S
					sstore 7;
				L12:	sload 7;
					ifne L14;
				L13:	getfield_a_this 20;		// reference im/status/phonon/PhononApplet.secureChannel
					aload_1;
					sconst_0;
					sspush 27011;
					invokevirtual 144;		// respond(Ljavacard/framework/APDU;SS)V
					return;
				L14:	sinc 7 -1;
					sload 7;
					getfield_s_this 16;		// short im/status/phonon/PhononApplet.phononKeyIndex
					if_scmplt L16;
				L15:	getfield_a_this 20;		// reference im/status/phonon/PhononApplet.secureChannel
					aload_1;
					sconst_0;
					sspush 27011;
					invokevirtual 144;		// respond(Ljavacard/framework/APDU;SS)V
					return;
				L16:	getfield_a_this 25;		// reference im/status/phonon/PhononApplet.PhononArray2
					sload 7;
					aaload;
					ifnonnull L18;
				L17:	getfield_a_this 20;		// reference im/status/phonon/PhononApplet.secureChannel
					aload_1;
					sconst_0;
					sspush 27011;
					invokevirtual 144;		// respond(Ljavacard/framework/APDU;SS)V
					return;
				L18:	getfield_a_this 25;		// reference im/status/phonon/PhononApplet.PhononArray2
					sload 7;
					aaload;
					getfield_s 64;		// short im/status/phonon/Phonon2.CurrencyType
					ifne L20;
				L19:	getfield_a_this 20;		// reference im/status/phonon/PhononApplet.secureChannel
					aload_1;
					sconst_0;
					sspush 27011;
					invokevirtual 144;		// respond(Ljavacard/framework/APDU;SS)V
					return;
				L20:	getfield_a_this 25;		// reference im/status/phonon/PhononApplet.PhononArray2
					sload 7;
					aaload;
					getfield_b 62;		// byte im/status/phonon/Phonon2.Status
					sconst_1;
					if_scmpeq L22;
				L21:	getfield_a_this 20;		// reference im/status/phonon/PhononApplet.secureChannel
					aload_1;
					sconst_0;
					sspush 27266;
					invokevirtual 144;		// respond(Ljavacard/framework/APDU;SS)V
					return;
				L22:	getfield_a_this 55;		// reference im/status/phonon/PhononApplet.BertlvArray
					sconst_1;
					aaload;
					astore 8;
				L23:	getfield_a_this 51;		// reference im/status/phonon/PhononApplet.OutputData
					astore 9;
				L24:	aload 8;
					bspush -128;
					getfield_a_this 25;		// reference im/status/phonon/PhononApplet.PhononArray2
					sload 7;
					aaload;
					getfield_s 58;		// short im/status/phonon/Phonon2.PhononPublicKeyLen
					getfield_a_this 25;		// reference im/status/phonon/PhononApplet.PhononArray2
					sload 7;
					aaload;
					getfield_a 59;		// reference im/status/phonon/Phonon2.sPhononPublicKey
					aload 9;
					invokevirtual 152;		// BuildTLVStructure(BS[B[B)[B
					pop;
					getfield_a_this 20;		// reference im/status/phonon/PhononApplet.secureChannel
					aload_1;
					aload 9;
					aload 8;
					getfield_s 1;		// short im/status/phonon/Bertlv.BuildLength
					sspush -28672;
					invokevirtual 182;		// respond(Ljavacard/framework/APDU;[BSS)V
					return;
		}

		.method private ListPhonons(Ljavacard/framework/APDU;)V {
			.stack 5;
			.locals 13;

			.descriptor	Ljavacard/framework/APDU;	1.10;

				L0:	aload_1;
					invokevirtual 112;		// getBuffer()[B
					astore_2;
				L1:	aload_2;
					sconst_2;
					baload;
					sstore_3;
				L2:	aload_2;
					sconst_3;
					baload;
					sstore 4;
				L3:	getfield_a_this 20;		// reference im/status/phonon/PhononApplet.secureChannel
					aload_2;
					invokevirtual 170;		// preprocessAPDU([B)S
					sstore 5;
				L4:	sload 5;
					ifne L7;
				L5:	sload_3;
					ifne L7;
				L6:	getfield_a_this 20;		// reference im/status/phonon/PhononApplet.secureChannel
					aload_1;
					sconst_0;
					sspush 27264;
					invokevirtual 144;		// respond(Ljavacard/framework/APDU;SS)V
					return;
				L7:	getfield_a_this 56;		// reference im/status/phonon/PhononApplet.pin
					invokevirtual 171;		// isValidated()Z
					ifne L9;
				L8:	getfield_a_this 20;		// reference im/status/phonon/PhononApplet.secureChannel
					aload_1;
					sconst_0;
					sspush 27013;
					invokevirtual 144;		// respond(Ljavacard/framework/APDU;SS)V
					return;
				L9:	sload_3;
					sconst_1;
					if_scmple L11;
				L10:	getfield_a_this 20;		// reference im/status/phonon/PhononApplet.secureChannel
					aload_1;
					sconst_0;
					sspush 27270;
					invokevirtual 144;		// respond(Ljavacard/framework/APDU;SS)V
					return;
				L11:	sload 5;
					sconst_2;
					invokestatic 184;		// javacard/framework/JCSystem.makeTransientByteArray(SB)[B
					astore 6;
				L12:	aload_2;
					sconst_5;
					aload 6;
					sconst_0;
					sload 5;
					invokestatic 228;		// javacard/framework/Util.arrayCopyNonAtomic([BS[BSS)S
					pop;
					sload_3;
					ifne_w L85;
				L13:	sload 4;
					sconst_3;
					if_scmple L15;
				L14:	getfield_a_this 20;		// reference im/status/phonon/PhononApplet.secureChannel
					aload_1;
					sconst_0;
					sspush 27270;
					invokevirtual 144;		// respond(Ljavacard/framework/APDU;SS)V
					return;
				L15:	getfield_a_this 55;		// reference im/status/phonon/PhononApplet.BertlvArray
					sconst_0;
					aaload;
					astore 7;
				L16:	aload 6;
					astore 8;
				L17:	aload 7;
					aload 8;
					invokevirtual 159;		// LoadTag([B)S
					pop;
					aload 7;
					invokevirtual 160;		// GetTag()B
					bspush 96;
					if_scmpeq L19;
				L18:	getfield_a_this 20;		// reference im/status/phonon/PhononApplet.secureChannel
					aload_1;
					sconst_0;
					sspush 27264;
					invokevirtual 144;		// respond(Ljavacard/framework/APDU;SS)V
					return;
				L19:	aload 7;
					bspush -127;
					invokevirtual 190;		// FindTag(B)S
					sstore 9;
				L20:	sload 9;
					sconst_m1;
					if_scmpne L22;
				L21:	getfield_a_this 20;		// reference im/status/phonon/PhononApplet.secureChannel
					aload_1;
					sconst_0;
					sspush 27264;
					invokevirtual 144;		// respond(Ljavacard/framework/APDU;SS)V
					return;
				L22:	getfield_a_this 55;		// reference im/status/phonon/PhononApplet.BertlvArray
					sconst_1;
					aaload;
					astore 10;
				L23:	aload 10;
					aload 7;
					getfield_a 0;		// reference im/status/phonon/Bertlv.bertag
					getfield_a 2;		// reference im/status/phonon/BerTag.data
					sload 9;
					invokevirtual 188;		// LoadTagBase([BS)S
					pop;
					aload 10;
					getfield_a 0;		// reference im/status/phonon/Bertlv.bertag
					getfield_a 2;		// reference im/status/phonon/BerTag.data
					sconst_0;
					invokestatic 186;		// javacard/framework/Util.getShort([BS)S
					sstore 11;
				L24:	sconst_4;
					sconst_2;
					invokestatic 184;		// javacard/framework/JCSystem.makeTransientByteArray(SB)[B
					astore 12;
				L25:	aload 12;
					sconst_0;
					sconst_4;
					sconst_0;
					invokestatic 249;		// javacard/framework/Util.arrayFillNonAtomic([BSSB)S
					pop;
					sload 4;
					sconst_1;
					if_scmpeq L27;
				L26:	sload 4;
					sconst_3;
					if_scmpne L31;
				L27:	aload 7;
					bspush -124;
					invokevirtual 190;		// FindTag(B)S
					sstore 9;
					sload 9;
					sconst_m1;
					if_scmpne L29;
				L28:	getfield_a_this 20;		// reference im/status/phonon/PhononApplet.secureChannel
					aload_1;
					sconst_0;
					sspush 27264;
					invokevirtual 144;		// respond(Ljavacard/framework/APDU;SS)V
					return;
				L29:	getfield_a_this 55;		// reference im/status/phonon/PhononApplet.BertlvArray
					sconst_2;
					aaload;
					astore 13;
				L30:	aload 13;
					aload 7;
					getfield_a 0;		// reference im/status/phonon/Bertlv.bertag
					getfield_a 2;		// reference im/status/phonon/BerTag.data
					sload 9;
					invokevirtual 188;		// LoadTagBase([BS)S
					pop;
					aload 13;
					getfield_a 0;		// reference im/status/phonon/Bertlv.bertag
					getfield_a 2;		// reference im/status/phonon/BerTag.data
					sconst_0;
					aload 12;
					sconst_0;
					sconst_4;
					invokestatic 228;		// javacard/framework/Util.arrayCopyNonAtomic([BS[BSS)S
					pop;
				L31:	sconst_4;
					sconst_2;
					invokestatic 184;		// javacard/framework/JCSystem.makeTransientByteArray(SB)[B
					astore 13;
				L32:	aload 13;
					sconst_0;
					sconst_4;
					sconst_0;
					invokestatic 249;		// javacard/framework/Util.arrayFillNonAtomic([BSSB)S
					pop;
					sload 4;
					sconst_2;
					if_scmpeq L34;
				L33:	sload 4;
					sconst_3;
					if_scmpne L38;
				L34:	aload 7;
					bspush -123;
					invokevirtual 190;		// FindTag(B)S
					sstore 9;
					sload 9;
					sconst_m1;
					if_scmpne L36;
				L35:	getfield_a_this 20;		// reference im/status/phonon/PhononApplet.secureChannel
					aload_1;
					sconst_0;
					sspush 27264;
					invokevirtual 144;		// respond(Ljavacard/framework/APDU;SS)V
					return;
				L36:	getfield_a_this 55;		// reference im/status/phonon/PhononApplet.BertlvArray
					sconst_3;
					aaload;
					astore 14;
				L37:	aload 14;
					aload 7;
					getfield_a 0;		// reference im/status/phonon/Bertlv.bertag
					getfield_a 2;		// reference im/status/phonon/BerTag.data
					sload 9;
					invokevirtual 188;		// LoadTagBase([BS)S
					pop;
					aload 14;
					getfield_a 0;		// reference im/status/phonon/Bertlv.bertag
					getfield_a 2;		// reference im/status/phonon/BerTag.data
					sconst_0;
					aload 13;
					sconst_0;
					sconst_4;
					invokestatic 228;		// javacard/framework/Util.arrayCopyNonAtomic([BS[BSS)S
					pop;
				L38:	aload_0;
					sconst_0;
					putfield_s 29;		// short im/status/phonon/PhononApplet.PhononListCount
					aload_0;
					sconst_0;
					putfield_s 30;		// short im/status/phonon/PhononApplet.PhononListLastSent
					sload 4;
					stableswitch L85 0 3 L39 L49 L61 L73;
				L39:	sconst_0;
					sstore 14;
				L40:	goto L47;
				L41:	getfield_a_this 25;		// reference im/status/phonon/PhononApplet.PhononArray2
					sload 14;
					aaload;
					ifnull L46;
				L42:	getfield_a_this 25;		// reference im/status/phonon/PhononApplet.PhononArray2
					sload 14;
					aaload;
					getfield_b 62;		// byte im/status/phonon/Phonon2.Status
					sconst_1;
					if_scmpne L46;
				L43:	sload 11;
					ifeq L45;
				L44:	sload 11;
					getfield_a_this 25;		// reference im/status/phonon/PhononApplet.PhononArray2
					sload 14;
					aaload;
					getfield_s 64;		// short im/status/phonon/Phonon2.CurrencyType
					if_scmpne L46;
				L45:	getfield_a_this 26;		// reference im/status/phonon/PhononApplet.PhononList
					getfield_s_this 29;		// short im/status/phonon/PhononApplet.PhononListCount
					sload 14;
					sastore;
					aload_0;
					dup;
					getfield_s 29;		// short im/status/phonon/PhononApplet.PhononListCount
					sconst_1;
					sadd;
					putfield_s 29;		// short im/status/phonon/PhononApplet.PhononListCount
				L46:	sinc 14 1;
				L47:	sload 14;
					getfield_s_this 16;		// short im/status/phonon/PhononApplet.phononKeyIndex
					if_scmplt L41;
				L48:	goto_w L85;
				L49:	sconst_0;
					sstore 14;
				L50:	goto L59;
				L51:	getfield_a_this 25;		// reference im/status/phonon/PhononApplet.PhononArray2
					sload 14;
					aaload;
					ifnull L58;
				L52:	getfield_a_this 25;		// reference im/status/phonon/PhononApplet.PhononArray2
					sload 14;
					aaload;
					getfield_b 62;		// byte im/status/phonon/Phonon2.Status
					sconst_1;
					if_scmpne L58;
				L53:	sload 11;
					ifne L55;
				L54:	getfield_a_this 25;		// reference im/status/phonon/PhononApplet.PhononArray2
					sload 14;
					aaload;
					getfield_s 64;		// short im/status/phonon/Phonon2.CurrencyType
					ifne L56;
				L55:	sload 11;
					getfield_a_this 25;		// reference im/status/phonon/PhononApplet.PhononArray2
					sload 14;
					aaload;
					getfield_s 64;		// short im/status/phonon/Phonon2.CurrencyType
					if_scmpne L58;
				L56:	getfield_a_this 25;		// reference im/status/phonon/PhononApplet.PhononArray2
					sload 14;
					aaload;
					getfield_a 65;		// reference im/status/phonon/Phonon2.Value
					sconst_0;
					aload 12;
					sconst_0;
					sconst_4;
					invokestatic 189;		// javacard/framework/Util.arrayCompare([BS[BSS)B
					sconst_1;
					if_scmpeq L58;
				L57:	getfield_a_this 26;		// reference im/status/phonon/PhononApplet.PhononList
					getfield_s_this 29;		// short im/status/phonon/PhononApplet.PhononListCount
					sload 14;
					sastore;
					aload_0;
					dup;
					getfield_s 29;		// short im/status/phonon/PhononApplet.PhononListCount
					sconst_1;
					sadd;
					putfield_s 29;		// short im/status/phonon/PhononApplet.PhononListCount
				L58:	sinc 14 1;
				L59:	sload 14;
					getfield_s_this 16;		// short im/status/phonon/PhononApplet.phononKeyIndex
					if_scmplt L51;
				L60:	goto_w L85;
				L61:	sconst_0;
					sstore 14;
				L62:	goto L71;
				L63:	getfield_a_this 25;		// reference im/status/phonon/PhononApplet.PhononArray2
					sload 14;
					aaload;
					ifnull L70;
				L64:	getfield_a_this 25;		// reference im/status/phonon/PhononApplet.PhononArray2
					sload 14;
					aaload;
					getfield_b 62;		// byte im/status/phonon/Phonon2.Status
					sconst_1;
					if_scmpne L70;
				L65:	sload 11;
					ifne L67;
				L66:	getfield_a_this 25;		// reference im/status/phonon/PhononApplet.PhononArray2
					sload 14;
					aaload;
					getfield_s 64;		// short im/status/phonon/Phonon2.CurrencyType
					ifne L68;
				L67:	sload 11;
					getfield_a_this 25;		// reference im/status/phonon/PhononApplet.PhononArray2
					sload 14;
					aaload;
					getfield_s 64;		// short im/status/phonon/Phonon2.CurrencyType
					if_scmpne L70;
				L68:	getfield_a_this 25;		// reference im/status/phonon/PhononApplet.PhononArray2
					sload 14;
					aaload;
					getfield_a 65;		// reference im/status/phonon/Phonon2.Value
					sconst_0;
					aload 13;
					sconst_0;
					sconst_4;
					invokestatic 189;		// javacard/framework/Util.arrayCompare([BS[BSS)B
					sconst_m1;
					if_scmpeq L70;
				L69:	getfield_a_this 26;		// reference im/status/phonon/PhononApplet.PhononList
					getfield_s_this 29;		// short im/status/phonon/PhononApplet.PhononListCount
					sload 14;
					sastore;
					aload_0;
					dup;
					getfield_s 29;		// short im/status/phonon/PhononApplet.PhononListCount
					sconst_1;
					sadd;
					putfield_s 29;		// short im/status/phonon/PhononApplet.PhononListCount
				L70:	sinc 14 1;
				L71:	sload 14;
					getfield_s_this 16;		// short im/status/phonon/PhononApplet.phononKeyIndex
					if_scmplt L63;
				L72:	goto L85;
				L73:	sconst_0;
					sstore 14;
				L74:	goto L84;
				L75:	getfield_a_this 25;		// reference im/status/phonon/PhononApplet.PhononArray2
					sload 14;
					aaload;
					ifnull L83;
				L76:	getfield_a_this 25;		// reference im/status/phonon/PhononApplet.PhononArray2
					sload 14;
					aaload;
					getfield_b 62;		// byte im/status/phonon/Phonon2.Status
					sconst_1;
					if_scmpne L83;
				L77:	sload 11;
					ifne L79;
				L78:	getfield_a_this 25;		// reference im/status/phonon/PhononApplet.PhononArray2
					sload 14;
					aaload;
					getfield_s 64;		// short im/status/phonon/Phonon2.CurrencyType
					ifne L80;
				L79:	sload 11;
					getfield_a_this 25;		// reference im/status/phonon/PhononApplet.PhononArray2
					sload 14;
					aaload;
					getfield_s 64;		// short im/status/phonon/Phonon2.CurrencyType
					if_scmpne L83;
				L80:	getfield_a_this 25;		// reference im/status/phonon/PhononApplet.PhononArray2
					sload 14;
					aaload;
					getfield_a 65;		// reference im/status/phonon/Phonon2.Value
					sconst_0;
					aload 12;
					sconst_0;
					sconst_4;
					invokestatic 189;		// javacard/framework/Util.arrayCompare([BS[BSS)B
					sconst_1;
					if_scmpeq L83;
				L81:	getfield_a_this 25;		// reference im/status/phonon/PhononApplet.PhononArray2
					sload 14;
					aaload;
					getfield_a 65;		// reference im/status/phonon/Phonon2.Value
					sconst_0;
					aload 13;
					sconst_0;
					sconst_4;
					invokestatic 189;		// javacard/framework/Util.arrayCompare([BS[BSS)B
					sconst_m1;
					if_scmpeq L83;
				L82:	getfield_a_this 26;		// reference im/status/phonon/PhononApplet.PhononList
					getfield_s_this 29;		// short im/status/phonon/PhononApplet.PhononListCount
					sload 14;
					sastore;
					aload_0;
					dup;
					getfield_s 29;		// short im/status/phonon/PhononApplet.PhononListCount
					sconst_1;
					sadd;
					putfield_s 29;		// short im/status/phonon/PhononApplet.PhononListCount
				L83:	sinc 14 1;
				L84:	sload 14;
					getfield_s_this 16;		// short im/status/phonon/PhononApplet.phononKeyIndex
					if_scmplt L75;
				L85:	aload_0;
					aload_1;
					bspush 82;
					invokespecial 191;		// im/status/phonon/PhononApplet.SendSelectPhononList(Ljavacard/framework/APDU;B)V
					return;
		}

		.method private SendSelectPhononList(Ljavacard/framework/APDU;B)V {
			.stack 5;
			.locals 13;

			.descriptor	Ljavacard/framework/APDU;	1.10;

				L0:	aload_1;
					invokevirtual 112;		// getBuffer()[B
					astore_3;
				L1:	getfield_a_this 52;		// reference im/status/phonon/PhononApplet.OutputData2
					astore 4;
				L2:	sconst_0;
					sstore 5;
				L3:	bspush 24;
					sconst_2;
					invokestatic 184;		// javacard/framework/JCSystem.makeTransientByteArray(SB)[B
					astore 8;
				L4:	sconst_4;
					sconst_2;
					invokestatic 184;		// javacard/framework/JCSystem.makeTransientByteArray(SB)[B
					astore 9;
				L5:	bspush 24;
					sconst_2;
					invokestatic 184;		// javacard/framework/JCSystem.makeTransientByteArray(SB)[B
					astore 10;
				L6:	getfield_s_this 30;		// short im/status/phonon/PhononApplet.PhononListLastSent
					sstore 7;
				L7:	goto_w L20;
				L8:	getfield_a_this 26;		// reference im/status/phonon/PhononApplet.PhononList
					sload 7;
					saload;
					sstore 6;
				L9:	sconst_0;
					sstore 11;
				L10:	getfield_a_this 55;		// reference im/status/phonon/PhononApplet.BertlvArray
					sconst_0;
					aaload;
					astore 12;
				L11:	getfield_a_this 25;		// reference im/status/phonon/PhononApplet.PhononArray2
					sload 6;
					aaload;
					getfield_s 64;		// short im/status/phonon/Phonon2.CurrencyType
					ifeq L13;
				L12:	aload 12;
					bspush -125;
					sconst_4;
					getfield_a_this 25;		// reference im/status/phonon/PhononApplet.PhononArray2
					sload 6;
					aaload;
					getfield_a 65;		// reference im/status/phonon/Phonon2.Value
					aload 10;
					invokevirtual 152;		// BuildTLVStructure(BS[B[B)[B
					pop;
					goto L14;
				L13:	aload 9;
					sconst_0;
					sconst_4;
					sconst_0;
					invokestatic 249;		// javacard/framework/Util.arrayFillNonAtomic([BSSB)S
					pop;
					aload 12;
					bspush -125;
					sconst_4;
					aload 9;
					aload 10;
					invokevirtual 152;		// BuildTLVStructure(BS[B[B)[B
					pop;
				L14:	aload 10;
					sconst_0;
					aload 8;
					sload 11;
					aload 12;
					getfield_s 1;		// short im/status/phonon/Bertlv.BuildLength
					invokestatic 228;		// javacard/framework/Util.arrayCopyNonAtomic([BS[BSS)S
					pop;
					sload 11;
					aload 12;
					getfield_s 1;		// short im/status/phonon/Bertlv.BuildLength
					sadd;
					sstore 11;
					getfield_a_this 55;		// reference im/status/phonon/PhononApplet.BertlvArray
					sconst_1;
					aaload;
					astore 13;
				L15:	aload 13;
					bspush -127;
					sconst_2;
					getfield_a_this 25;		// reference im/status/phonon/PhononApplet.PhononArray2
					sload 6;
					aaload;
					getfield_s 64;		// short im/status/phonon/Phonon2.CurrencyType
					aload 10;
					invokevirtual 192;		// BuildTLVStructure(BSS[B)[B
					pop;
					aload 10;
					sconst_0;
					aload 8;
					sload 11;
					aload 13;
					getfield_s 1;		// short im/status/phonon/Bertlv.BuildLength
					invokestatic 228;		// javacard/framework/Util.arrayCopyNonAtomic([BS[BSS)S
					pop;
					sload 11;
					aload 13;
					getfield_s 1;		// short im/status/phonon/Bertlv.BuildLength
					sadd;
					sstore 11;
					getfield_a_this 55;		// reference im/status/phonon/PhononApplet.BertlvArray
					sconst_2;
					aaload;
					astore 14;
				L16:	aload 14;
					bspush 65;
					sconst_2;
					sload 6;
					sconst_1;
					sadd;
					aload 10;
					invokevirtual 192;		// BuildTLVStructure(BSS[B)[B
					pop;
					aload 10;
					sconst_0;
					aload 8;
					sload 11;
					aload 14;
					getfield_s 1;		// short im/status/phonon/Bertlv.BuildLength
					invokestatic 228;		// javacard/framework/Util.arrayCopyNonAtomic([BS[BSS)S
					pop;
					sload 11;
					aload 14;
					getfield_s 1;		// short im/status/phonon/Bertlv.BuildLength
					sadd;
					sstore 11;
					getfield_a_this 55;		// reference im/status/phonon/PhononApplet.BertlvArray
					sconst_3;
					aaload;
					astore 15;
				L17:	aload 15;
					bspush 80;
					sload 11;
					aload 8;
					aload 10;
					invokevirtual 152;		// BuildTLVStructure(BS[B[B)[B
					pop;
					aload 10;
					sconst_0;
					aload 4;
					sload 5;
					aload 15;
					getfield_s 1;		// short im/status/phonon/Bertlv.BuildLength
					invokestatic 228;		// javacard/framework/Util.arrayCopyNonAtomic([BS[BSS)S
					pop;
					sload 5;
					aload 15;
					getfield_s 1;		// short im/status/phonon/Bertlv.BuildLength
					sadd;
					sstore 5;
					sload 5;
					aload 15;
					getfield_s 1;		// short im/status/phonon/Bertlv.BuildLength
					sadd;
					sspush 200;
					if_scmple L19;
				L18:	goto L21;
				L19:	sinc 7 1;
				L20:	sload 7;
					getfield_s_this 29;		// short im/status/phonon/PhononApplet.PhononListCount
					if_scmplt_w L8;
				L21:	getfield_a_this 55;		// reference im/status/phonon/PhononApplet.BertlvArray
					sconst_4;
					aaload;
					astore 11;
				L22:	getfield_a_this 51;		// reference im/status/phonon/PhononApplet.OutputData
					astore 12;
				L23:	aload 11;
					bspush 82;
					sload 5;
					aload 4;
					aload 12;
					invokevirtual 152;		// BuildTLVStructure(BS[B[B)[B
					pop;
					sspush -28672;
					sstore 13;
				L24:	sload 7;
					getfield_s_this 29;		// short im/status/phonon/PhononApplet.PhononListCount
					if_scmpge L26;
				L25:	aload_0;
					sload 7;
					sconst_1;
					sadd;
					putfield_s 30;		// short im/status/phonon/PhononApplet.PhononListLastSent
					getfield_s_this 29;		// short im/status/phonon/PhononApplet.PhononListCount
					getfield_s_this 30;		// short im/status/phonon/PhononApplet.PhononListLastSent
					ssub;
					sspush -28672;
					sadd;
					sstore 13;
				L26:	getfield_a_this 20;		// reference im/status/phonon/PhononApplet.secureChannel
					aload_1;
					aload 12;
					sload 5;
					sconst_2;
					sadd;
					sload 13;
					invokevirtual 182;		// respond(Ljavacard/framework/APDU;[BSS)V
					return;
		}

		.method private SendPhonons(Ljavacard/framework/APDU;)V {
			.stack 4;
			.locals 9;

			.descriptor	Ljavacard/framework/APDU;	1.10;

				L0:	aload_1;
					invokevirtual 112;		// getBuffer()[B
					astore_2;
				L1:	getfield_a_this 20;		// reference im/status/phonon/PhononApplet.secureChannel
					aload_2;
					invokevirtual 170;		// preprocessAPDU([B)S
					sstore_3;
				L2:	getfield_a_this 56;		// reference im/status/phonon/PhononApplet.pin
					invokevirtual 171;		// isValidated()Z
					ifne L4;
				L3:	getfield_a_this 20;		// reference im/status/phonon/PhononApplet.secureChannel
					aload_1;
					sconst_0;
					sspush 27013;
					invokevirtual 144;		// respond(Ljavacard/framework/APDU;SS)V
					return;
				L4:	aload_2;
					astore 4;
				L5:	aload_2;
					sconst_2;
					baload;
					sstore 5;
				L6:	sload 5;
					sconst_1;
					if_scmple L8;
				L7:	getfield_a_this 20;		// reference im/status/phonon/PhononApplet.secureChannel
					aload_1;
					sconst_0;
					sspush 27270;
					invokevirtual 144;		// respond(Ljavacard/framework/APDU;SS)V
					return;
				L8:	sload 5;
					ifne L21;
				L9:	aload_0;
					sconst_0;
					putfield_s 31;		// short im/status/phonon/PhononApplet.SendPhononListCount
					aload_0;
					sconst_0;
					putfield_s 32;		// short im/status/phonon/PhononApplet.SendPhononListLastSent
					aload_2;
					sconst_3;
					baload;
					sstore 6;
				L10:	sload 6;
					ifne L12;
				L11:	getfield_a_this 20;		// reference im/status/phonon/PhononApplet.secureChannel
					aload_1;
					sconst_0;
					sspush 27270;
					invokevirtual 144;		// respond(Ljavacard/framework/APDU;SS)V
					return;
				L12:	getfield_a_this 55;		// reference im/status/phonon/PhononApplet.BertlvArray
					sconst_0;
					aaload;
					astore 7;
				L13:	aload 4;
					astore 8;
				L14:	aload 7;
					aload 8;
					invokevirtual 159;		// LoadTag([B)S
					pop;
					aload 7;
					invokevirtual 160;		// GetTag()B
					bspush 66;
					if_scmpeq L16;
				L15:	getfield_a_this 20;		// reference im/status/phonon/PhononApplet.secureChannel
					aload_1;
					sconst_0;
					sspush 27264;
					invokevirtual 144;		// respond(Ljavacard/framework/APDU;SS)V
					return;
				L16:	aload_0;
					aload 7;
					invokevirtual 161;		// GetLength()S
					sconst_2;
					sdiv;
					putfield_s 31;		// short im/status/phonon/PhononApplet.SendPhononListCount
					sconst_0;
					sstore 9;
				L17:	sconst_0;
					sstore 10;
				L18:	goto L20;
				L19:	getfield_a_this 27;		// reference im/status/phonon/PhononApplet.SendPhononList
					sload 10;
					aload 7;
					invokevirtual 162;		// GetData()[B
					sload 9;
					invokestatic 186;		// javacard/framework/Util.getShort([BS)S
					sastore;
					sinc 9 2;
					sinc 10 1;
				L20:	sload 10;
					getfield_s_this 31;		// short im/status/phonon/PhononApplet.SendPhononListCount
					if_scmplt L19;
				L21:	aload_0;
					aload_1;
					bspush 67;
					invokespecial 193;		// im/status/phonon/PhononApplet.SendPhononList(Ljavacard/framework/APDU;B)V
					return;
		}

		.method private SendPhononList(Ljavacard/framework/APDU;B)V {
			.stack 6;
			.locals 11;

			.descriptor	Ljavacard/framework/APDU;	1.10;

				L0:	sspush 200;
					sconst_2;
					invokestatic 184;		// javacard/framework/JCSystem.makeTransientByteArray(SB)[B
					astore_3;
				L1:	sconst_0;
					sstore 4;
				L2:	invokestatic 172;		// javacard/framework/JCSystem.beginTransaction()V
					getfield_s_this 32;		// short im/status/phonon/PhononApplet.SendPhononListLastSent
					sstore 6;
				L3:	goto_w L19;
				L4:	getfield_a_this 27;		// reference im/status/phonon/PhononApplet.SendPhononList
					sload 6;
					saload;
					sstore 5;
				L5:	sinc 5 -1;
					bspush 100;
					sconst_2;
					invokestatic 184;		// javacard/framework/JCSystem.makeTransientByteArray(SB)[B
					astore 7;
				L6:	sconst_0;
					sstore 8;
				L7:	getfield_a_this 55;		// reference im/status/phonon/PhononApplet.BertlvArray
					sconst_0;
					aaload;
					astore 10;
				L8:	aload 10;
					bspush -127;
					getfield_a_this 25;		// reference im/status/phonon/PhononApplet.PhononArray2
					sload 5;
					aaload;
					getfield_s 60;		// short im/status/phonon/Phonon2.PhononPrivateKeyLen
					getfield_a_this 25;		// reference im/status/phonon/PhononApplet.PhononArray2
					sload 5;
					aaload;
					getfield_a 61;		// reference im/status/phonon/Phonon2.sPhononPrivateKey
					invokevirtual 194;		// BuildTLVStructure(BS[B)[B
					astore 9;
				L9:	aload 9;
					sconst_0;
					aload 7;
					sload 8;
					aload 10;
					getfield_s 1;		// short im/status/phonon/Bertlv.BuildLength
					invokestatic 228;		// javacard/framework/Util.arrayCopyNonAtomic([BS[BSS)S
					pop;
					sload 8;
					aload 10;
					getfield_s 1;		// short im/status/phonon/Bertlv.BuildLength
					sadd;
					sstore 8;
					getfield_a_this 55;		// reference im/status/phonon/PhononApplet.BertlvArray
					sconst_1;
					aaload;
					astore 11;
				L10:	getfield_a_this 25;		// reference im/status/phonon/PhononApplet.PhononArray2
					sload 5;
					aaload;
					getfield_s 64;		// short im/status/phonon/Phonon2.CurrencyType
					ifeq L12;
				L11:	aload 11;
					bspush -125;
					sconst_4;
					getfield_a_this 25;		// reference im/status/phonon/PhononApplet.PhononArray2
					sload 5;
					aaload;
					getfield_a 65;		// reference im/status/phonon/Phonon2.Value
					invokevirtual 194;		// BuildTLVStructure(BS[B)[B
					astore 9;
					goto L14;
				L12:	sconst_4;
					sconst_2;
					invokestatic 184;		// javacard/framework/JCSystem.makeTransientByteArray(SB)[B
					astore 12;
				L13:	aload 12;
					sconst_0;
					sconst_4;
					sconst_0;
					invokestatic 249;		// javacard/framework/Util.arrayFillNonAtomic([BSSB)S
					pop;
					aload 11;
					bspush -125;
					sconst_4;
					aload 12;
					invokevirtual 194;		// BuildTLVStructure(BS[B)[B
					astore 9;
				L14:	aload 9;
					sconst_0;
					aload 7;
					sload 8;
					aload 11;
					getfield_s 1;		// short im/status/phonon/Bertlv.BuildLength
					invokestatic 228;		// javacard/framework/Util.arrayCopyNonAtomic([BS[BSS)S
					pop;
					sload 8;
					aload 11;
					getfield_s 1;		// short im/status/phonon/Bertlv.BuildLength
					sadd;
					sstore 8;
					getfield_a_this 55;		// reference im/status/phonon/PhononApplet.BertlvArray
					sconst_2;
					aaload;
					astore 12;
				L15:	aload 12;
					bspush -127;
					sconst_2;
					getfield_a_this 25;		// reference im/status/phonon/PhononApplet.PhononArray2
					sload 5;
					aaload;
					getfield_s 64;		// short im/status/phonon/Phonon2.CurrencyType
					invokevirtual 195;		// BuildTLVStructure(BSS)[B
					astore 9;
					aload 9;
					sconst_0;
					aload 7;
					sload 8;
					aload 12;
					getfield_s 1;		// short im/status/phonon/Bertlv.BuildLength
					invokestatic 228;		// javacard/framework/Util.arrayCopyNonAtomic([BS[BSS)S
					pop;
					sload 8;
					aload 12;
					getfield_s 1;		// short im/status/phonon/Bertlv.BuildLength
					sadd;
					sstore 8;
					getfield_a_this 25;		// reference im/status/phonon/PhononApplet.PhononArray2
					sload 5;
					aaload;
					sconst_3;
					putfield_b 62;		// byte im/status/phonon/Phonon2.Status
					getfield_a_this 55;		// reference im/status/phonon/PhononApplet.BertlvArray
					sconst_3;
					aaload;
					astore 13;
				L16:	aload 13;
					bspush 68;
					sload 8;
					aload 7;
					invokevirtual 194;		// BuildTLVStructure(BS[B)[B
					astore 9;
					aload 9;
					sconst_0;
					aload_3;
					sload 4;
					aload 13;
					getfield_s 1;		// short im/status/phonon/Bertlv.BuildLength
					invokestatic 228;		// javacard/framework/Util.arrayCopyNonAtomic([BS[BSS)S
					pop;
					sload 4;
					aload 13;
					getfield_s 1;		// short im/status/phonon/Bertlv.BuildLength
					sadd;
					sstore 4;
					sload 4;
					aload 13;
					getfield_s 1;		// short im/status/phonon/Bertlv.BuildLength
					sadd;
					sspush 200;
					if_scmple L18;
				L17:	goto L20;
				L18:	sinc 6 1;
				L19:	sload 6;
					getfield_s_this 31;		// short im/status/phonon/PhononApplet.SendPhononListCount
					if_scmplt_w L4;
				L20:	getfield_a_this 55;		// reference im/status/phonon/PhononApplet.BertlvArray
					sconst_4;
					aaload;
					astore 7;
				L21:	getfield_a_this 51;		// reference im/status/phonon/PhononApplet.OutputData
					astore 8;
				L22:	aload 7;
					bspush 67;
					sload 4;
					aload_3;
					aload 8;
					invokevirtual 152;		// BuildTLVStructure(BS[B[B)[B
					pop;
					sconst_0;
					sstore 9;
				L23:	sload 6;
					getfield_s_this 31;		// short im/status/phonon/PhononApplet.SendPhononListCount
					if_scmpge L25;
				L24:	aload_0;
					sload 6;
					sconst_1;
					sadd;
					putfield_s 32;		// short im/status/phonon/PhononApplet.SendPhononListLastSent
					getfield_s_this 31;		// short im/status/phonon/PhononApplet.SendPhononListCount
					getfield_s_this 32;		// short im/status/phonon/PhononApplet.SendPhononListLastSent
					ssub;
					sspush -28672;
					sadd;
					sstore 9;
				L25:	getfield_a_this 20;		// reference im/status/phonon/PhononApplet.secureChannel
					aload_1;
					aload 8;
					sload 4;
					sconst_2;
					sadd;
					sspush -28672;
					sload 9;
					sadd;
					invokevirtual 182;		// respond(Ljavacard/framework/APDU;[BSS)V
					invokestatic 181;		// javacard/framework/JCSystem.commitTransaction()V
					return;
		}

		.method private SetTransactionsAsComplete(Ljavacard/framework/APDU;)V {
			.stack 4;
			.locals 7;

			.descriptor	Ljavacard/framework/APDU;	1.10;

				L0:	aload_1;
					invokevirtual 112;		// getBuffer()[B
					astore_2;
				L1:	getfield_a_this 20;		// reference im/status/phonon/PhononApplet.secureChannel
					aload_2;
					invokevirtual 170;		// preprocessAPDU([B)S
					sstore_3;
				L2:	getfield_a_this 56;		// reference im/status/phonon/PhononApplet.pin
					invokevirtual 171;		// isValidated()Z
					ifne L4;
				L3:	getfield_a_this 20;		// reference im/status/phonon/PhononApplet.secureChannel
					aload_1;
					sconst_0;
					sspush 27013;
					invokevirtual 144;		// respond(Ljavacard/framework/APDU;SS)V
					return;
				L4:	getfield_a_this 55;		// reference im/status/phonon/PhononApplet.BertlvArray
					sconst_0;
					aaload;
					astore 4;
				L5:	aload_2;
					astore 5;
				L6:	aload 4;
					aload 5;
					invokevirtual 159;		// LoadTag([B)S
					pop;
					aload 4;
					invokevirtual 160;		// GetTag()B
					bspush 66;
					if_scmpeq L8;
				L7:	getfield_a_this 20;		// reference im/status/phonon/PhononApplet.secureChannel
					aload_1;
					sconst_0;
					sspush 27264;
					invokevirtual 144;		// respond(Ljavacard/framework/APDU;SS)V
					return;
				L8:	aload_0;
					aload 4;
					invokevirtual 161;		// GetLength()S
					sconst_2;
					sdiv;
					putfield_s 31;		// short im/status/phonon/PhononApplet.SendPhononListCount
					sconst_0;
					sstore 6;
				L9:	invokestatic 172;		// javacard/framework/JCSystem.beginTransaction()V
					sconst_0;
					sstore 8;
				L10:	goto L13;
				L11:	aload 4;
					invokevirtual 162;		// GetData()[B
					sload 6;
					invokestatic 186;		// javacard/framework/Util.getShort([BS)S
					sstore 7;
				L12:	sinc 7 -1;
					getfield_a_this 25;		// reference im/status/phonon/PhononApplet.PhononArray2
					sload 7;
					aaload;
					sconst_4;
					putfield_b 62;		// byte im/status/phonon/Phonon2.Status
					sinc 6 2;
					sinc 8 1;
				L13:	sload 8;
					getfield_s_this 31;		// short im/status/phonon/PhononApplet.SendPhononListCount
					if_scmplt L11;
				L14:	invokestatic 181;		// javacard/framework/JCSystem.commitTransaction()V
					getfield_a_this 20;		// reference im/status/phonon/PhononApplet.secureChannel
					aload_1;
					sconst_0;
					sspush -28672;
					invokevirtual 144;		// respond(Ljavacard/framework/APDU;SS)V
					return;
		}

		.method private selectApplet(Ljavacard/framework/APDU;)V {
			.stack 5;
			.locals 4;

			.descriptor	Ljavacard/framework/APDU;	1.10;

				L0:	getfield_a_this 56;		// reference im/status/phonon/PhononApplet.pin
					invokevirtual 196;		// reset()V
					getfield_a_this 20;		// reference im/status/phonon/PhononApplet.secureChannel
					invokevirtual 197;		// reset()V
					getfield_a_this 20;		// reference im/status/phonon/PhononApplet.secureChannel
					invokevirtual 198;		// updateSecureChannelCounter()V
					aload_1;
					invokevirtual 112;		// getBuffer()[B
					astore_2;
				L1:	sconst_0;
					sstore_3;
				L2:	aload_2;
					sload_3;
					dup;
					sconst_1;
					sadd;
					sstore_3;
					bspush -92;
					bastore;
					getfield_a_this 39;		// reference im/status/phonon/PhononApplet.privateKey
					invokeinterface 1 235 3;		// javacard/security/ECPrivateKey
					ifeq L4;
				L3:	aload_2;
					sload_3;
					dup;
					sconst_1;
					sadd;
					sstore_3;
					bspush -127;
					bastore;
				L4:	sload_3;
					dup;
					sconst_1;
					sadd;
					sstore_3;
					sstore 4;
				L5:	aload_2;
					sload_3;
					dup;
					sconst_1;
					sadd;
					sstore_3;
					bspush -113;
					bastore;
					aload_2;
					sload_3;
					dup;
					sconst_1;
					sadd;
					sstore_3;
					bspush 16;
					bastore;
					getfield_a_this 21;		// reference im/status/phonon/PhononApplet.uid
					sconst_0;
					aload_2;
					sload_3;
					bspush 16;
					invokestatic 228;		// javacard/framework/Util.arrayCopyNonAtomic([BS[BSS)S
					pop;
					sinc 3 16;
					aload_2;
					sload_3;
					dup;
					sconst_1;
					sadd;
					sstore_3;
					bspush -128;
					bastore;
					getfield_a_this 20;		// reference im/status/phonon/PhononApplet.secureChannel
					aload_2;
					sload_3;
					sconst_1;
					sadd;
					invokevirtual 199;		// copyPublicKey([BS)S
					sstore 5;
				L6:	aload_2;
					sload_3;
					dup;
					sconst_1;
					sadd;
					sstore_3;
					sload 5;
					s2b;
					bastore;
					sload_3;
					sload 5;
					sadd;
					sstore_3;
					aload_2;
					sload_3;
					dup;
					sconst_1;
					sadd;
					sstore_3;
					sconst_2;
					bastore;
					aload_2;
					sload_3;
					dup;
					sconst_1;
					sadd;
					sstore_3;
					sconst_2;
					bastore;
					aload_2;
					sload_3;
					sconst_2;
					invokestatic 230;		// javacard/framework/Util.setShort([BSS)S
					pop;
					sinc 3 2;
					aload_2;
					sload_3;
					dup;
					sconst_1;
					sadd;
					sstore_3;
					sconst_3;
					bastore;
					aload_2;
					sload_3;
					dup;
					sconst_1;
					sadd;
					sstore_3;
					sconst_1;
					bastore;
					aload_2;
					sload_3;
					dup;
					sconst_1;
					sadd;
					sstore_3;
					getfield_a_this 20;		// reference im/status/phonon/PhononApplet.secureChannel
					invokevirtual 200;		// getRemainingPairingSlots()B
					bastore;
					aload_2;
					sload_3;
					dup;
					sconst_1;
					sadd;
					sstore_3;
					bspush -115;
					bastore;
					aload_2;
					sload_3;
					dup;
					sconst_1;
					sadd;
					sstore_3;
					sconst_1;
					bastore;
					aload_2;
					sload_3;
					dup;
					sconst_1;
					sadd;
					sstore_3;
					bspush 7;
					bastore;
					aload_2;
					sload 4;
					sload_3;
					sload 4;
					ssub;
					sconst_1;
					ssub;
					s2b;
					bastore;
					aload_1;
					sconst_0;
					sload_3;
					invokevirtual 154;		// setOutgoingAndSend(SS)V
					return;
		}

		.method private resetCurveParameters()V {
			.stack 2;
			.locals 0;

				L0:	getfield_a_this 19;		// reference im/status/phonon/PhononApplet.secp256k1
					getfield_a_this 34;		// reference im/status/phonon/PhononApplet.masterPublic
					invokevirtual 168;		// setCurveParameters(Ljavacard/security/ECKey;)V
					getfield_a_this 19;		// reference im/status/phonon/PhononApplet.secp256k1
					getfield_a_this 35;		// reference im/status/phonon/PhononApplet.masterPrivate
					invokevirtual 168;		// setCurveParameters(Ljavacard/security/ECKey;)V
					getfield_a_this 19;		// reference im/status/phonon/PhononApplet.secp256k1
					getfield_a_this 36;		// reference im/status/phonon/PhononApplet.parentPublicKey
					invokevirtual 168;		// setCurveParameters(Ljavacard/security/ECKey;)V
					getfield_a_this 19;		// reference im/status/phonon/PhononApplet.secp256k1
					getfield_a_this 37;		// reference im/status/phonon/PhononApplet.parentPrivateKey
					invokevirtual 168;		// setCurveParameters(Ljavacard/security/ECKey;)V
					getfield_a_this 19;		// reference im/status/phonon/PhononApplet.secp256k1
					getfield_a_this 38;		// reference im/status/phonon/PhononApplet.publicKey
					invokevirtual 168;		// setCurveParameters(Ljavacard/security/ECKey;)V
					getfield_a_this 19;		// reference im/status/phonon/PhononApplet.secp256k1
					getfield_a_this 39;		// reference im/status/phonon/PhononApplet.privateKey
					invokevirtual 168;		// setCurveParameters(Ljavacard/security/ECKey;)V
					getfield_a_this 19;		// reference im/status/phonon/PhononApplet.secp256k1
					getfield_a_this 40;		// reference im/status/phonon/PhononApplet.pinlessPublicKey
					invokevirtual 168;		// setCurveParameters(Ljavacard/security/ECKey;)V
					getfield_a_this 19;		// reference im/status/phonon/PhononApplet.secp256k1
					getfield_a_this 41;		// reference im/status/phonon/PhononApplet.pinlessPrivateKey
					invokevirtual 168;		// setCurveParameters(Ljavacard/security/ECKey;)V
					return;
		}

		.method private processInit(Ljavacard/framework/APDU;)V {
			.stack 5;
			.locals 1;

			.descriptor	Ljavacard/framework/APDU;	1.10;

				L0:	aload_1;
					invokevirtual 112;		// getBuffer()[B
					astore_2;
				L1:	aload_1;
					invokevirtual 201;		// setIncomingAndReceive()S
					pop;
					aload_0;
					invokevirtual 116;		// selectingApplet()Z
					ifeq L3;
				L2:	aload_2;
					sconst_0;
					bspush -128;
					bastore;
					aload_2;
					sconst_1;
					getfield_a_this 20;		// reference im/status/phonon/PhononApplet.secureChannel
					aload_2;
					sconst_2;
					invokevirtual 199;		// copyPublicKey([BS)S
					s2b;
					bastore;
					aload_1;
					sconst_0;
					aload_2;
					sconst_1;
					baload;
					sconst_2;
					sadd;
					invokevirtual 154;		// setOutgoingAndSend(SS)V
					goto L9;
				L3:	aload_2;
					sconst_1;
					baload;
					bspush -2;
					if_scmpne L8;
				L4:	getfield_a_this 20;		// reference im/status/phonon/PhononApplet.secureChannel
					aload_2;
					invokevirtual 202;		// oneShotDecrypt([B)V
					aload_2;
					sconst_4;
					baload;
					bspush 38;
					if_scmpne L6;
				L5:	aload_0;
					aload_2;
					sconst_5;
					bspush 6;
					invokespecial 203;		// im/status/phonon/PhononApplet.allDigits([BSS)Z
					ifne L7;
				L6:	sspush 27264;
					invokestatic 226;		// javacard/framework/ISOException.throwIt(S)V
				L7:	invokestatic 172;		// javacard/framework/JCSystem.beginTransaction()V
					getfield_a_this 20;		// reference im/status/phonon/PhononApplet.secureChannel
					aload_2;
					bspush 11;
					invokevirtual 204;		// initSecureChannel([BS)V
					aload_0;
					new 205;		// javacard/framework/OwnerPIN
					dup;
					sconst_3;
					bspush 6;
					invokespecial 206;		// javacard/framework/OwnerPIN.<init>(BB)V
					putfield_a 56;		// reference im/status/phonon/PhononApplet.pin
					getfield_a_this 56;		// reference im/status/phonon/PhononApplet.pin
					aload_2;
					sconst_5;
					bspush 6;
					invokevirtual 207;		// update([BSB)V
					invokestatic 181;		// javacard/framework/JCSystem.commitTransaction()V
					getfield_a_this 19;		// reference im/status/phonon/PhononApplet.secp256k1
					getfield_a_this 53;		// reference im/status/phonon/PhononApplet.PhononKey
					invokevirtual 166;		// getPrivate()Ljavacard/security/PrivateKey;
					checkcast 0 167;		// T_CLASSORINTERFACE javacard/security/ECKey
					invokevirtual 168;		// setCurveParameters(Ljavacard/security/ECKey;)V
					getfield_a_this 19;		// reference im/status/phonon/PhononApplet.secp256k1
					getfield_a_this 53;		// reference im/status/phonon/PhononApplet.PhononKey
					invokevirtual 169;		// getPublic()Ljavacard/security/PublicKey;
					checkcast 0 167;		// T_CLASSORINTERFACE javacard/security/ECKey
					invokevirtual 168;		// setCurveParameters(Ljavacard/security/ECKey;)V
					goto L9;
				L8:	sspush 27904;
					invokestatic 226;		// javacard/framework/ISOException.throwIt(S)V
				L9:	return;
		}

		.method private allDigits([BSS)Z {
			.stack 3;
			.locals 1;

				L0:	goto L5;
				L1:	sinc 3 -1;
					aload_1;
					sload_2;
					sload_3;
					sadd;
					baload;
					sstore 4;
				L2:	sload 4;
					bspush 48;
					if_scmplt L4;
				L3:	sload 4;
					bspush 57;
					if_scmple L5;
				L4:	sconst_0;
					sreturn;
				L5:	sload_3;
					ifgt L1;
				L6:	sconst_1;
					sreturn;
		}

		.method private unpair(Ljavacard/framework/APDU;)V {
			.stack 2;
			.locals 1;

			.descriptor	Ljavacard/framework/APDU;	1.10;

				L0:	aload_1;
					invokevirtual 112;		// getBuffer()[B
					astore_2;
				L1:	getfield_a_this 20;		// reference im/status/phonon/PhononApplet.secureChannel
					aload_2;
					invokevirtual 170;		// preprocessAPDU([B)S
					pop;
					getfield_a_this 56;		// reference im/status/phonon/PhononApplet.pin
					invokevirtual 171;		// isValidated()Z
					ifeq L3;
				L2:	getfield_a_this 20;		// reference im/status/phonon/PhononApplet.secureChannel
					aload_2;
					invokevirtual 208;		// unpair([B)V
					goto L4;
				L3:	sspush 27013;
					invokestatic 226;		// javacard/framework/ISOException.throwIt(S)V
				L4:	return;
		}

		.method private verifyPIN(Ljavacard/framework/APDU;)V {
			.stack 4;
			.locals 2;

			.descriptor	Ljavacard/framework/APDU;	1.10;

				L0:	aload_1;
					invokevirtual 112;		// getBuffer()[B
					astore_2;
				L1:	getfield_a_this 20;		// reference im/status/phonon/PhononApplet.secureChannel
					aload_2;
					invokevirtual 170;		// preprocessAPDU([B)S
					s2b;
					sstore_3;
				L2:	getfield_a_this 56;		// reference im/status/phonon/PhononApplet.pin
					aload_2;
					sconst_5;
					sload_3;
					invokevirtual 209;		// check([BSB)Z
					ifne L4;
				L3:	sspush 25536;
					getfield_a_this 56;		// reference im/status/phonon/PhononApplet.pin
					invokevirtual 210;		// getTriesRemaining()B
					sor;
					invokestatic 226;		// javacard/framework/ISOException.throwIt(S)V
				L4:	return;
		}

		.method private changePIN(Ljavacard/framework/APDU;)V {
			.stack 3;
			.locals 2;

			.descriptor	Ljavacard/framework/APDU;	1.10;

				L0:	aload_1;
					invokevirtual 112;		// getBuffer()[B
					astore_2;
				L1:	getfield_a_this 20;		// reference im/status/phonon/PhononApplet.secureChannel
					aload_2;
					invokevirtual 170;		// preprocessAPDU([B)S
					s2b;
					sstore_3;
				L2:	getfield_a_this 56;		// reference im/status/phonon/PhononApplet.pin
					invokevirtual 171;		// isValidated()Z
					ifne L4;
				L3:	sspush 27013;
					invokestatic 226;		// javacard/framework/ISOException.throwIt(S)V
				L4:	aload_2;
					sconst_2;
					baload;
					stableswitch L7 0 2 L5 L7 L6;
				L5:	aload_0;
					aload_2;
					sload_3;
					invokespecial 211;		// im/status/phonon/PhononApplet.changeUserPIN([BB)V
					goto L8;
				L6:	aload_0;
					aload_2;
					sload_3;
					invokespecial 212;		// im/status/phonon/PhononApplet.changePairingSecret([BB)V
					goto L8;
				L7:	sspush 27270;
					invokestatic 226;		// javacard/framework/ISOException.throwIt(S)V
				L8:	return;
		}

		.method private changeUserPIN([BB)V {
			.stack 4;
			.locals 0;

				L0:	sload_2;
					bspush 6;
					if_scmpne L2;
				L1:	aload_0;
					aload_1;
					sconst_5;
					sload_2;
					invokespecial 203;		// im/status/phonon/PhononApplet.allDigits([BSS)Z
					ifne L3;
				L2:	sspush 27264;
					invokestatic 226;		// javacard/framework/ISOException.throwIt(S)V
				L3:	getfield_a_this 56;		// reference im/status/phonon/PhononApplet.pin
					aload_1;
					sconst_5;
					sload_2;
					invokevirtual 207;		// update([BSB)V
					getfield_a_this 56;		// reference im/status/phonon/PhononApplet.pin
					aload_1;
					sconst_5;
					sload_2;
					invokevirtual 209;		// check([BSB)Z
					pop;
					return;
		}

		.method private changePairingSecret([BB)V {
			.stack 3;
			.locals 0;

				L0:	sload_2;
					bspush 32;
					if_scmpeq L2;
				L1:	sspush 27264;
					invokestatic 226;		// javacard/framework/ISOException.throwIt(S)V
				L2:	getfield_a_this 20;		// reference im/status/phonon/PhononApplet.secureChannel
					aload_1;
					sconst_5;
					invokevirtual 213;		// updatePairingSecret([BB)V
					return;
		}

	}

	.class public SECP256k1 5 extends 0.0 {		// extends java/lang/Object

		.fields {
			private 2.22 ecPointMultiplier 0;		// Ljavacard/security/KeyAgreement;
			private Crypto crypto 1;		// Lim/status/phonon/Crypto;
			private 2.18 tmpECPrivateKey 2;		// Ljavacard/security/ECPrivateKey;
			static final byte[] SECP256K1_FP = {-1,-1,-1,-1,-1,-1,-1,-1,-1,-1,-1,-1,-1,-1,-1,-1,-1,-1,-1,-1,-1,-1,-1,-1,-1,-1,-1,-2,-1,-1,-4,47};		// [B
			static final byte[] SECP256K1_A = {0,0,0,0,0,0,0,0,0,0,0,0,0,0,0,0,0,0,0,0,0,0,0,0,0,0,0,0,0,0,0,0};		// [B
			static final byte[] SECP256K1_B = {0,0,0,0,0,0,0,0,0,0,0,0,0,0,0,0,0,0,0,0,0,0,0,0,0,0,0,0,0,0,0,7};		// [B
			static final byte[] SECP256K1_G = {4,121,-66,102,126,-7,-36,-69,-84,85,-96,98,-107,-50,-121,11,7,2,-101,-4,-37,45,-50,40,-39,89,-14,-127,91,22,-8,23,-104,72,58,-38,119,38,-93,-60,101,93,-92,-5,-4,14,17,8,-88,-3,23,-76,72,-90,-123,84,25,-100,71,-48,-113,-5,16,-44,-72};		// [B
			static final byte[] SECP256K1_R = {-1,-1,-1,-1,-1,-1,-1,-1,-1,-1,-1,-1,-1,-1,-1,-2,-70,-82,-36,-26,-81,72,-96,59,-65,-46,94,-116,-48,54,65,65};		// [B
			static final byte SECP256K1_K = 1;		// B
			static final short SECP256K1_KEY_SIZE = 256;		// S
			private static final byte ALG_EC_SVDP_DH_PLAIN_XY = 6;		// B
		}

		.publicMethodTable 1 {
			equals(Ljava/lang/Object;)Z;
		}

		.packageMethodTable 0 {
			setCurveParameters(Ljavacard/security/ECKey;)V;
			derivePublicKey(Ljavacard/security/ECPrivateKey;[BS)S;
			derivePublicKey([BS[BS)S;
			multiplyPoint(Ljavacard/security/ECPrivateKey;[BSS[BS)S;
		}

		.method  <init>(Lim/status/phonon/Crypto;)V {
			.stack 4;
			.locals 0;

				L0:	aload_0;
					invokespecial 102;		// java/lang/Object.<init>()V
					aload_0;
					aload_1;
					putfield_a 66;		// reference im/status/phonon/SECP256k1.crypto
					aload_0;
					bspush 6;
					sconst_0;
					invokestatic 114;		// javacard/security/KeyAgreement.getInstance(BZ)Ljavacard/security/KeyAgreement;
					putfield_a 67;		// reference im/status/phonon/SECP256k1.ecPointMultiplier
					aload_0;
					bspush 12;
					sspush 256;
					sconst_0;
					invokestatic 224;		// javacard/security/KeyBuilder.buildKey(BSZ)Ljavacard/security/Key;
					checkcast 0 235;		// T_CLASSORINTERFACE javacard/security/ECPrivateKey
					putfield_a 68;		// reference im/status/phonon/SECP256k1.tmpECPrivateKey
					aload_0;
					getfield_a_this 68;		// reference im/status/phonon/SECP256k1.tmpECPrivateKey
					invokevirtual 168;		// setCurveParameters(Ljavacard/security/ECKey;)V
					return;
		}

		.method  setCurveParameters(Ljavacard/security/ECKey;)V 128 {
			.stack 4;
			.locals 0;

			.descriptor	Ljavacard/security/ECKey;	2.17;

				L0:	aload_1;
					getstatic_a 217;		// reference im/status/phonon/SECP256k1.SECP256K1_A
					sconst_0;
					getstatic_a 217;		// reference im/status/phonon/SECP256k1.SECP256K1_A
					arraylength;
					invokeinterface 4 167 3;		// javacard/security/ECKey
					aload_1;
					getstatic_a 218;		// reference im/status/phonon/SECP256k1.SECP256K1_B
					sconst_0;
					getstatic_a 218;		// reference im/status/phonon/SECP256k1.SECP256K1_B
					arraylength;
					invokeinterface 4 167 4;		// javacard/security/ECKey
					aload_1;
					getstatic_a 219;		// reference im/status/phonon/SECP256k1.SECP256K1_FP
					sconst_0;
					getstatic_a 219;		// reference im/status/phonon/SECP256k1.SECP256K1_FP
					arraylength;
					invokeinterface 4 167 0;		// javacard/security/ECKey
					aload_1;
					getstatic_a 220;		// reference im/status/phonon/SECP256k1.SECP256K1_G
					sconst_0;
					getstatic_a 220;		// reference im/status/phonon/SECP256k1.SECP256K1_G
					arraylength;
					invokeinterface 4 167 5;		// javacard/security/ECKey
					aload_1;
					getstatic_a 238;		// reference im/status/phonon/SECP256k1.SECP256K1_R
					sconst_0;
					getstatic_a 238;		// reference im/status/phonon/SECP256k1.SECP256K1_R
					arraylength;
					invokeinterface 4 167 6;		// javacard/security/ECKey
					aload_1;
					sconst_1;
					invokeinterface 2 167 7;		// javacard/security/ECKey
					return;
		}

		.method  derivePublicKey(Ljavacard/security/ECPrivateKey;[BS)S 129 {
			.stack 7;
			.locals 0;

			.descriptor	Ljavacard/security/ECPrivateKey;	2.18;

				L0:	aload_0;
					aload_1;
					getstatic_a 220;		// reference im/status/phonon/SECP256k1.SECP256K1_G
					sconst_0;
					getstatic_a 220;		// reference im/status/phonon/SECP256k1.SECP256K1_G
					arraylength;
					aload_2;
					sload_3;
					invokevirtual 221;		// multiplyPoint(Ljavacard/security/ECPrivateKey;[BSS[BS)S
					sreturn;
		}

		.method  derivePublicKey([BS[BS)S 130 {
			.stack 4;
			.locals 0;

				L0:	getfield_a_this 68;		// reference im/status/phonon/SECP256k1.tmpECPrivateKey
					aload_1;
					sload_2;
					bspush 32;
					invokeinterface 4 235 18;		// javacard/security/ECPrivateKey
					aload_0;
					getfield_a_this 68;		// reference im/status/phonon/SECP256k1.tmpECPrivateKey
					aload_3;
					sload 4;
					invokevirtual 185;		// derivePublicKey(Ljavacard/security/ECPrivateKey;[BS)S
					sreturn;
		}

		.method  multiplyPoint(Ljavacard/security/ECPrivateKey;[BSS[BS)S 131 {
			.stack 6;
			.locals 0;

			.descriptor	Ljavacard/security/ECPrivateKey;	2.18;

				L0:	getfield_a_this 67;		// reference im/status/phonon/SECP256k1.ecPointMultiplier
					aload_1;
					invokevirtual 222;		// init(Ljavacard/security/PrivateKey;)V
					getfield_a_this 67;		// reference im/status/phonon/SECP256k1.ecPointMultiplier
					aload_2;
					sload_3;
					sload 4;
					aload 5;
					sload 6;
					invokevirtual 223;		// generateSecret([BSS[BS)S
					sreturn;
		}

	}

	.class public SecureChannel 6 extends 0.0 {		// extends java/lang/Object

		.fields {
			public byte[] SenderidCertificate 0;		// [B
			public byte[] CardAESIV 1;		// [B
			public byte[] CardHash 2;		// [B
			public byte[] CardsessionKey 3;		// [B
			public byte[] CardSecret 4;		// [B
			private 2.16 idKeypair 5;		// Ljavacard/security/KeyPair;
			private byte[] idCertificate 6;		// [B
			private 2.20 scEncKey 7;		// Ljavacard/security/AESKey;
			private 2.20 scMacKey 8;		// Ljavacard/security/AESKey;
			private 2.15 scMac 9;		// Ljavacard/security/Signature;
			private 2.16 scKeypair 10;		// Ljavacard/security/KeyPair;
			private 2.15 eccSig 11;		// Ljavacard/security/Signature;
			private byte[] secret 12;		// [B
			private byte[] pairingSecret 13;		// [B
			private 2.20 CardscEncKey 14;		// Ljavacard/security/AESKey;
			private 2.20 CardscMacKey 15;		// Ljavacard/security/AESKey;
			private byte[] Cardsecret 16;		// [B
			private byte[] SenderSalt 17;		// [B
			private SECP256k1 localsecp256k1 18;		// Lim/status/phonon/SECP256k1;
			private byte[] pairingKeys 19;		// [B
			private Crypto crypto 20;		// Lim/status/phonon/Crypto;
			private byte[] DebugMasterPrivateKey 21;		// [B
			private byte idCertStatus 22;		// B
			private short scCounter 23;		// S
			private byte CardidCertStatus 24;		// B
			private short preassignedPairingOffset 25;		// S
			private byte remainingSlots 26;		// B
			private boolean mutuallyAuthenticated 27;		// Z
			public static final byte ID_CERTIFICATE_EMPTY = 0;		// B
			public static final byte ID_CERTIFICATE_LOCKED = -1;		// B
			public static final boolean SECURE_CHANNEL_DEBUG = 1;		// Z
			public static final short SC_KEY_LENGTH = 256;		// S
			public static final short SC_SECRET_LENGTH = 32;		// S
			public static final short PAIRING_KEY_LENGTH = 33;		// S
			public static final short SC_BLOCK_SIZE = 16;		// S
			public static final short SC_OUT_OFFSET = 37;		// S
			public static final short SC_COUNTER_MAX = 100;		// S
			public static final byte INS_OPEN_SECURE_CHANNEL = 16;		// B
			public static final byte INS_MUTUALLY_AUTHENTICATE = 17;		// B
			public static final byte INS_PAIR = 18;		// B
			public static final byte INS_UNPAIR = 19;		// B
			public static final byte INS_IDENTIFY_CARD = 20;		// B
			public static final byte INS_LOAD_CERT = 21;		// B
			public static final byte PAIR_P1_FIRST_STEP = 0;		// B
			public static final byte PAIR_P1_LAST_STEP = 1;		// B
			public static final short SC_MAX_PLAIN_LENGTH = 223;		// S
			static final short ECDSA_MAX_LEN = 74;		// S
			static final short PUBKEY_LEN = 65;		// S
			static final short CERTIFICATE_MAX_LEN = 147;		// S
		}

		.publicMethodTable 1 {
			equals(Ljava/lang/Object;)Z;
			SetDebugKey()V;
			initSecureChannel([BS)V;
			oneShotDecrypt([B)V;
			openSecureChannel(Ljavacard/framework/APDU;)V;
			mutuallyAuthenticate(Ljavacard/framework/APDU;)V;
			loadCert(Ljavacard/framework/APDU;)V;
			SenderloadCert([BS)V;
			GetSenderSalt()[B;
			identifyCard(Ljavacard/framework/APDU;)V;
			pair(Ljavacard/framework/APDU;)V;
			GetKeyPair()Ljavacard/security/KeyPair;;
			GetCardCertificate([B)S;
			GetCardPublicKey([B)S;
			CardSenderpair([BS[B)V;
			CardSignSession([B)S;
			CardVerifySession([BS)Z;
			CardVerifySignature([BS)Z;
			CardGetAESIV()[B;
			unpair([B)V;
			GetCertStatus()B;
			preprocessAPDU([B)S;
			respond(Ljavacard/framework/APDU;SS)V;
			respond(Ljavacard/framework/APDU;[BSS)V;
			copyPublicKey([BS)S;
			isOpen()Z;
			getRemainingPairingSlots()B;
			updateSecureChannelCounter()V;
			reset()V;
			updatePairingSecret([BB)V;
			SetCardidCertStatus(B)V;
		}

		.packageMethodTable 0 {
			SetSenderSalt([B)V;
		}

		.method public <init>(BLim/status/phonon/Crypto;Lim/status/phonon/SECP256k1;)V 0 {
			.stack 5;
			.locals 0;

				L0:	aload_0;
					invokespecial 102;		// java/lang/Object.<init>()V
					aload_0;
					sconst_m1;
					putfield_s 69;		// short im/status/phonon/SecureChannel.preassignedPairingOffset
					aload_0;
					sconst_0;
					putfield_b 70;		// boolean im/status/phonon/SecureChannel.mutuallyAuthenticated
					aload_0;
					bspush 33;
					newarray 11;
					dup;
					sconst_1;
					bspush -112;
					bastore;
					dup;
					sconst_2;
					bspush -12;
					bastore;
					dup;
					sconst_3;
					bspush 85;
					bastore;
					dup;
					sconst_4;
					bspush 97;
					bastore;
					dup;
					sconst_5;
					bspush -75;
					bastore;
					dup;
					bspush 6;
					bspush -92;
					bastore;
					dup;
					bspush 7;
					bspush 61;
					bastore;
					dup;
					bspush 8;
					bspush -94;
					bastore;
					dup;
					bspush 9;
					bspush 127;
					bastore;
					dup;
					bspush 10;
					bspush 53;
					bastore;
					dup;
					bspush 11;
					bspush 112;
					bastore;
					dup;
					bspush 12;
					bspush 99;
					bastore;
					dup;
					bspush 13;
					bspush 72;
					bastore;
					dup;
					bspush 14;
					bspush -65;
					bastore;
					dup;
					bspush 15;
					bspush -122;
					bastore;
					dup;
					bspush 16;
					bspush -92;
					bastore;
					dup;
					bspush 17;
					bspush 117;
					bastore;
					dup;
					bspush 18;
					bspush -101;
					bastore;
					dup;
					bspush 19;
					bspush 35;
					bastore;
					dup;
					bspush 20;
					bspush -118;
					bastore;
					dup;
					bspush 21;
					bspush 88;
					bastore;
					dup;
					bspush 22;
					bspush -96;
					bastore;
					dup;
					bspush 23;
					bspush -19;
					bastore;
					dup;
					bspush 24;
					bspush -37;
					bastore;
					dup;
					bspush 25;
					bspush 36;
					bastore;
					dup;
					bspush 26;
					bspush 42;
					bastore;
					dup;
					bspush 27;
					bspush -94;
					bastore;
					dup;
					bspush 28;
					bspush 100;
					bastore;
					dup;
					bspush 29;
					bspush -48;
					bastore;
					dup;
					bspush 30;
					bspush -16;
					bastore;
					dup;
					bspush 31;
					bspush 47;
					bastore;
					dup;
					bspush 32;
					bspush 85;
					bastore;
					putfield_a 71;		// reference im/status/phonon/SecureChannel.DebugMasterPrivateKey
					aload_0;
					aload_2;
					putfield_a 72;		// reference im/status/phonon/SecureChannel.crypto
					aload_0;
					aload_3;
					putfield_a 73;		// reference im/status/phonon/SecureChannel.localsecp256k1
					aload_0;
					new 100;		// javacard/security/KeyPair
					dup;
					sconst_5;
					sspush 256;
					invokespecial 101;		// javacard/security/KeyPair.<init>(BS)V
					putfield_a 74;		// reference im/status/phonon/SecureChannel.idKeypair
					aload_3;
					getfield_a_this 74;		// reference im/status/phonon/SecureChannel.idKeypair
					invokevirtual 166;		// getPrivate()Ljavacard/security/PrivateKey;
					checkcast 0 167;		// T_CLASSORINTERFACE javacard/security/ECKey
					invokevirtual 168;		// setCurveParameters(Ljavacard/security/ECKey;)V
					aload_3;
					getfield_a_this 74;		// reference im/status/phonon/SecureChannel.idKeypair
					invokevirtual 169;		// getPublic()Ljavacard/security/PublicKey;
					checkcast 0 167;		// T_CLASSORINTERFACE javacard/security/ECKey
					invokevirtual 168;		// setCurveParameters(Ljavacard/security/ECKey;)V
					getfield_a_this 74;		// reference im/status/phonon/SecureChannel.idKeypair
					invokevirtual 174;		// genKeyPair()V
					aload_0;
					sspush 147;
					newarray 11;
					putfield_a 75;		// reference im/status/phonon/SecureChannel.idCertificate
					aload_0;
					sconst_0;
					putfield_b 76;		// byte im/status/phonon/SecureChannel.idCertStatus
					aload_0;
					sconst_0;
					putfield_b 77;		// byte im/status/phonon/SecureChannel.CardidCertStatus
					aload_0;
					bspush 18;
					sconst_0;
					invokestatic 227;		// javacard/security/Signature.getInstance(BZ)Ljavacard/security/Signature;
					putfield_a 78;		// reference im/status/phonon/SecureChannel.scMac
					aload_0;
					bspush 33;
					sconst_0;
					invokestatic 227;		// javacard/security/Signature.getInstance(BZ)Ljavacard/security/Signature;
					putfield_a 79;		// reference im/status/phonon/SecureChannel.eccSig
					aload_0;
					bspush 14;
					sspush 256;
					sconst_0;
					invokestatic 224;		// javacard/security/KeyBuilder.buildKey(BSZ)Ljavacard/security/Key;
					checkcast 0 225;		// T_CLASSORINTERFACE javacard/security/AESKey
					putfield_a 80;		// reference im/status/phonon/SecureChannel.scEncKey
					aload_0;
					bspush 14;
					sspush 256;
					sconst_0;
					invokestatic 224;		// javacard/security/KeyBuilder.buildKey(BSZ)Ljavacard/security/Key;
					checkcast 0 225;		// T_CLASSORINTERFACE javacard/security/AESKey
					putfield_a 81;		// reference im/status/phonon/SecureChannel.scMacKey
					aload_0;
					bspush 14;
					sspush 256;
					sconst_0;
					invokestatic 224;		// javacard/security/KeyBuilder.buildKey(BSZ)Ljavacard/security/Key;
					checkcast 0 225;		// T_CLASSORINTERFACE javacard/security/AESKey
					putfield_a 82;		// reference im/status/phonon/SecureChannel.CardscEncKey
					aload_0;
					bspush 14;
					sspush 256;
					sconst_0;
					invokestatic 224;		// javacard/security/KeyBuilder.buildKey(BSZ)Ljavacard/security/Key;
					checkcast 0 225;		// T_CLASSORINTERFACE javacard/security/AESKey
					putfield_a 83;		// reference im/status/phonon/SecureChannel.CardscMacKey
					aload_0;
					new 100;		// javacard/security/KeyPair
					dup;
					sconst_5;
					sspush 256;
					invokespecial 101;		// javacard/security/KeyPair.<init>(BS)V
					putfield_a 84;		// reference im/status/phonon/SecureChannel.scKeypair
					aload_3;
					getfield_a_this 84;		// reference im/status/phonon/SecureChannel.scKeypair
					invokevirtual 166;		// getPrivate()Ljavacard/security/PrivateKey;
					checkcast 0 167;		// T_CLASSORINTERFACE javacard/security/ECKey
					invokevirtual 168;		// setCurveParameters(Ljavacard/security/ECKey;)V
					aload_3;
					getfield_a_this 84;		// reference im/status/phonon/SecureChannel.scKeypair
					invokevirtual 169;		// getPublic()Ljavacard/security/PublicKey;
					checkcast 0 167;		// T_CLASSORINTERFACE javacard/security/ECKey
					invokevirtual 168;		// setCurveParameters(Ljavacard/security/ECKey;)V
					getfield_a_this 84;		// reference im/status/phonon/SecureChannel.scKeypair
					invokevirtual 174;		// genKeyPair()V
					aload_0;
					bspush 64;
					sconst_2;
					invokestatic 184;		// javacard/framework/JCSystem.makeTransientByteArray(SB)[B
					putfield_a 85;		// reference im/status/phonon/SecureChannel.secret
					aload_0;
					bspush 64;
					newarray 11;
					putfield_a 86;		// reference im/status/phonon/SecureChannel.CardsessionKey
					aload_0;
					bspush 33;
					sload_1;
					smul;
					newarray 11;
					putfield_a 87;		// reference im/status/phonon/SecureChannel.pairingKeys
					aload_0;
					sload_1;
					putfield_b 88;		// byte im/status/phonon/SecureChannel.remainingSlots
					aload_0;
					bspush 16;
					newarray 11;
					putfield_a 57;		// reference im/status/phonon/SecureChannel.CardAESIV
					aload_0;
					bspush 32;
					newarray 11;
					putfield_a 89;		// reference im/status/phonon/SecureChannel.SenderSalt
					aload_0;
					bspush 32;
					newarray 11;
					putfield_a 90;		// reference im/status/phonon/SecureChannel.CardHash
					aload_0;
					bspush 32;
					newarray 11;
					putfield_a 91;		// reference im/status/phonon/SecureChannel.CardSecret
					return;
		}

		.method public SetDebugKey()V 1 {
			.stack 4;
			.locals 4;

				L0:	getfield_a_this 74;		// reference im/status/phonon/SecureChannel.idKeypair
					invokevirtual 166;		// getPrivate()Ljavacard/security/PrivateKey;
					checkcast 0 235;		// T_CLASSORINTERFACE javacard/security/ECPrivateKey
					astore_1;
				L1:	aload_1;
					getfield_a_this 71;		// reference im/status/phonon/SecureChannel.DebugMasterPrivateKey
					sconst_0;
					bspush 32;
					invokeinterface 4 235 18;		// javacard/security/ECPrivateKey
					bspush 70;
					newarray 11;
					astore_2;
				L2:	getfield_a_this 73;		// reference im/status/phonon/SecureChannel.localsecp256k1
					aload_1;
					aload_2;
					sconst_0;
					invokevirtual 185;		// derivePublicKey(Ljavacard/security/ECPrivateKey;[BS)S
					sstore_3;
				L3:	getfield_a_this 74;		// reference im/status/phonon/SecureChannel.idKeypair
					invokevirtual 169;		// getPublic()Ljavacard/security/PublicKey;
					checkcast 0 233;		// T_CLASSORINTERFACE javacard/security/ECPublicKey
					astore 4;
				L4:	aload 4;
					aload_2;
					sconst_0;
					sload_3;
					invokeinterface 4 233 18;		// javacard/security/ECPublicKey
					return;
		}

		.method public initSecureChannel([BS)V 2 {
			.stack 5;
			.locals 0;

				L0:	getfield_a_this 92;		// reference im/status/phonon/SecureChannel.pairingSecret
					ifnull L2;
				L1:	return;
				L2:	aload_0;
					bspush 32;
					newarray 11;
					putfield_a 92;		// reference im/status/phonon/SecureChannel.pairingSecret
					aload_1;
					sload_2;
					getfield_a_this 92;		// reference im/status/phonon/SecureChannel.pairingSecret
					sconst_0;
					bspush 32;
					invokestatic 177;		// javacard/framework/Util.arrayCopy([BS[BSS)S
					pop;
					getfield_a_this 84;		// reference im/status/phonon/SecureChannel.scKeypair
					invokevirtual 174;		// genKeyPair()V
					return;
		}

		.method public oneShotDecrypt([B)V 3 {
			.stack 8;
			.locals 2;

				L0:	getfield_a_this 72;		// reference im/status/phonon/SecureChannel.crypto
					getfield_a 8;		// reference im/status/phonon/Crypto.ecdh
					getfield_a_this 84;		// reference im/status/phonon/SecureChannel.scKeypair
					invokevirtual 166;		// getPrivate()Ljavacard/security/PrivateKey;
					invokevirtual 222;		// init(Ljavacard/security/PrivateKey;)V
					bspush 6;
					sstore_2;
				L1:	getfield_a_this 72;		// reference im/status/phonon/SecureChannel.crypto
					getfield_a 8;		// reference im/status/phonon/Crypto.ecdh
					aload_1;
					sload_2;
					aload_1;
					sconst_5;
					baload;
					getfield_a_this 85;		// reference im/status/phonon/SecureChannel.secret
					sconst_0;
					invokevirtual 223;		// generateSecret([BSS[BS)S
					pop;
					sload_2;
					aload_1;
					sconst_5;
					baload;
					sadd;
					sstore_2;
				L2:	goto L5;
				L3:	astore_3;
				L4:	sspush 27264;
					invokestatic 226;		// javacard/framework/ISOException.throwIt(S)V
					return;
				L5:	getfield_a_this 80;		// reference im/status/phonon/SecureChannel.scEncKey
					getfield_a_this 85;		// reference im/status/phonon/SecureChannel.secret
					sconst_0;
					invokeinterface 3 225 4;		// javacard/security/AESKey
					getfield_a_this 72;		// reference im/status/phonon/SecureChannel.crypto
					getfield_a 11;		// reference im/status/phonon/Crypto.aesCbcIso9797m2
					getfield_a_this 80;		// reference im/status/phonon/SecureChannel.scEncKey
					sconst_1;
					aload_1;
					sload_2;
					bspush 16;
					invokevirtual 232;		// init(Ljavacard/security/Key;B[BSS)V
					sinc 2 16;
					aload_1;
					sconst_4;
					getfield_a_this 72;		// reference im/status/phonon/SecureChannel.crypto
					getfield_a 11;		// reference im/status/phonon/Crypto.aesCbcIso9797m2
					aload_1;
					sload_2;
					aload_1;
					sconst_4;
					baload;
					sspush 255;
					sand;
					sload_2;
					ssub;
					sconst_5;
					sadd;
					aload_1;
					sconst_5;
					invokevirtual 234;		// doFinal([BSS[BS)S
					s2b;
					bastore;
					return;
			.exceptionTable {
				// start_block end_block handler_block catch_type_index
				L1 L2 L3 111;
			}
		}

		.method public openSecureChannel(Ljavacard/framework/APDU;)V 4 {
			.stack 6;
			.locals 4;

			.descriptor	Ljavacard/framework/APDU;	1.10;

				L0:	aload_0;
					sconst_m1;
					putfield_s 69;		// short im/status/phonon/SecureChannel.preassignedPairingOffset
					aload_0;
					sconst_0;
					putfield_b 70;		// boolean im/status/phonon/SecureChannel.mutuallyAuthenticated
					aload_1;
					invokevirtual 112;		// getBuffer()[B
					astore_2;
				L1:	aload_0;
					aload_2;
					sconst_2;
					baload;
					invokespecial 248;		// im/status/phonon/SecureChannel.checkPairingIndexAndGetOffset(B)S
					sstore_3;
				L2:	getfield_a_this 87;		// reference im/status/phonon/SecureChannel.pairingKeys
					sload_3;
					baload;
					sconst_1;
					if_scmpeq L4;
				L3:	sspush 27270;
					invokestatic 226;		// javacard/framework/ISOException.throwIt(S)V
					goto L5;
				L4:	sinc 3 1;
				L5:	getfield_a_this 72;		// reference im/status/phonon/SecureChannel.crypto
					getfield_a 8;		// reference im/status/phonon/Crypto.ecdh
					getfield_a_this 84;		// reference im/status/phonon/SecureChannel.scKeypair
					invokevirtual 166;		// getPrivate()Ljavacard/security/PrivateKey;
					invokevirtual 222;		// init(Ljavacard/security/PrivateKey;)V
				L6:	getfield_a_this 72;		// reference im/status/phonon/SecureChannel.crypto
					getfield_a 8;		// reference im/status/phonon/Crypto.ecdh
					aload_2;
					sconst_5;
					aload_2;
					sconst_4;
					baload;
					getfield_a_this 85;		// reference im/status/phonon/SecureChannel.secret
					sconst_0;
					invokevirtual 223;		// generateSecret([BSS[BS)S
					sstore 4;
				L7:	goto L10;
				L8:	astore 5;
				L9:	sspush 27010;
					invokestatic 226;		// javacard/framework/ISOException.throwIt(S)V
					return;
				L10:	getfield_a_this 72;		// reference im/status/phonon/SecureChannel.crypto
					getfield_a 7;		// reference im/status/phonon/Crypto.random
					aload_2;
					sconst_0;
					bspush 48;
					invokevirtual 187;		// generateData([BSS)V
					getfield_a_this 72;		// reference im/status/phonon/SecureChannel.crypto
					getfield_a 9;		// reference im/status/phonon/Crypto.sha512
					getfield_a_this 85;		// reference im/status/phonon/SecureChannel.secret
					sconst_0;
					sload 4;
					invokevirtual 95;		// update([BSS)V
					getfield_a_this 72;		// reference im/status/phonon/SecureChannel.crypto
					getfield_a 9;		// reference im/status/phonon/Crypto.sha512
					getfield_a_this 87;		// reference im/status/phonon/SecureChannel.pairingKeys
					sload_3;
					bspush 32;
					invokevirtual 95;		// update([BSS)V
					getfield_a_this 72;		// reference im/status/phonon/SecureChannel.crypto
					getfield_a 9;		// reference im/status/phonon/Crypto.sha512
					aload_2;
					sconst_0;
					bspush 32;
					getfield_a_this 85;		// reference im/status/phonon/SecureChannel.secret
					sconst_0;
					invokevirtual 96;		// doFinal([BSS[BS)S
					pop;
					getfield_a_this 80;		// reference im/status/phonon/SecureChannel.scEncKey
					getfield_a_this 85;		// reference im/status/phonon/SecureChannel.secret
					sconst_0;
					invokeinterface 3 225 4;		// javacard/security/AESKey
					getfield_a_this 81;		// reference im/status/phonon/SecureChannel.scMacKey
					getfield_a_this 85;		// reference im/status/phonon/SecureChannel.secret
					bspush 32;
					invokeinterface 3 225 4;		// javacard/security/AESKey
					aload_2;
					bspush 32;
					getfield_a_this 85;		// reference im/status/phonon/SecureChannel.secret
					sconst_0;
					bspush 16;
					invokestatic 228;		// javacard/framework/Util.arrayCopyNonAtomic([BS[BSS)S
					pop;
					getfield_a_this 85;		// reference im/status/phonon/SecureChannel.secret
					bspush 16;
					getfield_a_this 85;		// reference im/status/phonon/SecureChannel.secret
					arraylength;
					bspush 16;
					ssub;
					sconst_0;
					invokestatic 249;		// javacard/framework/Util.arrayFillNonAtomic([BSSB)S
					pop;
					aload_1;
					sconst_0;
					bspush 48;
					invokevirtual 154;		// setOutgoingAndSend(SS)V
					return;
			.exceptionTable {
				// start_block end_block handler_block catch_type_index
				L6 L7 L8 111;
			}
		}

		.method public mutuallyAuthenticate(Ljavacard/framework/APDU;)V 5 {
			.stack 4;
			.locals 3;

			.descriptor	Ljavacard/framework/APDU;	1.10;

				L0:	getfield_a_this 80;		// reference im/status/phonon/SecureChannel.scEncKey
					invokeinterface 1 225 3;		// javacard/security/AESKey
					ifne L2;
				L1:	sspush 27013;
					invokestatic 226;		// javacard/framework/ISOException.throwIt(S)V
				L2:	getfield_b_this 70;		// boolean im/status/phonon/SecureChannel.mutuallyAuthenticated
					sstore_2;
				L3:	aload_0;
					sconst_1;
					putfield_b 70;		// boolean im/status/phonon/SecureChannel.mutuallyAuthenticated
					aload_1;
					invokevirtual 112;		// getBuffer()[B
					astore_3;
				L4:	aload_0;
					aload_3;
					invokevirtual 170;		// preprocessAPDU([B)S
					sstore 4;
				L5:	sload_2;
					ifeq L7;
				L6:	sspush 26753;
					invokestatic 226;		// javacard/framework/ISOException.throwIt(S)V
				L7:	sload 4;
					bspush 32;
					if_scmpeq L9;
				L8:	aload_0;
					invokevirtual 197;		// reset()V
					sspush 27010;
					invokestatic 226;		// javacard/framework/ISOException.throwIt(S)V
				L9:	getfield_a_this 72;		// reference im/status/phonon/SecureChannel.crypto
					getfield_a 7;		// reference im/status/phonon/Crypto.random
					aload_3;
					bspush 37;
					bspush 32;
					invokevirtual 187;		// generateData([BSS)V
					aload_0;
					aload_1;
					sload 4;
					sspush -28672;
					invokevirtual 144;		// respond(Ljavacard/framework/APDU;SS)V
					return;
		}

		.method public loadCert(Ljavacard/framework/APDU;)V 6 {
			.stack 6;
			.locals 1;

			.descriptor	Ljavacard/framework/APDU;	1.10;

				L0:	aload_1;
					invokevirtual 112;		// getBuffer()[B
					astore_2;
				L1:	getfield_b_this 76;		// byte im/status/phonon/SecureChannel.idCertStatus
					ifeq L3;
				L2:	sspush 27014;
					invokestatic 226;		// javacard/framework/ISOException.throwIt(S)V
				L3:	aload_2;
					sconst_4;
					baload;
					bspush -109;
					if_scmpgt L5;
				L4:	aload_2;
					sconst_5;
					getfield_a_this 75;		// reference im/status/phonon/SecureChannel.idCertificate
					sconst_0;
					aload_2;
					sconst_4;
					baload;
					sspush 255;
					sand;
					invokestatic 228;		// javacard/framework/Util.arrayCopyNonAtomic([BS[BSS)S
					pop;
					aload_0;
					sconst_m1;
					putfield_b 76;		// byte im/status/phonon/SecureChannel.idCertStatus
					goto L6;
				L5:	sspush 27012;
					invokestatic 226;		// javacard/framework/ISOException.throwIt(S)V
				L6:	return;
		}

		.method public SenderloadCert([BS)V 7 {
			.stack 5;
			.locals 0;

				L0:	getfield_b_this 77;		// byte im/status/phonon/SecureChannel.CardidCertStatus
					ifeq L2;
				L1:	sspush 27014;
					invokestatic 226;		// javacard/framework/ISOException.throwIt(S)V
				L2:	getfield_a_this 93;		// reference im/status/phonon/SecureChannel.SenderidCertificate
					ifnonnull L4;
				L3:	aload_0;
					sspush 147;
					sconst_2;
					invokestatic 184;		// javacard/framework/JCSystem.makeTransientByteArray(SB)[B
					putfield_a 93;		// reference im/status/phonon/SecureChannel.SenderidCertificate
				L4:	sload_2;
					sspush 147;
					if_scmple L6;
				L5:	sspush 27012;
					invokestatic 226;		// javacard/framework/ISOException.throwIt(S)V
					goto L7;
				L6:	aload_1;
					sconst_0;
					getfield_a_this 93;		// reference im/status/phonon/SecureChannel.SenderidCertificate
					sconst_0;
					sload_2;
					invokestatic 228;		// javacard/framework/Util.arrayCopyNonAtomic([BS[BSS)S
					pop;
					aload_0;
					sconst_m1;
					putfield_b 77;		// byte im/status/phonon/SecureChannel.CardidCertStatus
				L7:	return;
		}

		.method  SetSenderSalt([B)V 128 {
			.stack 5;
			.locals 0;

				L0:	aload_1;
					sconst_0;
					getfield_a_this 89;		// reference im/status/phonon/SecureChannel.SenderSalt
					sconst_0;
					bspush 32;
					invokestatic 228;		// javacard/framework/Util.arrayCopyNonAtomic([BS[BSS)S
					pop;
					return;
		}

		.method public GetSenderSalt()[B 8 {
			.stack 1;
			.locals 0;

				L0:	getfield_a_this 89;		// reference im/status/phonon/SecureChannel.SenderSalt
					areturn;
		}

		.method public identifyCard(Ljavacard/framework/APDU;)V 9 {
			.stack 6;
			.locals 6;

			.descriptor	Ljavacard/framework/APDU;	1.10;

				L0:	aload_1;
					invokevirtual 112;		// getBuffer()[B
					astore_2;
				L1:	aload_2;
					sconst_4;
					baload;
					bspush 32;
					if_scmpeq L3;
				L2:	sspush 27012;
					invokestatic 226;		// javacard/framework/ISOException.throwIt(S)V
				L3:	bspush 37;
					sstore_3;
				L4:	sload_3;
					sstore 4;
				L5:	getfield_a_this 74;		// reference im/status/phonon/SecureChannel.idKeypair
					invokevirtual 169;		// getPublic()Ljavacard/security/PublicKey;
					checkcast 0 233;		// T_CLASSORINTERFACE javacard/security/ECPublicKey
					astore 5;
				L6:	aload 5;
					aload_2;
					sload 4;
					sconst_2;
					sadd;
					invokeinterface 3 233 19;		// javacard/security/ECPublicKey
					sstore 6;
				L7:	aload_2;
					sload 4;
					dup;
					sconst_1;
					sadd;
					sstore 4;
					bspush -128;
					bastore;
					aload_2;
					sload 4;
					dup;
					sconst_1;
					sadd;
					sstore 4;
					sload 6;
					s2b;
					bastore;
					sload 4;
					sload 6;
					sadd;
					sstore 4;
					getfield_a_this 79;		// reference im/status/phonon/SecureChannel.eccSig
					getfield_a_this 74;		// reference im/status/phonon/SecureChannel.idKeypair
					invokevirtual 166;		// getPrivate()Ljavacard/security/PrivateKey;
					sconst_1;
					invokevirtual 246;		// init(Ljavacard/security/Key;B)V
					getfield_a_this 79;		// reference im/status/phonon/SecureChannel.eccSig
					aload_2;
					sconst_5;
					bspush 32;
					aload_2;
					sload 4;
					invokevirtual 250;		// signPreComputedHash([BSS[BS)S
					sstore 7;
				L8:	sload 4;
					sload 7;
					sadd;
					sstore 4;
					aload_1;
					sload_3;
					sload 4;
					sload_3;
					ssub;
					invokevirtual 154;		// setOutgoingAndSend(SS)V
					return;
		}

		.method public pair(Ljavacard/framework/APDU;)V 10 {
			.stack 3;
			.locals 2;

			.descriptor	Ljavacard/framework/APDU;	1.10;

				L0:	aload_0;
					invokevirtual 145;		// isOpen()Z
					ifeq L2;
				L1:	sspush 27013;
					invokestatic 226;		// javacard/framework/ISOException.throwIt(S)V
				L2:	aload_1;
					invokevirtual 112;		// getBuffer()[B
					astore_2;
				L3:	aload_2;
					sconst_2;
					baload;
					ifne L6;
				L4:	aload_0;
					aload_2;
					invokespecial 251;		// im/status/phonon/SecureChannel.pairStep1([B)S
					sstore_3;
				L5:	goto L11;
				L6:	aload_2;
					sconst_2;
					baload;
					sconst_1;
					if_scmpne L10;
				L7:	getfield_s_this 69;		// short im/status/phonon/SecureChannel.preassignedPairingOffset
					sconst_m1;
					if_scmpeq L10;
				L8:	aload_0;
					aload_2;
					invokespecial 252;		// im/status/phonon/SecureChannel.pairStep2([B)S
					sstore_3;
				L9:	goto L11;
				L10:	sspush 27270;
					invokestatic 226;		// javacard/framework/ISOException.throwIt(S)V
					return;
				L11:	aload_1;
					sconst_0;
					sload_3;
					invokevirtual 154;		// setOutgoingAndSend(SS)V
					return;
		}

		.method public GetKeyPair()Ljavacard/security/KeyPair; 11 {
			.stack 1;
			.locals 0;

			.descriptor	Ljavacard/security/KeyPair;	2.16;

				L0:	getfield_a_this 74;		// reference im/status/phonon/SecureChannel.idKeypair
					areturn;
		}

		.method public GetCardCertificate([B)S 12 {
			.stack 5;
			.locals 1;

				L0:	sconst_2;
					getfield_a_this 75;		// reference im/status/phonon/SecureChannel.idCertificate
					sconst_1;
					baload;
					sspush 255;
					sand;
					sadd;
					sstore_2;
				L1:	getfield_a_this 75;		// reference im/status/phonon/SecureChannel.idCertificate
					sconst_0;
					aload_1;
					sconst_0;
					sload_2;
					invokestatic 228;		// javacard/framework/Util.arrayCopyNonAtomic([BS[BSS)S
					pop;
					sload_2;
					sreturn;
		}

		.method public GetCardPublicKey([B)S 13 {
			.stack 3;
			.locals 2;

				L0:	getfield_a_this 74;		// reference im/status/phonon/SecureChannel.idKeypair
					invokevirtual 169;		// getPublic()Ljavacard/security/PublicKey;
					checkcast 0 233;		// T_CLASSORINTERFACE javacard/security/ECPublicKey
					astore_2;
				L1:	aload_2;
					aload_1;
					sconst_0;
					invokeinterface 3 233 19;		// javacard/security/ECPublicKey
					sstore_3;
				L2:	sload_3;
					sreturn;
		}

		.method private pairStep1([B)S {
			.stack 6;
			.locals 4;

				L0:	aload_1;
					sconst_4;
					baload;
					bspush 99;
					if_scmpeq L2;
				L1:	sspush 27264;
					invokestatic 226;		// javacard/framework/ISOException.throwIt(S)V
					sconst_0;
					sreturn;
				L2:	getfield_b_this 76;		// byte im/status/phonon/SecureChannel.idCertStatus
					sconst_m1;
					if_scmpeq L4;
				L3:	sspush 26754;
					invokestatic 226;		// javacard/framework/ISOException.throwIt(S)V
					sconst_0;
					sreturn;
				L4:	aload_0;
					sconst_0;
					putfield_s 69;		// short im/status/phonon/SecureChannel.preassignedPairingOffset
					bspush 37;
					sstore_2;
				L5:	getfield_a_this 72;		// reference im/status/phonon/SecureChannel.crypto
					getfield_a 8;		// reference im/status/phonon/Crypto.ecdh
					getfield_a_this 74;		// reference im/status/phonon/SecureChannel.idKeypair
					invokevirtual 166;		// getPrivate()Ljavacard/security/PrivateKey;
					invokevirtual 222;		// init(Ljavacard/security/PrivateKey;)V
					getfield_a_this 72;		// reference im/status/phonon/SecureChannel.crypto
					getfield_a 8;		// reference im/status/phonon/Crypto.ecdh
					aload_1;
					bspush 39;
					aload_1;
					bspush 38;
					baload;
					getfield_a_this 85;		// reference im/status/phonon/SecureChannel.secret
					sconst_0;
					invokevirtual 223;		// generateSecret([BSS[BS)S
					pop;
				L6:	goto L9;
				L7:	astore_3;
				L8:	sspush 27010;
					invokestatic 226;		// javacard/framework/ISOException.throwIt(S)V
					sconst_0;
					sreturn;
				L9:	getfield_a_this 72;		// reference im/status/phonon/SecureChannel.crypto
					getfield_a 10;		// reference im/status/phonon/Crypto.sha256
					aload_1;
					sconst_5;
					bspush 32;
					invokevirtual 95;		// update([BSS)V
					getfield_a_this 72;		// reference im/status/phonon/SecureChannel.crypto
					getfield_a 10;		// reference im/status/phonon/Crypto.sha256
					getfield_a_this 85;		// reference im/status/phonon/SecureChannel.secret
					sconst_0;
					bspush 32;
					getfield_a_this 85;		// reference im/status/phonon/SecureChannel.secret
					sconst_0;
					invokevirtual 96;		// doFinal([BSS[BS)S
					pop;
					sconst_0;
					sstore_3;
				L10:	getfield_a_this 72;		// reference im/status/phonon/SecureChannel.crypto
					getfield_a 7;		// reference im/status/phonon/Crypto.random
					aload_1;
					sload_3;
					bspush 32;
					invokevirtual 187;		// generateData([BSS)V
					sinc 3 32;
					sconst_2;
					getfield_a_this 75;		// reference im/status/phonon/SecureChannel.idCertificate
					sconst_1;
					baload;
					sspush 255;
					sand;
					sadd;
					sstore 4;
				L11:	getfield_a_this 75;		// reference im/status/phonon/SecureChannel.idCertificate
					sconst_0;
					aload_1;
					sload_3;
					sload 4;
					invokestatic 228;		// javacard/framework/Util.arrayCopyNonAtomic([BS[BSS)S
					pop;
					sload_3;
					sload 4;
					sadd;
					sstore_3;
					getfield_a_this 79;		// reference im/status/phonon/SecureChannel.eccSig
					getfield_a_this 74;		// reference im/status/phonon/SecureChannel.idKeypair
					invokevirtual 166;		// getPrivate()Ljavacard/security/PrivateKey;
					sconst_1;
					invokevirtual 246;		// init(Ljavacard/security/Key;B)V
					getfield_a_this 79;		// reference im/status/phonon/SecureChannel.eccSig
					getfield_a_this 85;		// reference im/status/phonon/SecureChannel.secret
					sconst_0;
					bspush 32;
					aload_1;
					sload_3;
					invokevirtual 250;		// signPreComputedHash([BSS[BS)S
					sstore 5;
				L12:	sload_3;
					sload 5;
					sadd;
					sstore_3;
					getfield_a_this 72;		// reference im/status/phonon/SecureChannel.crypto
					getfield_a 10;		// reference im/status/phonon/Crypto.sha256
					aload_1;
					sconst_0;
					bspush 32;
					invokevirtual 95;		// update([BSS)V
					getfield_a_this 72;		// reference im/status/phonon/SecureChannel.crypto
					getfield_a 10;		// reference im/status/phonon/Crypto.sha256
					getfield_a_this 85;		// reference im/status/phonon/SecureChannel.secret
					sconst_0;
					bspush 32;
					getfield_a_this 85;		// reference im/status/phonon/SecureChannel.secret
					bspush 32;
					invokevirtual 96;		// doFinal([BSS[BS)S
					pop;
					sload_3;
					sreturn;
			.exceptionTable {
				// start_block end_block handler_block catch_type_index
				L5 L6 L7 111;
			}
		}

		.method private pairStep2([B)S {
			.stack 7;
			.locals 0;

				L0:	aload_1;
					sconst_4;
					baload;
					bspush 32;
					if_scmpeq L2;
				L1:	sspush 27264;
					invokestatic 226;		// javacard/framework/ISOException.throwIt(S)V
				L2:	aload_1;
					sconst_5;
					getfield_a_this 85;		// reference im/status/phonon/SecureChannel.secret
					bspush 32;
					bspush 32;
					invokestatic 189;		// javacard/framework/Util.arrayCompare([BS[BSS)B
					ifeq L4;
				L3:	aload_0;
					sconst_m1;
					putfield_s 69;		// short im/status/phonon/SecureChannel.preassignedPairingOffset
					sspush 27010;
					invokestatic 226;		// javacard/framework/ISOException.throwIt(S)V
				L4:	getfield_a_this 72;		// reference im/status/phonon/SecureChannel.crypto
					getfield_a 7;		// reference im/status/phonon/Crypto.random
					aload_1;
					sconst_1;
					bspush 32;
					invokevirtual 187;		// generateData([BSS)V
					getfield_a_this 72;		// reference im/status/phonon/SecureChannel.crypto
					getfield_a 10;		// reference im/status/phonon/Crypto.sha256
					aload_1;
					sconst_1;
					bspush 32;
					invokevirtual 95;		// update([BSS)V
					getfield_a_this 72;		// reference im/status/phonon/SecureChannel.crypto
					getfield_a 10;		// reference im/status/phonon/Crypto.sha256
					getfield_a_this 85;		// reference im/status/phonon/SecureChannel.secret
					sconst_0;
					bspush 32;
					getfield_a_this 87;		// reference im/status/phonon/SecureChannel.pairingKeys
					getfield_s_this 69;		// short im/status/phonon/SecureChannel.preassignedPairingOffset
					sconst_1;
					sadd;
					invokevirtual 96;		// doFinal([BSS[BS)S
					pop;
					getfield_a_this 87;		// reference im/status/phonon/SecureChannel.pairingKeys
					getfield_s_this 69;		// short im/status/phonon/SecureChannel.preassignedPairingOffset
					sconst_1;
					bastore;
					aload_0;
					dup;
					getfield_b 88;		// byte im/status/phonon/SecureChannel.remainingSlots
					sconst_1;
					ssub;
					s2b;
					putfield_b 88;		// byte im/status/phonon/SecureChannel.remainingSlots
					aload_1;
					sconst_0;
					getfield_s_this 69;		// short im/status/phonon/SecureChannel.preassignedPairingOffset
					bspush 33;
					sdiv;
					s2b;
					bastore;
					aload_0;
					sconst_m1;
					putfield_s 69;		// short im/status/phonon/SecureChannel.preassignedPairingOffset
					bspush 33;
					sreturn;
		}

		.method public CardSenderpair([BS[B)V 14 {
			.stack 6;
			.locals 3;

				L0:	getfield_b_this 76;		// byte im/status/phonon/SecureChannel.idCertStatus
					sconst_m1;
					if_scmpeq L2;
				L1:	sspush 26754;
					invokestatic 226;		// javacard/framework/ISOException.throwIt(S)V
					return;
				L2:	getfield_a_this 72;		// reference im/status/phonon/SecureChannel.crypto
					getfield_a 8;		// reference im/status/phonon/Crypto.ecdh
					getfield_a_this 74;		// reference im/status/phonon/SecureChannel.idKeypair
					invokevirtual 166;		// getPrivate()Ljavacard/security/PrivateKey;
					invokevirtual 222;		// init(Ljavacard/security/PrivateKey;)V
					getfield_a_this 93;		// reference im/status/phonon/SecureChannel.SenderidCertificate
					sconst_3;
					baload;
					sstore 5;
				L3:	getfield_a_this 93;		// reference im/status/phonon/SecureChannel.SenderidCertificate
					sconst_5;
					sload 5;
					sadd;
					baload;
					sstore 6;
				L4:	getfield_a_this 72;		// reference im/status/phonon/SecureChannel.crypto
					getfield_a 8;		// reference im/status/phonon/Crypto.ecdh
					getfield_a_this 93;		// reference im/status/phonon/SecureChannel.SenderidCertificate
					bspush 6;
					sload 5;
					sadd;
					sload 6;
					getfield_a_this 91;		// reference im/status/phonon/SecureChannel.CardSecret
					sconst_0;
					invokevirtual 223;		// generateSecret([BSS[BS)S
					sstore 4;
				L5:	goto L8;
				L6:	astore 5;
				L7:	sspush 27010;
					invokestatic 226;		// javacard/framework/ISOException.throwIt(S)V
					return;
				L8:	getfield_a_this 72;		// reference im/status/phonon/SecureChannel.crypto
					getfield_a 9;		// reference im/status/phonon/Crypto.sha512
					aload_1;
					sconst_0;
					sload 4;
					invokevirtual 95;		// update([BSS)V
					getfield_a_this 72;		// reference im/status/phonon/SecureChannel.crypto
					getfield_a 9;		// reference im/status/phonon/Crypto.sha512
					aload_3;
					sconst_0;
					bspush 32;
					invokevirtual 95;		// update([BSS)V
					getfield_a_this 72;		// reference im/status/phonon/SecureChannel.crypto
					getfield_a 9;		// reference im/status/phonon/Crypto.sha512
					getfield_a_this 91;		// reference im/status/phonon/SecureChannel.CardSecret
					sconst_0;
					bspush 32;
					getfield_a_this 86;		// reference im/status/phonon/SecureChannel.CardsessionKey
					sconst_0;
					invokevirtual 96;		// doFinal([BSS[BS)S
					pop;
					getfield_a_this 82;		// reference im/status/phonon/SecureChannel.CardscEncKey
					getfield_a_this 86;		// reference im/status/phonon/SecureChannel.CardsessionKey
					sconst_0;
					invokeinterface 3 225 4;		// javacard/security/AESKey
					getfield_a_this 83;		// reference im/status/phonon/SecureChannel.CardscMacKey
					getfield_a_this 86;		// reference im/status/phonon/SecureChannel.CardsessionKey
					bspush 32;
					invokeinterface 3 225 4;		// javacard/security/AESKey
					return;
			.exceptionTable {
				// start_block end_block handler_block catch_type_index
				L2 L5 L6 111;
			}
		}

		.method public CardSignSession([B)S 15 {
			.stack 6;
			.locals 1;

				L0:	getfield_a_this 72;		// reference im/status/phonon/SecureChannel.crypto
					getfield_a 10;		// reference im/status/phonon/Crypto.sha256
					getfield_a_this 86;		// reference im/status/phonon/SecureChannel.CardsessionKey
					sconst_0;
					bspush 64;
					invokevirtual 95;		// update([BSS)V
					getfield_a_this 72;		// reference im/status/phonon/SecureChannel.crypto
					getfield_a 10;		// reference im/status/phonon/Crypto.sha256
					getfield_a_this 57;		// reference im/status/phonon/SecureChannel.CardAESIV
					sconst_0;
					bspush 16;
					getfield_a_this 90;		// reference im/status/phonon/SecureChannel.CardHash
					sconst_0;
					invokevirtual 96;		// doFinal([BSS[BS)S
					pop;
					getfield_a_this 79;		// reference im/status/phonon/SecureChannel.eccSig
					getfield_a_this 74;		// reference im/status/phonon/SecureChannel.idKeypair
					invokevirtual 166;		// getPrivate()Ljavacard/security/PrivateKey;
					sconst_1;
					invokevirtual 246;		// init(Ljavacard/security/Key;B)V
					getfield_a_this 79;		// reference im/status/phonon/SecureChannel.eccSig
					getfield_a_this 90;		// reference im/status/phonon/SecureChannel.CardHash
					sconst_0;
					bspush 32;
					aload_1;
					sconst_0;
					invokevirtual 250;		// signPreComputedHash([BSS[BS)S
					sstore_2;
				L1:	sload_2;
					sreturn;
		}

		.method public CardVerifySession([BS)Z 16 {
			.stack 8;
			.locals 5;

				L0:	getfield_a_this 72;		// reference im/status/phonon/SecureChannel.crypto
					getfield_a 10;		// reference im/status/phonon/Crypto.sha256
					getfield_a_this 86;		// reference im/status/phonon/SecureChannel.CardsessionKey
					sconst_0;
					bspush 64;
					invokevirtual 95;		// update([BSS)V
					getfield_a_this 72;		// reference im/status/phonon/SecureChannel.crypto
					getfield_a 10;		// reference im/status/phonon/Crypto.sha256
					getfield_a_this 57;		// reference im/status/phonon/SecureChannel.CardAESIV
					sconst_0;
					bspush 16;
					getfield_a_this 90;		// reference im/status/phonon/SecureChannel.CardHash
					sconst_0;
					invokevirtual 96;		// doFinal([BSS[BS)S
					pop;
					getfield_a_this 93;		// reference im/status/phonon/SecureChannel.SenderidCertificate
					sconst_3;
					baload;
					sstore_3;
				L1:	getfield_a_this 93;		// reference im/status/phonon/SecureChannel.SenderidCertificate
					sconst_5;
					sload_3;
					sadd;
					baload;
					sstore 4;
				L2:	new 100;		// javacard/security/KeyPair
					dup;
					sconst_5;
					sspush 256;
					invokespecial 101;		// javacard/security/KeyPair.<init>(BS)V
					astore 5;
				L3:	getfield_a_this 73;		// reference im/status/phonon/SecureChannel.localsecp256k1
					aload 5;
					invokevirtual 166;		// getPrivate()Ljavacard/security/PrivateKey;
					checkcast 0 167;		// T_CLASSORINTERFACE javacard/security/ECKey
					invokevirtual 168;		// setCurveParameters(Ljavacard/security/ECKey;)V
					getfield_a_this 73;		// reference im/status/phonon/SecureChannel.localsecp256k1
					aload 5;
					invokevirtual 169;		// getPublic()Ljavacard/security/PublicKey;
					checkcast 0 167;		// T_CLASSORINTERFACE javacard/security/ECKey
					invokevirtual 168;		// setCurveParameters(Ljavacard/security/ECKey;)V
					aload 5;
					invokevirtual 174;		// genKeyPair()V
					aload 5;
					invokevirtual 169;		// getPublic()Ljavacard/security/PublicKey;
					checkcast 0 233;		// T_CLASSORINTERFACE javacard/security/ECPublicKey
					astore 6;
				L4:	getfield_a_this 73;		// reference im/status/phonon/SecureChannel.localsecp256k1
					aload 6;
					invokevirtual 168;		// setCurveParameters(Ljavacard/security/ECKey;)V
					aload 6;
					getfield_a_this 93;		// reference im/status/phonon/SecureChannel.SenderidCertificate
					bspush 6;
					sload_3;
					sadd;
					sload 4;
					invokeinterface 4 233 18;		// javacard/security/ECPublicKey
					getfield_a_this 79;		// reference im/status/phonon/SecureChannel.eccSig
					aload 6;
					sconst_2;
					invokevirtual 246;		// init(Ljavacard/security/Key;B)V
					getfield_a_this 79;		// reference im/status/phonon/SecureChannel.eccSig
					getfield_a_this 90;		// reference im/status/phonon/SecureChannel.CardHash
					sconst_0;
					bspush 32;
					aload_1;
					sconst_0;
					aload_1;
					sconst_1;
					baload;
					sconst_2;
					sadd;
					invokevirtual 253;		// verify([BSS[BSS)Z
					sstore 7;
				L5:	sload 7;
					sreturn;
		}

		.method public CardVerifySignature([BS)Z 17 {
			.stack 7;
			.locals 1;

				L0:	getfield_a_this 79;		// reference im/status/phonon/SecureChannel.eccSig
					getfield_a_this 74;		// reference im/status/phonon/SecureChannel.idKeypair
					invokevirtual 169;		// getPublic()Ljavacard/security/PublicKey;
					checkcast 0 233;		// T_CLASSORINTERFACE javacard/security/ECPublicKey
					sconst_2;
					invokevirtual 246;		// init(Ljavacard/security/Key;B)V
					getfield_a_this 79;		// reference im/status/phonon/SecureChannel.eccSig
					getfield_a_this 90;		// reference im/status/phonon/SecureChannel.CardHash
					sconst_0;
					bspush 32;
					aload_1;
					sconst_0;
					sload_2;
					invokevirtual 253;		// verify([BSS[BSS)Z
					sstore_3;
				L1:	sload_3;
					sreturn;
		}

		.method public CardGetAESIV()[B 18 {
			.stack 1;
			.locals 0;

				L0:	getfield_a_this 57;		// reference im/status/phonon/SecureChannel.CardAESIV
					areturn;
		}

		.method public unpair([B)V 19 {
			.stack 4;
			.locals 1;

				L0:	aload_0;
					aload_1;
					sconst_2;
					baload;
					invokespecial 248;		// im/status/phonon/SecureChannel.checkPairingIndexAndGetOffset(B)S
					sstore_2;
				L1:	getfield_a_this 87;		// reference im/status/phonon/SecureChannel.pairingKeys
					sload_2;
					baload;
					sconst_1;
					if_scmpne L3;
				L2:	getfield_a_this 87;		// reference im/status/phonon/SecureChannel.pairingKeys
					sload_2;
					bspush 33;
					sconst_0;
					invokestatic 249;		// javacard/framework/Util.arrayFillNonAtomic([BSSB)S
					pop;
					aload_0;
					dup;
					getfield_b 88;		// byte im/status/phonon/SecureChannel.remainingSlots
					sconst_1;
					sadd;
					s2b;
					putfield_b 88;		// byte im/status/phonon/SecureChannel.remainingSlots
				L3:	return;
		}

		.method public GetCertStatus()B 20 {
			.stack 1;
			.locals 0;

				L0:	getfield_b_this 76;		// byte im/status/phonon/SecureChannel.idCertStatus
					sreturn;
		}

		.method public preprocessAPDU([B)S 21 {
			.stack 6;
			.locals 2;

				L0:	aload_0;
					invokevirtual 145;		// isOpen()Z
					ifne L2;
				L1:	sspush 27013;
					invokestatic 226;		// javacard/framework/ISOException.throwIt(S)V
				L2:	aload_1;
					sconst_4;
					baload;
					sspush 255;
					sand;
					sstore_2;
				L3:	aload_0;
					aload_1;
					sload_2;
					invokespecial 254;		// im/status/phonon/SecureChannel.verifyAESMAC([BS)Z
					ifne L5;
				L4:	aload_0;
					invokevirtual 197;		// reset()V
					sspush 27010;
					invokestatic 226;		// javacard/framework/ISOException.throwIt(S)V
				L5:	getfield_a_this 72;		// reference im/status/phonon/SecureChannel.crypto
					getfield_a 11;		// reference im/status/phonon/Crypto.aesCbcIso9797m2
					getfield_a_this 80;		// reference im/status/phonon/SecureChannel.scEncKey
					sconst_1;
					getfield_a_this 85;		// reference im/status/phonon/SecureChannel.secret
					sconst_0;
					bspush 16;
					invokevirtual 232;		// init(Ljavacard/security/Key;B[BSS)V
					aload_1;
					sconst_5;
					getfield_a_this 85;		// reference im/status/phonon/SecureChannel.secret
					sconst_0;
					bspush 16;
					invokestatic 228;		// javacard/framework/Util.arrayCopyNonAtomic([BS[BSS)S
					pop;
					getfield_a_this 72;		// reference im/status/phonon/SecureChannel.crypto
					getfield_a 11;		// reference im/status/phonon/Crypto.aesCbcIso9797m2
					aload_1;
					bspush 21;
					sload_2;
					bspush 16;
					ssub;
					aload_1;
					sconst_5;
					invokevirtual 234;		// doFinal([BSS[BS)S
					sstore_3;
				L6:	aload_1;
					sconst_4;
					sload_3;
					s2b;
					bastore;
					sload_3;
					sreturn;
		}

		.method private verifyAESMAC([BS)Z {
			.stack 7;
			.locals 0;

				L0:	getfield_a_this 78;		// reference im/status/phonon/SecureChannel.scMac
					getfield_a_this 81;		// reference im/status/phonon/SecureChannel.scMacKey
					sconst_2;
					invokevirtual 246;		// init(Ljavacard/security/Key;B)V
					getfield_a_this 78;		// reference im/status/phonon/SecureChannel.scMac
					aload_1;
					sconst_0;
					sconst_5;
					invokevirtual 255;		// update([BSS)V
					getfield_a_this 78;		// reference im/status/phonon/SecureChannel.scMac
					getfield_a_this 85;		// reference im/status/phonon/SecureChannel.secret
					bspush 16;
					bspush 11;
					invokevirtual 255;		// update([BSS)V
					getfield_a_this 78;		// reference im/status/phonon/SecureChannel.scMac
					aload_1;
					bspush 21;
					sload_2;
					bspush 16;
					ssub;
					aload_1;
					sconst_5;
					bspush 16;
					invokevirtual 253;		// verify([BSS[BSS)Z
					sreturn;
		}

		.method public respond(Ljavacard/framework/APDU;SS)V 22 {
			.stack 6;
			.locals 1;

			.descriptor	Ljavacard/framework/APDU;	1.10;

				L0:	aload_1;
					invokevirtual 112;		// getBuffer()[B
					astore 4;
				L1:	aload 4;
					bspush 37;
					sload_2;
					sadd;
					sload_3;
					invokestatic 230;		// javacard/framework/Util.setShort([BSS)S
					pop;
					sinc 2 2;
					getfield_a_this 72;		// reference im/status/phonon/SecureChannel.crypto
					getfield_a 11;		// reference im/status/phonon/Crypto.aesCbcIso9797m2
					getfield_a_this 80;		// reference im/status/phonon/SecureChannel.scEncKey
					sconst_2;
					getfield_a_this 85;		// reference im/status/phonon/SecureChannel.secret
					sconst_0;
					bspush 16;
					invokevirtual 232;		// init(Ljavacard/security/Key;B[BSS)V
					getfield_a_this 72;		// reference im/status/phonon/SecureChannel.crypto
					getfield_a 11;		// reference im/status/phonon/Crypto.aesCbcIso9797m2
					aload 4;
					bspush 37;
					sload_2;
					aload 4;
					bspush 21;
					invokevirtual 234;		// doFinal([BSS[BS)S
					sstore_2;
					aload 4;
					sconst_0;
					sload_2;
					bspush 16;
					sadd;
					s2b;
					bastore;
					aload_0;
					sload_2;
					aload 4;
					invokespecial 256;		// im/status/phonon/SecureChannel.computeAESMAC(S[B)V
					aload 4;
					sconst_5;
					getfield_a_this 85;		// reference im/status/phonon/SecureChannel.secret
					sconst_0;
					bspush 16;
					invokestatic 228;		// javacard/framework/Util.arrayCopyNonAtomic([BS[BSS)S
					pop;
					sinc 2 16;
					aload_1;
					sconst_5;
					sload_2;
					invokevirtual 154;		// setOutgoingAndSend(SS)V
					return;
		}

		.method public respond(Ljavacard/framework/APDU;[BSS)V 23 {
			.stack 5;
			.locals 1;

			.descriptor	Ljavacard/framework/APDU;	1.10;

				L0:	aload_1;
					invokevirtual 112;		// getBuffer()[B
					astore 5;
				L1:	aload_2;
					sconst_0;
					aload 5;
					bspush 37;
					sload_3;
					invokestatic 228;		// javacard/framework/Util.arrayCopyNonAtomic([BS[BSS)S
					pop;
					aload_0;
					aload_1;
					sload_3;
					sload 4;
					invokevirtual 144;		// respond(Ljavacard/framework/APDU;SS)V
					return;
		}

		.method private computeAESMAC(S[B)V {
			.stack 6;
			.locals 0;

				L0:	getfield_a_this 78;		// reference im/status/phonon/SecureChannel.scMac
					getfield_a_this 81;		// reference im/status/phonon/SecureChannel.scMacKey
					sconst_1;
					invokevirtual 246;		// init(Ljavacard/security/Key;B)V
					getfield_a_this 78;		// reference im/status/phonon/SecureChannel.scMac
					aload_2;
					sconst_0;
					sconst_1;
					invokevirtual 255;		// update([BSS)V
					getfield_a_this 78;		// reference im/status/phonon/SecureChannel.scMac
					getfield_a_this 85;		// reference im/status/phonon/SecureChannel.secret
					bspush 16;
					bspush 15;
					invokevirtual 255;		// update([BSS)V
					getfield_a_this 78;		// reference im/status/phonon/SecureChannel.scMac
					aload_2;
					bspush 21;
					sload_1;
					aload_2;
					sconst_5;
					invokevirtual 247;		// sign([BSS[BS)S
					pop;
					return;
		}

		.method public copyPublicKey([BS)S 24 {
			.stack 3;
			.locals 1;

				L0:	getfield_a_this 84;		// reference im/status/phonon/SecureChannel.scKeypair
					invokevirtual 169;		// getPublic()Ljavacard/security/PublicKey;
					checkcast 0 233;		// T_CLASSORINTERFACE javacard/security/ECPublicKey
					astore_3;
				L1:	aload_3;
					aload_1;
					sload_2;
					invokeinterface 3 233 19;		// javacard/security/ECPublicKey
					sreturn;
		}

		.method public isOpen()Z 25 {
			.stack 1;
			.locals 0;

				L0:	getfield_a_this 80;		// reference im/status/phonon/SecureChannel.scEncKey
					invokeinterface 1 225 3;		// javacard/security/AESKey
					ifeq L4;
				L1:	getfield_a_this 81;		// reference im/status/phonon/SecureChannel.scMacKey
					invokeinterface 1 225 3;		// javacard/security/AESKey
					ifeq L4;
				L2:	getfield_b_this 70;		// boolean im/status/phonon/SecureChannel.mutuallyAuthenticated
					ifeq L4;
				L3:	sconst_1;
					sreturn;
				L4:	sconst_0;
					sreturn;
		}

		.method public getRemainingPairingSlots()B 26 {
			.stack 1;
			.locals 0;

				L0:	getfield_b_this 88;		// byte im/status/phonon/SecureChannel.remainingSlots
					sreturn;
		}

		.method public updateSecureChannelCounter()V 27 {
			.stack 3;
			.locals 0;

				L0:	getfield_s_this 94;		// short im/status/phonon/SecureChannel.scCounter
					bspush 100;
					if_scmpge L2;
				L1:	aload_0;
					dup;
					getfield_s 94;		// short im/status/phonon/SecureChannel.scCounter
					sconst_1;
					sadd;
					putfield_s 94;		// short im/status/phonon/SecureChannel.scCounter
					goto L3;
				L2:	getfield_a_this 84;		// reference im/status/phonon/SecureChannel.scKeypair
					invokevirtual 174;		// genKeyPair()V
					aload_0;
					sconst_0;
					putfield_s 94;		// short im/status/phonon/SecureChannel.scCounter
				L3:	return;
		}

		.method public reset()V 28 {
			.stack 2;
			.locals 0;

				L0:	getfield_a_this 80;		// reference im/status/phonon/SecureChannel.scEncKey
					invokeinterface 1 225 0;		// javacard/security/AESKey
					getfield_a_this 81;		// reference im/status/phonon/SecureChannel.scMacKey
					invokeinterface 1 225 0;		// javacard/security/AESKey
					aload_0;
					sconst_0;
					putfield_b 70;		// boolean im/status/phonon/SecureChannel.mutuallyAuthenticated
					aload_0;
					sconst_0;
					putfield_b 77;		// byte im/status/phonon/SecureChannel.CardidCertStatus
					return;
		}

		.method public updatePairingSecret([BB)V 29 {
			.stack 5;
			.locals 0;

				L0:	aload_1;
					sload_2;
					getfield_a_this 92;		// reference im/status/phonon/SecureChannel.pairingSecret
					sconst_0;
					bspush 32;
					invokestatic 177;		// javacard/framework/Util.arrayCopy([BS[BSS)S
					pop;
					return;
		}

		.method private checkPairingIndexAndGetOffset(B)S {
			.stack 2;
			.locals 1;

				L0:	sload_1;
					bspush 33;
					smul;
					sstore_2;
				L1:	sload_2;
					getfield_a_this 87;		// reference im/status/phonon/SecureChannel.pairingKeys
					arraylength;
					if_scmplt L3;
				L2:	sspush 27270;
					invokestatic 226;		// javacard/framework/ISOException.throwIt(S)V
				L3:	sload_2;
					sreturn;
		}

		.method public SetCardidCertStatus(B)V 30 {
			.stack 2;
			.locals 0;

				L0:	aload_0;
					sload_1;
					putfield_b 77;		// byte im/status/phonon/SecureChannel.CardidCertStatus
					return;
		}

	}

	.class  SharedMemory extends 0.0 {		// extends java/lang/Object

		.fields {
			static final byte[] ndefDataFile = {0,0,0,0,0,0,0,0,0,0,0,0,0,0,0,0,0,0,0,0,0,0,0,0,0,0,0,0,0,0,0,0,0,0,0,0,0,0,0,0,0,0,0,0,0,0,0,0,0,0,0,0,0,0,0,0,0,0,0,0,0,0,0,0,0,0,0,0,0,0,0,0,0,0,0,0,0,0,0,0,0,0,0,0,0,0,0,0,0,0,0,0,0,0,0,0,0,0,0,0,0,0,0,0,0,0,0,0,0,0,0,0,0,0,0,0,0,0,0,0,0,0,0,0,0,0,0,0,0,0,0,0,0,0,0,0,0,0,0,0,0,0,0,0,0,0,0,0,0,0,0,0,0,0,0,0,0,0,0,0,0,0,0,0,0,0,0,0,0,0,0,0,0,0,0,0,0,0,0,0,0,0,0,0,0,0,0,0,0,0,0,0,0,0,0,0,0,0,0,0,0,0,0,0,0,0,0,0,0,0,0,0,0,0,0,0,0,0,0,0,0,0,0};		// [B
		}

		.publicMethodTable 1 {
			equals(Ljava/lang/Object;)Z;
		}

		.packageMethodTable 0 {
		}

		.method  <init>()V {
			.stack 1;
			.locals 0;

				L0:	aload_0;
					invokespecial 102;		// java/lang/Object.<init>()V
					return;
		}

	}

}
